Workbook

Sheet Valores
A1: Categoría Mensaje | D1: Tipo de Mensaje | G1: Modelo
A2: Categoría | B2: Código | D2: Tipo de Mensaje | E2: Código | G2: Nombre Modelo | H2: Código
A3: Información | B3: INF | D3: Usuario final | E3: USU | G3: General | H3: GEN
A4: Éxito | B4: EXI | D4: Técnico | E4: TEC | G4: Usuario | H4: MOD_1
A5: Advertencia | B5: ADV | G5: Login | H5: MOD_2
A6: Confirmación | B6: CON | G6: Pago | H6: MOD_3
A7: Error | B7: ERR | G7: Abastecimiento | H7: MOD_4
A8: Fatal | B8: FAT | G8: Insumo | H8: MOD_5
G9: Cliente | H9: MOD_6
G10: Sede | H10: MOD_7
G11: Devolución | H11: MOD_8
G12: Venta | H12: MOD_9
G13: Envio | H13: MOD_10
G14: Producto | H14: MOD_11
G15: Produccion | H15: MOD_12
G16: Proveedor | H16: MOD_13
G17: Categoria | H17: MOD_14
G18: Persona | H18: MOD_15

Sheet Catálogo mensajes
A1: Modelo | B1: Número Mensaje | C1: Número Mensaje | D1: Código mensaje | E1: Tipo | F1: Categoría Mensaje | G1: Título Mensaje | H1: Contenido Mensaje | I1: Parámetros
A2: Usuario | B2: 1 | C2: =RIGHT("0000"&B2,5) -> 00001 | D2: =IF(AND(EXACT(LEN(TRIM(H2)),0), EXACT(LEN(TRIM(G2)),0)),"",A2&"_"&VLOOKUP(E2,Valores!$D$3:$E$4,2,FALSE)&"_"&VLOOKUP(F2,Valores!$A$3:$B$8,2,FALSE)&"_"&C2) -> Usuario_USU_EXI_00001 | E2: Usuario final | F2: Éxito | G2: ¡Usuario registrado de forma exitosa! | H2: ¡El usuario “${0}” ha sido registrado de forma exitosa! | I2: ${0}: Usuario (login) registrado
A3: General | B3: 2 | C3: =RIGHT("0000"&B3,5) -> 00002 | D3: =IF(AND(EXACT(LEN(TRIM(H3)),0), EXACT(LEN(TRIM(G3)),0)),"",A3&"_"&VLOOKUP(E3,Valores!$D$3:$E$4,2,FALSE)&"_"&VLOOKUP(F3,Valores!$A$3:$B$8,2,FALSE)&"_"&C3) -> General_USU_INF_00002 | E3: Usuario final | F3: Información | G3: ¡Usuario ya registrado! | H3: ¡El usuario con identificación “${0}” ya ha sido registrado! | I3: ${0}: Número de identificación
A4: General | B4: 3 | C4: =RIGHT("0000"&B4,5) -> 00003 | D4: =IF(AND(EXACT(LEN(TRIM(H4)),0), EXACT(LEN(TRIM(G4)),0)),"",A4&"_"&VLOOKUP(E4,Valores!$D$3:$E$4,2,FALSE)&"_"&VLOOKUP(F4,Valores!$A$3:$B$8,2,FALSE)&"_"&C4) -> General_USU_INF_00003 | E4: Usuario final | F4: Información | G4: ¡Usuario ya registrado! | H4: ¡El usuario con correo electrónico “${0}” ya ha sido registrado! | I4: ${0}: Correo electrónico
A5: Usuario | B5: 4 | C5: =RIGHT("0000"&B5,5) -> 00004 | D5: =IF(AND(EXACT(LEN(TRIM(H5)),0), EXACT(LEN(TRIM(G5)),0)),"",A5&"_"&VLOOKUP(E5,Valores!$D$3:$E$4,2,FALSE)&"_"&VLOOKUP(F5,Valores!$A$3:$B$8,2,FALSE)&"_"&C5) -> Usuario_USU_INF_00004 | E5: Usuario final | F5: Información | G5: ¡Usuario ya registrado! | H5: ¡El usuario con nombre de inicio de sesión “${0}” ya existe. Elige otro! | I5: ${0}: Usuario (login)
A6: General | B6: 5 | C6: =RIGHT("0000"&B6,5) -> 00005 | D6: =IF(AND(EXACT(LEN(TRIM(H6)),0), EXACT(LEN(TRIM(G6)),0)),"",A6&"_"&VLOOKUP(E6,Valores!$D$3:$E$4,2,FALSE)&"_"&VLOOKUP(F6,Valores!$A$3:$B$8,2,FALSE)&"_"&C6) -> General_TEC_ERR_00005 | E6: Técnico | F6: Error | G6: Conflicto de unicidad | H6: No fue posible registrar: los siguientes campos deben ser únicos y ya existen: ${0}. | I6: ${0}: Lista de campos en conflicto (p. ej., “Numero_Identificacion, Correo”)
A7: General | B7: 6 | C7: =RIGHT("0000"&B7,5) -> 00006 | D7: =IF(AND(EXACT(LEN(TRIM(H7)),0), EXACT(LEN(TRIM(G7)),0)),"",A7&"_"&VLOOKUP(E7,Valores!$D$3:$E$4,2,FALSE)&"_"&VLOOKUP(F7,Valores!$A$3:$B$8,2,FALSE)&"_"&C7) -> General_USU_ERR_00006 | E7: Usuario final | F7: Error | G7: Dato requerido no diligenciado | H7: Debes registrar un valor para “${0}”, el cual es obligatorio. | I7: ${0}: Nombre del campo obligatorio
A8: General | B8: 7 | C8: =RIGHT("0000"&B8,5) -> 00007 | D8: =IF(AND(EXACT(LEN(TRIM(H8)),0), EXACT(LEN(TRIM(G8)),0)),"",A8&"_"&VLOOKUP(E8,Valores!$D$3:$E$4,2,FALSE)&"_"&VLOOKUP(F8,Valores!$A$3:$B$8,2,FALSE)&"_"&C8) -> General_USU_ERR_00007 | E8: Usuario final | F8: Error | G8: Longitud máxima excedida | H8: El campo “${0}” supera la longitud máxima permitida (${1} caracteres). | I8: ${0}: Campo; ${1}: Longitud máxima
A9: General | B9: 8 | C9: =RIGHT("0000"&B9,5) -> 00008 | D9: =IF(AND(EXACT(LEN(TRIM(H9)),0), EXACT(LEN(TRIM(G9)),0)),"",A9&"_"&VLOOKUP(E9,Valores!$D$3:$E$4,2,FALSE)&"_"&VLOOKUP(F9,Valores!$A$3:$B$8,2,FALSE)&"_"&C9) -> General_USU_ERR_00008 | E9: Usuario final | F9: Error | G9: Longitud mínima no cumplida | H9: El campo “${0}” no cumple la longitud mínima requerida (${1} caracteres). | I9: ${0}: Campo; ${1}: Longitud mínima
A10: General | B10: 9 | C10: =RIGHT("0000"&B10,5) -> 00009 | D10: =IF(AND(EXACT(LEN(TRIM(H10)),0), EXACT(LEN(TRIM(G10)),0)),"",A10&"_"&VLOOKUP(E10,Valores!$D$3:$E$4,2,FALSE)&"_"&VLOOKUP(F10,Valores!$A$3:$B$8,2,FALSE)&"_"&C10) -> General_USU_ERR_00009 | E10: Usuario final | F10: Error | G10: Formato inválido | H10: El campo “${0}” solo permite letras y espacios. | I10: ${0}: Campo (Primer_Nombre, Segundo_Nombre, Primer_Apellido, Segundo_Apellido, Tipo_Identificacion)
A11: General | B11: 10 | C11: =RIGHT("0000"&B11,5) -> 00010 | D11: =IF(AND(EXACT(LEN(TRIM(H11)),0), EXACT(LEN(TRIM(G11)),0)),"",A11&"_"&VLOOKUP(E11,Valores!$D$3:$E$4,2,FALSE)&"_"&VLOOKUP(F11,Valores!$A$3:$B$8,2,FALSE)&"_"&C11) -> General_USU_ERR_00010 | E11: Usuario final | F11: Error | G11: Formato inválido | H11: El campo “${0}” debe contener únicamente números enteros. | I11: ${0}: Campo (Código, Numero_Identificacion, Celular)
A12: General | B12: 11 | C12: =RIGHT("0000"&B12,5) -> 00011 | D12: =IF(AND(EXACT(LEN(TRIM(H12)),0), EXACT(LEN(TRIM(G12)),0)),"",A12&"_"&VLOOKUP(E12,Valores!$D$3:$E$4,2,FALSE)&"_"&VLOOKUP(F12,Valores!$A$3:$B$8,2,FALSE)&"_"&C12) -> General_USU_ERR_00011 | E12: Usuario final | F12: Error | G12: Formato de correo inválido | H12: El correo “${0}” no cumple el formato de correo electrónico válido. | I12: ${0}: Correo ingresado
A13: Usuario | B13: 12 | C13: =RIGHT("0000"&B13,5) -> 00012 | D13: =IF(AND(EXACT(LEN(TRIM(H13)),0), EXACT(LEN(TRIM(G13)),0)),"",A13&"_"&VLOOKUP(E13,Valores!$D$3:$E$4,2,FALSE)&"_"&VLOOKUP(F13,Valores!$A$3:$B$8,2,FALSE)&"_"&C13) -> Usuario_USU_ERR_00012 | E13: Usuario final | F13: Error | G13: Usuario inválido | H13: El “Usuario” solo puede contener caracteres alfanuméricos y .-_ sin espacios. Valor recibido: “${0}”. | I13: ${0}: Usuario ingresado
... A29: Login | B29: 28 | C29: =RIGHT("0000"&B29,5) -> 00028 | D29: =IF(AND(EXACT(LEN(TRIM(H29)),0), EXACT(LEN(TRIM(G29)),0)),"",A29&"_"&VLOOKUP(E29,Valores!$D$3:$E$4,2,FALSE)&"_"&VLOOKUP(F29,Valores!$A$3:$B$8,2,FALSE)&"_"&C29) -> Login_USU_INF_00028 | E29: Usuario final | F29: Información | G29: Sesión cerrada por inactividad | H29: Por seguridad, tu sesión se cerró tras ${0} minuto(s) de inactividad. Serás redirigido a la pantalla de login. | I29: ${0}: Minutos de inactividad configurados

Sheet CatalogoMensajes_ ReestContra
A1: Modelo | B1: Número Mensaje | C1: Número Mensaje | D1: Código mensaje | E1: Tipo | F1: Categoría Mensaje | G1: Título Mensaje | H1: Contenido Mensaje | I1: Parámetros
A2: Login
A3: Login
A4: Login
A5: Login
A6: Login
A7: Login

Sheet CatalogoMensajes Reg Y Mod Pago
A1: Modelo | B1: Número Mensaje | C1: Número Mensaje | D1: Código mensaje | E1: Tipo | F1: Categoría Mensaje | G1: Título Mensaje | H1: Contenido Mensaje | I1: Parámetros
A2: Pago | B2: 1 | C2: =RIGHT("0000"&B2,5) -> 00001 | D2: =IF(AND(EXACT(LEN(TRIM(H2)),0), EXACT(LEN(TRIM(G2)),0)),"",A2&"_"&VLOOKUP(E2,Valores!$D$3:$E$4,2,FALSE)&"_"&VLOOKUP(F2,Valores!$A$3:$B$8,2,FALSE)&"_"&C2) -> Pago_USU_EXI_00001 | E2: Usuario final | F2: Éxito | G2: Pagos registrados | H2: Se ha registrado ${0} pago exitosamente por un total de ${1}. | I2: ${0}: Cantidad de pagos registrados, ${1}: Monto
A3: Pago | B3: 2 | C3: =RIGHT("0000"&B3,5) -> 00002 | D3: =IF(AND(EXACT(LEN(TRIM(H3)),0), EXACT(LEN(TRIM(G3)),0)),"",A3&"_"&VLOOKUP(E3,Valores!$D$3:$E$4,2,FALSE)&"_"&VLOOKUP(F3,Valores!$A$3:$B$8,2,FALSE)&"_"&C3) -> Pago_USU_EXI_00002 | E3: Usuario final | F3: Éxito | G3: Pago parcial registrado | H3: Se registró un abono de ${0}. Saldo pendiente: ${1}. Estado de la venta: Pendiente de pago. | I3: ${0}: Monto, ${1}: Saldo restante
A4: Pago | B4: 3 | C4: =RIGHT("0000"&B4,5) -> 00003 | D4: =IF(AND(EXACT(LEN(TRIM(H4)),0), EXACT(LEN(TRIM(G4)),0)),"",A4&"_"&VLOOKUP(E4,Valores!$D$3:$E$4,2,FALSE)&"_"&VLOOKUP(F4,Valores!$A$3:$B$8,2,FALSE)&"_"&C4) -> Pago_USU_EXI_00003 | E4: Usuario final | F4: Éxito | G4: Pago completado | H4: Se registró el pago total de la venta “${0}”. Estado actualizado a: Pagada. | I4: ${0}: Id de la venta
A5: Pago | B5: 4 | C5: =RIGHT("0000"&B5,5) -> 00004 | D5: =IF(AND(EXACT(LEN(TRIM(H5)),0), EXACT(LEN(TRIM(G5)),0)),"",A5&"_"&VLOOKUP(E5,Valores!$D$3:$E$4,2,FALSE)&"_"&VLOOKUP(F5,Valores!$A$3:$B$8,2,FALSE)&"_"&C5) -> Pago_USU_ERR_00004 | E5: Usuario final | F5: Error | G5: Error de validación | H5: El campo “${0}” es inválido. Detalle: ${1}. | I5: ${0}: Nombre del campo, ${1}: Descripción error
A6: Pago | B6: 5 | C6: =RIGHT("0000"&B6,5) -> 00005 | D6: =IF(AND(EXACT(LEN(TRIM(H6)),0), EXACT(LEN(TRIM(G6)),0)),"",A6&"_"&VLOOKUP(E6,Valores!$D$3:$E$4,2,FALSE)&"_"&VLOOKUP(F6,Valores!$A$3:$B$8,2,FALSE)&"_"&C6) -> Pago_USU_INF_00005 | E6: Usuario final | F6: Información | G6: Registro cancelado | H6: El registro de pago fue cancelado. No se guardaron cambios. | I6: –
A7: Pago | B7: 6 | C7: =RIGHT("0000"&B7,5) -> 00006 | D7: =IF(AND(EXACT(LEN(TRIM(H7)),0), EXACT(LEN(TRIM(G7)),0)),"",A7&"_"&VLOOKUP(E7,Valores!$D$3:$E$4,2,FALSE)&"_"&VLOOKUP(F7,Valores!$A$3:$B$8,2,FALSE)&"_"&C7) -> Pago_USU_ERR_00006 | E7: Usuario final | F7: Error | G7: Monto excede saldo pendiente | H7: El monto ingresado (${0}) supera el saldo pendiente de la venta (${1}). Ajuste el valor e intente nuevamente. | I7: ${0}: Monto ingresado, ${1}: Saldo pendiente
A9: CATALOGO MENSAJES ACTUALIZAR PAGO (HU09)
A11: Modelo | B11: Número Mensaje | C11: Número Mensaje | D11: Código mensaje | E11: Tipo | F11: Categoría Mensaje | G11: Título Mensaje | H11: Contenido Mensaje | I11: Parámetros
A12: Pago | B12: 7 | C12: =RIGHT("0000"&B12,5) -> 00007 | D12: =IF(AND(EXACT(LEN(TRIM(H12)),0), EXACT(LEN(TRIM(G12)),0)),"",A12&"_"&VLOOKUP(E12,Valores!$D$3:$E$4,2,FALSE)&"_"&VLOOKUP(F12,Valores!$A$3:$B$8,2,FALSE)&"_"&C12) -> Pago_USU_EXI_00007 | E12: Usuario final | F12: Éxito | G12: ¡Pago actualizado exitosamente! | H12: El pago “${0}” ha sido actualizado correctamente. | I12: ${0}: Id del pago
A13: Pago | B13: 8 | C13: =RIGHT("0000"&B13,5) -> 00008 | D13: =IF(AND(EXACT(LEN(TRIM(H13)),0), EXACT(LEN(TRIM(G13)),0)),"",A13&"_"&VLOOKUP(E13,Valores!$D$3:$E$4,2,FALSE)&"_"&VLOOKUP(F13,Valores!$A$3:$B$8,2,FALSE)&"_"&C13) -> Pago_USU_ERR_00008 | E13: Usuario final | F13: Error | G13: Fecha inválida | H13: La fecha ingresada (${0}) no es válida. Debe ser igual o posterior a la fecha de la venta y no mayor a la fecha actual. | I13: ${0}: Fecha ingresada
A14: Pago | B14: 9 | C14: =RIGHT("0000"&B14,5) -> 00009 | D14: =IF(AND(EXACT(LEN(TRIM(H14)),0), EXACT(LEN(TRIM(G14)),0)),"",A14&"_"&VLOOKUP(E14,Valores!$D$3:$E$4,2,FALSE)&"_"&VLOOKUP(F14,Valores!$A$3:$B$8,2,FALSE)&"_"&C14) -> Pago_USU_ERR_00009 | E14: Usuario final | F14: Error | G14: Pago no modificable | H14: No se puede modificar un pago asociado a una venta en estado “${0}”. | I14: ${0}: Estado de la venta (Pagada/Anulada)
A15: Pago | B15: 10 | C15: =RIGHT("0000"&B15,5) -> 00010 | D15: =IF(AND(EXACT(LEN(TRIM(H15)),0), EXACT(LEN(TRIM(G15)),0)),"",A15&"_"&VLOOKUP(E15,Valores!$D$3:$E$4,2,FALSE)&"_"&VLOOKUP(F15,Valores!$A$3:$B$8,2,FALSE)&"_"&C15) -> Pago_USU_EXI_00010 | E15: Usuario final | F15: Éxito | G15: Actualización reflejada | H15: Los cambios del pago “${0}” han sido guardados, estado de la venta, “${1}” | I15: ${0}: Id del pago, “${1}”: Estado de la venta

Sheet CatalogoMensajes Reg y Mod Insu
A1: Modelo | B1: Número Mensaje | C1: Número Mensaje | D1: Código mensaje | E1: Tipo | F1: Categoría Mensaje | G1: Título Mensaje | H1: Contenido Mensaje | I1: Parámetros
A2: Insumo | B2: 1 | C2: =RIGHT("0000"&B2,5) -> 00001 | D2: =IF(AND(EXACT(LEN(TRIM(H2)),0), EXACT(LEN(TRIM(G2)),0)),"",A2&"_"&VLOOKUP(E2,Valores!$D$3:$E$4,2,FALSE)&"_"&VLOOKUP(F2,Valores!$A$3:$B$8,2,FALSE)&"_"&C2) -> Insumo_USU_EXI_00001 | E2: Usuario final | F2: Éxito | G2: ¡Insumo registrado exitosamente! | H2: El insumo “${0}” fue registrado correctamente y descontado del inventario. | I2: ${0}: Id o nombre del insumo
A3: Insumo | B3: 2 | C3: =RIGHT("0000"&B3,5) -> 00002 | D3: =IF(AND(EXACT(LEN(TRIM(H3)),0), EXACT(LEN(TRIM(G3)),0)),"",A3&"_"&VLOOKUP(E3,Valores!$D$3:$E$4,2,FALSE)&"_"&VLOOKUP(F3,Valores!$A$3:$B$8,2,FALSE)&"_"&C3) -> Insumo_USU_ADV_00002 | E3: Usuario final | F3: Advertencia | G3: Cantidad supera inventario | H3: La cantidad solicitada (${0}) supera el stock disponible (${1}). | I3: ${0}: Cantidad solicitada, ${1}: Cantidad disponible
A4: Insumo | B4: 3 | C4: =RIGHT("0000"&B4,5) -> 00003 | D4: =IF(AND(EXACT(LEN(TRIM(H4)),0), EXACT(LEN(TRIM(G4)),0)),"",A4&"_"&VLOOKUP(E4,Valores!$D$3:$E$4,2,FALSE)&"_"&VLOOKUP(F4,Valores!$A$3:$B$8,2,FALSE)&"_"&C4) -> Insumo_USU_ERR_00003 | E4: Usuario final | F4: Error | G4: Cantidad inválida | H4: El valor ingresado (${0}) no es válido. Debe ser numérico, mayor que cero. | I4: ${0}: Valor ingresado
A5: Insumo | B5: 4 | C5: =RIGHT("0000"&B5,5) -> 00004 | D5: =IF(AND(EXACT(LEN(TRIM(H5)),0), EXACT(LEN(TRIM(G5)),0)),"",A5&"_"&VLOOKUP(E5,Valores!$D$3:$E$4,2,FALSE)&"_"&VLOOKUP(F5,Valores!$A$3:$B$8,2,FALSE)&"_"&C5) -> Insumo_USU_ERR_00004 | E5: Usuario final | F5: Error | G5: Error de validación de campo | H5: El campo “${0}” es inválido. Detalle: ${1}. | I5: ${0}: Nombre del campo, ${1}: Descripción error
A6: Insumo | B6: 5 | C6: =RIGHT("0000"&B6,5) -> 00005 | D6: =IF(AND(EXACT(LEN(TRIM(H6)),0), EXACT(LEN(TRIM(G6)),0)),"",A6&"_"&VLOOKUP(E6,Valores!$D$3:$E$4,2,FALSE)&"_"&VLOOKUP(F6,Valores!$A$3:$B$8,2,FALSE)&"_"&C6) -> Insumo_USU_EXI_00005 | E6: Usuario final | F6: Éxito | G6: Cambios reflejados | H6: El registro del insumo “${0}” se guardó exitosamente y se reflejó en inventario e historial. | I6: ${0}: Id o nombre del insumo
A8: CATALOGO MENSAJES ACTUALIZAR Insumo(HU14)
A10: Modelo | B10: Número Mensaje | C10: Número Mensaje | D10: Código mensaje | E10: Tipo | F10: Categoría Mensaje | G10: Título Mensaje | H10: Contenido Mensaje | I10: Parámetros
A11: Insumo | B11: 6 | C11: =RIGHT("0000"&B11,5) -> 00006 | D11: =IF(AND(EXACT(LEN(TRIM(H11)),0), EXACT(LEN(TRIM(G11)),0)),"",A11&"_"&VLOOKUP(E11,Valores!$D$3:$E$4,2,FALSE)&"_"&VLOOKUP(F11,Valores!$A$3:$B$8,2,FALSE)&"_"&C11) -> Insumo_USU_ERR_00006 | E11: Usuario final | F11: Error | G11: Stock insuficiente | H11: La cantidad adicional solicitada (${0}) supera el stock disponible (${1}). | I11: ${0}: Cantidad solicitada, ${1}: Stock disponible
A12: Insumo | B12: 7 | C12: =RIGHT("0000"&B12,5) -> 00007 | D12: =IF(AND(EXACT(LEN(TRIM(H12)),0), EXACT(LEN(TRIM(G12)),0)),"",A12&"_"&VLOOKUP(E12,Valores!$D$3:$E$4,2,FALSE)&"_"&VLOOKUP(F12,Valores!$A$3:$B$8,2,FALSE)&"_"&C12) -> Insumo_USU_ERR_00007 | E12: Usuario final | F12: Error | G12: Stock actualizado | H12: Se redujo la cantidad consumida. Se devolvieron ${0} unidades al inventario del producto “${1}”. | I12: ${0}: Cantidad devuelta, ${1}: Nombre producto
A13: Insumo | B13: 14 | C13: =RIGHT("0000"&B13,5) -> 00014 | D13: =IF(AND(EXACT(LEN(TRIM(H13)),0), EXACT(LEN(TRIM(G13)),0)),"",A13&"_"&VLOOKUP(E13,Valores!$D$3:$E$4,2,FALSE)&"_"&VLOOKUP(F13,Valores!$A$3:$B$8,2,FALSE)&"_"&C13) -> Insumo_USU_EXI_00014 | E13: Usuario final | F13: Éxito | G13: ¡Insumo actualizado exitosamente! | H13: El insumo “${0}” fue actualizado correctamente y los cambios quedaron registrados. | I13: ${0}: Id o nombre del insumo

Sheet CatalogoMensajes_regModCon Abas
A1: Modelo | B1: Número Mensaje | D1: Número Mensaje | E1: Código mensaje | F1: Tipo | G1: Categoría Mensaje | H1: Título Mensaje | I1: Contenido Mensaje | J1: Parámetros
A2: Abastecimiento | B2: 1 | D2: =RIGHT("0000"&B2,5) -> 00001 | E2: =IF(AND(EXACT(LEN(TRIM(I2)),0), EXACT(LEN(TRIM(H2)),0)),"",A2&"_"&VLOOKUP(F2,Valores!$D$3:$E$4,2,FALSE)&"_"&VLOOKUP(G2,Valores!$A$3:$B$8,2,FALSE)&"_"&D2) -> Abastecimiento_USU_EXI_00001 | F2: Usuario final | G2: Éxito | H2: ¡Abastecimiento registrado! | I2: El abastecimiento “${0}” fue registrado correctamente. Stock incrementado para los productos asociados. | J2: ${0}: Código abastecimiento o número de factura
A3: Abastecimiento | B3: 2 | D3: =RIGHT("0000"&B3,5) -> 00002 | E3: =IF(AND(EXACT(LEN(TRIM(I3)),0), EXACT(LEN(TRIM(H3)),0)),"",A3&"_"&VLOOKUP(F3,Valores!$D$3:$E$4,2,FALSE)&"_"&VLOOKUP(G3,Valores!$A$3:$B$8,2,FALSE)&"_"&D3) -> Abastecimiento_USU_ERR_00002 | F3: Usuario final | G3: Error | H3: Factura ya registrada | I3: El número de factura “${0}” ya fue registrado para el proveedor “${1}”. No se permiten duplicados. | J3: ${0}: NroFactura, ${1}: Proveedor
A4: Abastecimiento | B4: 3 | D4: =RIGHT("0000"&B4,5) -> 00003 | E4: =IF(AND(EXACT(LEN(TRIM(I4)),0), EXACT(LEN(TRIM(H4)),0)),"",A4&"_"&VLOOKUP(F4,Valores!$D$3:$E$4,2,FALSE)&"_"&VLOOKUP(G4,Valores!$A$3:$B$8,2,FALSE)&"_"&D4) -> Abastecimiento_USU_ERR_00003 | F4: Usuario final | G4: Error | H4: Error de validación de campo | I4: El campo “${0}” es inválido. Detalle: ${1}. | J4: ${0}: Nombre del campo, ${1}: Descripción error
A5: Abastecimiento | B5: 4 | D5: =RIGHT("0000"&B5,5) -> 00004 | E5: =IF(AND(EXACT(LEN(TRIM(I5)),0), EXACT(LEN(TRIM(H5)),0)),"",A5&"_"&VLOOKUP(F5,Valores!$D$3:$E$4,2,FALSE)&"_"&VLOOKUP(G5,Valores!$A$3:$B$8,2,FALSE)&"_"&D5) -> Abastecimiento_USU_ERR_00004 | F5: Usuario final | G5: Error | H5: Cantidad inválida | I5: La cantidad ingresada (${0}) no es válida. Debe ser mayor que 0. | J5: ${0}: Cantidad ingresada
A7: CATALOGO MENSAJES ACTUALIZAR Abastecimiento(HU19)
A9: Modelo | B9: Número Mensaje | D9: Número Mensaje | E9: Código mensaje | F9: Tipo | G9: Categoría Mensaje | H9: Título Mensaje | I9: Contenido Mensaje | J9: Parámetros
A10: Abastecimiento | B10: 8 | C10: 5 | D10: =RIGHT("0000"&B10,5) -> 00008 | E10: =IF(AND(EXACT(LEN(TRIM(I10)),0), EXACT(LEN(TRIM(H10)),0)),"",A10&"_"&VLOOKUP(F10,Valores!$D$3:$E$4,2,FALSE)&"_"&VLOOKUP(G10,Valores!$A$3:$B$8,2,FALSE)&"_"&D10) -> Abastecimiento_USU_EXI_00008 | F10: Usuario final | G10: Éxito | H10: ¡Abastecimiento actualizado! | I10: El abastecimiento “${0}” fue actualizado correctamente. | J10: ${0}: Código de abastecimiento
A11: Abastecimiento | B11: 9 | C11: 6 | D11: =RIGHT("0000"&B11,5) -> 00009 | E11: =IF(AND(EXACT(LEN(TRIM(I11)),0), EXACT(LEN(TRIM(H11)),0)),"",A11&"_"&VLOOKUP(F11,Valores!$D$3:$E$4,2,FALSE)&"_"&VLOOKUP(G11,Valores!$A$3:$B$8,2,FALSE)&"_"&D11) -> Abastecimiento_USU_ERR_00009 | F11: Usuario final | G11: Error | H11: Stock insuficiente | I11: No se puede actualizar debido que las ${0} unidades registradas, no estan disponibles en el stock ${1}. | J11: ${0}: Cantidad solicitada, ${1}: Stock disponible
A12: Abastecimiento | B12: 10 | C12: 7 | D12: =RIGHT("0000"&B12,5) -> 00010 | E12: =IF(AND(EXACT(LEN(TRIM(I12)),0), EXACT(LEN(TRIM(H12)),0)),"",A12&"_"&VLOOKUP(F12,Valores!$D$3:$E$4,2,FALSE)&"_"&VLOOKUP(G12,Valores!$A$3:$B$8,2,FALSE)&"_"&D12) -> Abastecimiento_USU_ERR_00010 | F12: Usuario final | G12: Error | H12: Factura duplicada | I12: El número de factura “${0}” ya existe para el proveedor “${1}”. No se permiten duplicados. | J12: ${0}: NroFactura, ${1}: Proveedor
A14: CATALOGO MENSAJES Consultar Abastecimiento(HU20)
A16: Modelo | B16: Número Mensaje | D16: Número Mensaje | E16: Código mensaje | F16: Tipo | G16: Categoría Mensaje | H16: Título Mensaje | I16: Contenido Mensaje | J16: Parámetros
A17: Abastecimiento | B17: 16 | C17: 8 | D17: =RIGHT("0000"&B17,5) -> 00016 | E17: =IF(AND(EXACT(LEN(TRIM(I17)),0), EXACT(LEN(TRIM(H17)),0)),"",A17&"_"&VLOOKUP(F17,Valores!$D$3:$E$4,2,FALSE)&"_"&VLOOKUP(G17,Valores!$A$3:$B$8,2,FALSE)&"_"&D17) -> Abastecimiento_USU_ERR_00016 | F17: Usuario final | G17: Error | H17: Abastecimiento no encontrado | I17: El abastecimiento con código “${0}” no existe o el identificador es incorrecto. | J17: ${0}: Código abastecimiento
A18: Abastecimiento | B18: 19 | D18: =RIGHT("0000"&B18,5) -> 00019 | E18: =IF(AND(EXACT(LEN(TRIM(I18)),0), EXACT(LEN(TRIM(H18)),0)),"",A18&"_"&VLOOKUP(F18,Valores!$D$3:$E$4,2,FALSE)&"_"&VLOOKUP(G18,Valores!$A$3:$B$8,2,FALSE)&"_"&D18) -> Abastecimiento_USU_INF_00019 | F18: Usuario final | G18: Información | H18: Filtros aplicados | I18: Los resultados han sido filtrados por: ${0}. | J18: ${0}: Lista de filtros aplicados

Sheet CatalogoMensajes_regModCon Devo
A1: Modelo | B1: Número Mensaje | C1: Número Mensaje | D1: Código mensaje | E1: Tipo | F1: Categoría Mensaje | G1: Título Mensaje | H1: Contenido Mensaje | I1: Parámetros
A2: Devolución | B2: 1 | C2: =RIGHT("0000"&B2,5) -> 00001 | D2: =IF(AND(EXACT(LEN(TRIM(H2)),0), EXACT(LEN(TRIM(G2)),0)),"",A2&"_"&VLOOKUP(E2,Valores!$D$3:$E$4,2,FALSE)&"_"&VLOOKUP(F2,Valores!$A$3:$B$8,2,FALSE)&"_"&C2) -> Devolución_USU_EXI_00001 | E2: Usuario final | F2: Éxito | G2: ¡Devolución registrada exitosamente! | H2: La devolución “${0}” fue registrada correctamente. | I2: ${0}: Código devolución,
A3: Devolución | B3: 2 | C3: =RIGHT("0000"&B3,5) -> 00002 | D3: =IF(AND(EXACT(LEN(TRIM(H3)),0), EXACT(LEN(TRIM(G3)),0)),"",A3&"_"&VLOOKUP(E3,Valores!$D$3:$E$4,2,FALSE)&"_"&VLOOKUP(F3,Valores!$A$3:$B$8,2,FALSE)&"_"&C3) -> Devolución_USU_ERR_00002 | E3: Usuario final | F3: Error | G3: Error de validación de campo | H3: El campo “${0}” es inválido. Detalle: ${1}. | I3: ${0}: Nombre del campo, ${1}: Descripción error
A4: Devolución | B4: 3 | C4: =RIGHT("0000"&B4,5) -> 00003 | D4: =IF(AND(EXACT(LEN(TRIM(H4)),0), EXACT(LEN(TRIM(G4)),0)),"",A4&"_"&VLOOKUP(E4,Valores!$D$3:$E$4,2,FALSE)&"_"&VLOOKUP(F4,Valores!$A$3:$B$8,2,FALSE)&"_"&C4) -> Devolución_USU_ERR_00003 | E4: Usuario final | F4: Error | G4: Estado de venta inválido | H4: No es posible registrar devolución para la venta en estado “${0}”. | I4: ${0}: Estado de venta
A5: Devolución | B5: 4 | C5: =RIGHT("0000"&B5,5) -> 00004 | D5: =IF(AND(EXACT(LEN(TRIM(H5)),0), EXACT(LEN(TRIM(G5)),0)),"",A5&"_"&VLOOKUP(E5,Valores!$D$3:$E$4,2,FALSE)&"_"&VLOOKUP(F5,Valores!$A$3:$B$8,2,FALSE)&"_"&C5) -> Devolución_USU_ERR_00004 | E5: Usuario final | F5: Error | G5: Fecha fuera de período | H5: La fecha de devolución ingresada no es válida: ${0}. | I5: ${0}: FechaDevolución
A6: Devolución | B6: 5 | C6: =RIGHT("0000"&B6,5) -> 00005 | D6: =IF(AND(EXACT(LEN(TRIM(H6)),0), EXACT(LEN(TRIM(G6)),0)),"",A6&"_"&VLOOKUP(E6,Valores!$D$3:$E$4,2,FALSE)&"_"&VLOOKUP(F6,Valores!$A$3:$B$8,2,FALSE)&"_"&C6) -> Devolución_USU_ERR_00005 | E6: Usuario final | F6: Error | G6: Cantidad supera máximo devolvible | H6: La cantidad solicitada (${0}) supera el máximo que se puede devolver (${1}). | I6: ${0}: Cantidad solicitada, ${1}: Cantidad máxima
A7: Devolución | B7: 6 | C7: =RIGHT("0000"&B7,5) -> 00006 | D7: =IF(AND(EXACT(LEN(TRIM(H7)),0), EXACT(LEN(TRIM(G7)),0)),"",A7&"_"&VLOOKUP(E7,Valores!$D$3:$E$4,2,FALSE)&"_"&VLOOKUP(F7,Valores!$A$3:$B$8,2,FALSE)&"_"&C7) -> Devolución_USU_ERR_00006 | E7: Usuario final | F7: Error | G7: Sin ítems en devolución | H7: Debe registrar al menos un producto para guardar la devolución. | I7: –
A8: Devolución | B8: 7 | C8: =RIGHT("0000"&B8,5) -> 00007 | D8: =IF(AND(EXACT(LEN(TRIM(H8)),0), EXACT(LEN(TRIM(G8)),0)),"",A8&"_"&VLOOKUP(E8,Valores!$D$3:$E$4,2,FALSE)&"_"&VLOOKUP(F8,Valores!$A$3:$B$8,2,FALSE)&"_"&C8) -> Devolución_USU_ERR_00007 | E8: Usuario final | F8: Error | G8: Total devuelto no editable | H8: El valor del total devuelto se calcula automáticamente. No es posible modificarlo manualmente. | I8: –
A9: Devolución | B9: 8 | C9: =RIGHT("0000"&B9,5) -> 00008 | D9: =IF(AND(EXACT(LEN(TRIM(H9)),0), EXACT(LEN(TRIM(G9)),0)),"",A9&"_"&VLOOKUP(E9,Valores!$D$3:$E$4,2,FALSE)&"_"&VLOOKUP(F9,Valores!$A$3:$B$8,2,FALSE)&"_"&C9) -> Devolución_USU_EXI_00008 | E9: Usuario final | F9: Éxito | G9: Stock actualizado | H9: El stock de los productos fue incrementado correctamente según las cantidades devueltas. | I9: –
A11: CATALOGO MENSAJES Actualizar Devolución(HU34)
A13: Modelo | B13: Número Mensaje | C13: Número Mensaje | D13: Código mensaje | E13: Tipo | F13: Categoría Mensaje | G13: Título Mensaje | H13: Contenido Mensaje | I13: Parámetros
A14: Devolución | B14: 9 | C14: =RIGHT("0000"&B14,5) -> 00009 | D14: =IF(AND(EXACT(LEN(TRIM(H14)),0), EXACT(LEN(TRIM(G14)),0)),"",A14&"_"&VLOOKUP(E14,Valores!$D$3:$E$4,2,FALSE)&"_"&VLOOKUP(F14,Valores!$A$3:$B$8,2,FALSE)&"_"&C14) -> Devolución_USU_EXI_00009 | E14: Usuario final | F14: Éxito | G14: ¡Devolución modificada exitosamente! | H14: La devolución “${0}” fue modificada correctamente. El TotalDevuelto se ha recalculado. | I14: ${0}: Código devolución
A15: Devolución | B15: 10 | C15: =RIGHT("0000"&B15,5) -> 00010 | D15: =IF(AND(EXACT(LEN(TRIM(H15)),0), EXACT(LEN(TRIM(G15)),0)),"",A15&"_"&VLOOKUP(E15,Valores!$D$3:$E$4,2,FALSE)&"_"&VLOOKUP(F15,Valores!$A$3:$B$8,2,FALSE)&"_"&C15) -> Devolución_USU_EXI_00010 | E15: Usuario final | F15: Éxito | G15: Total recalculado | H15: El TotalDevuelto se recalculó automáticamente con los precios de la venta original. | I15: –
A17: CATALOGO MENSAJES Consultar Devolución(HU35)
A19: Modelo | B19: Número Mensaje | C19: Número Mensaje | D19: Código mensaje | E19: Tipo | F19: Categoría Mensaje | G19: Título Mensaje | H19: Contenido Mensaje | I19: Parámetros
A20: Devolución | B20: 11 | C20: =RIGHT("0000"&B20,5) -> 00011 | D20: =IF(AND(EXACT(LEN(TRIM(H20)),0), EXACT(LEN(TRIM(G20)),0)),"",A20&"_"&VLOOKUP(E20,Valores!$D$3:$E$4,2,FALSE)&"_"&VLOOKUP(F20,Valores!$A$3:$B$8,2,FALSE)&"_"&C20) -> Devolución_USU_ERR_00011 | E20: Usuario final | F20: Error | G20: Rango de fechas inválido | H20: La fecha de fin (${0}) no puede ser anterior a la fecha de inicio (${1}). | I20: ${0}: Fecha fin, ${1}: Fecha inicio
A21: Devolución | B21: 12 | C21: =RIGHT("0000"&B21,5) -> 00012 | D21: =IF(AND(EXACT(LEN(TRIM(H21)),0), EXACT(LEN(TRIM(G21)),0)),"",A21&"_"&VLOOKUP(E21,Valores!$D$3:$E$4,2,FALSE)&"_"&VLOOKUP(F21,Valores!$A$3:$B$8,2,FALSE)&"_"&C21) -> Devolución_USU_INF_00012 | E21: Usuario final | F21: Información | G21: No se encontraron registros | H21: No existen devoluciones que cumplan los criterios de búsqueda. | I21: –
A22: Devolución | B22: 13 | C22: =RIGHT("0000"&B22,5) -> 00013 | D22: =IF(AND(EXACT(LEN(TRIM(H22)),0), EXACT(LEN(TRIM(G22)),0)),"",A22&"_"&VLOOKUP(E22,Valores!$D$3:$E$4,2,FALSE)&"_"&VLOOKUP(F22,Valores!$A$3:$B$8,2,FALSE)&"_"&C22) -> Devolución_USU_ERR_00013 | E22: Usuario final | F22: Error | G22: Acceso denegado | H22: No tiene permisos para consultar devoluciones. Contacte al administrador. | I22: –

Sheet CatalogoMensajes RegYMod Client
A1: Modelo | B1: Número Mensaje | C1: Número Mensaje | D1: Código mensaje | E1: Tipo | F1: Categoría Mensaje | G1: Título Mensaje | H1: Contenido Mensaje | I1: Parámetros
A2: Cliente | B2: 1 | C2: =RIGHT("0000"&B2,5) -> 00001 | D2: =IF(AND(EXACT(LEN(TRIM(H2)),0), EXACT(LEN(TRIM(G2)),0)),"",A2&"_"&VLOOKUP(E2,Valores!$D$3:$E$4,2,FALSE)&"_"&VLOOKUP(F2,Valores!$A$3:$B$8,2,FALSE)&"_"&C2) -> Cliente_USU_EXI_00001 | E2: Usuario final | F2: Éxito | G2: ¡Cliente registrado exitosamente! | H2: El cliente “${0}” fue registrado correctamente en el sistema. | I2: ${0}: Nombre completo del cliente
A3: Cliente | B3: 2 | C3: =RIGHT("0000"&B3,5) -> 00002 | D3: =IF(AND(EXACT(LEN(TRIM(H3)),0), EXACT(LEN(TRIM(G3)),0)),"",A3&"_"&VLOOKUP(E3,Valores!$D$3:$E$4,2,FALSE)&"_"&VLOOKUP(F3,Valores!$A$3:$B$8,2,FALSE)&"_"&C3) -> Cliente_USU_ERR_00002 | E3: Usuario final | F3: Error | G3: Campo obligatorio inválido | H3: El campo “${0}” es obligatorio o tiene un formato inválido. Detalle: ${1}. | I3: ${0}: Nombre del campo, ${1}: Descripción error
A4: Cliente | B4: 3 | C4: =RIGHT("0000"&B4,5) -> 00003 | D4: =IF(AND(EXACT(LEN(TRIM(H4)),0), EXACT(LEN(TRIM(G4)),0)),"",A4&"_"&VLOOKUP(E4,Valores!$D$3:$E$4,2,FALSE)&"_"&VLOOKUP(F4,Valores!$A$3:$B$8,2,FALSE)&"_"&C4) -> Cliente_USU_ERR_00003 | E4: Usuario final | F4: Error | G4: Cliente ya registrado | H4: El cliente con ${0} “${1}” ya está registrado en el sistema. | I4: ${0}: Tipo de dato (Documento/Correo), ${1}: Valor
A5: Cliente | B5: 4 | C5: =RIGHT("0000"&B5,5) -> 00004 | D5: =IF(AND(EXACT(LEN(TRIM(H5)),0), EXACT(LEN(TRIM(G5)),0)),"",A5&"_"&VLOOKUP(E5,Valores!$D$3:$E$4,2,FALSE)&"_"&VLOOKUP(F5,Valores!$A$3:$B$8,2,FALSE)&"_"&C5) -> Cliente_USU_ERR_00004 | E5: Usuario final | F5: Error | G5: Error de validación de campo | H5: El campo “${0}” no cumple la regla: ${1}. Corrija el valor antes de continuar. | I5: ${0}: Nombre del campo, ${1}: Regla incumplida
A7: CATALOGO MENSAJES ACTUALIZAR CLIENTE (HU24)
A9: Modelo | B9: Número Mensaje | C9: Número Mensaje | D9: Código mensaje | E9: Tipo | F9: Categoría Mensaje | G9: Título Mensaje | H9: Contenido Mensaje | I9: Parámetros
A10: Cliente | B10: 5 | C10: =RIGHT("0000"&B10,5) -> 00005 | D10: =IF(AND(EXACT(LEN(TRIM(H10)),0), EXACT(LEN(TRIM(G10)),0)),"",A10&"_"&VLOOKUP(E10,Valores!$D$3:$E$4,2,FALSE)&"_"&VLOOKUP(F10,Valores!$A$3:$B$8,2,FALSE)&"_"&C10) -> Cliente_USU_EXI_00005 | E10: Usuario final | F10: Éxito | G10: ¡Cliente actualizado exitosamente! | H10: El cliente “${0}” fue actualizado correctamente. Los cambios se reflejan en la base de datos y en la visualización. | I10: ${0}: Nombre cliente

Sheet CatalogoMensajes Reg y mod Sede
A1: Modelo | B1: Número Mensaje | C1: Número Mensaje | D1: Código mensaje | E1: Tipo | F1: Categoría Mensaje | G1: Título Mensaje | H1: Contenido Mensaje | I1: Parámetros
A2: Sede | B2: 1 | C2: =RIGHT("0000"&B2,5) -> 00001 | D2: =IF(AND(EXACT(LEN(TRIM(H2)),0), EXACT(LEN(TRIM(G2)),0)),"",A2&"_"&VLOOKUP(E2,Valores!$D$3:$E$4,2,FALSE)&"_"&VLOOKUP(F2,Valores!$A$3:$B$8,2,FALSE)&"_"&C2) -> Sede_USU_EXI_00001 | E2: Usuario final | F2: Éxito | G2: ¡Sede registrada exitosamente! | H2: La sede “${0}” fue registrada correctamente y ya está disponible en el listado de sedes. | I2: ${0}: Nombre de la sede
A3: Sede | B3: 2 | C3: =RIGHT("0000"&B3,5) -> 00002 | D3: =IF(AND(EXACT(LEN(TRIM(H3)),0), EXACT(LEN(TRIM(G3)),0)),"",A3&"_"&VLOOKUP(E3,Valores!$D$3:$E$4,2,FALSE)&"_"&VLOOKUP(F3,Valores!$A$3:$B$8,2,FALSE)&"_"&C3) -> Sede_USU_ERR_00002 | E3: Usuario final | F3: Error | G3: Sede ya registrada | H3: La sede con ${0} “${1}” ya existe en el sistema. No se permite duplicidad. | I3: ${0}: Tipo de dato (Nombre/Dirección), ${1}: Valor
A4: Sede | B4: 3 | C4: =RIGHT("0000"&B4,5) -> 00003 | D4: =IF(AND(EXACT(LEN(TRIM(H4)),0), EXACT(LEN(TRIM(G4)),0)),"",A4&"_"&VLOOKUP(E4,Valores!$D$3:$E$4,2,FALSE)&"_"&VLOOKUP(F4,Valores!$A$3:$B$8,2,FALSE)&"_"&C4) -> Sede_USU_ERR_00003 | E4: Usuario final | F4: Error | G4: Error de validación de campo | H4: El campo “${0}” es inválido. Detalle: ${1}. | I4: ${0}: Nombre campo, ${1}: Descripción error
A6: CATALOGO MENSAJES ACTUALIZAR Sede (HU28)
A8: Modelo | B8: Número Mensaje | C8: Número Mensaje | D8: Código mensaje | E8: Tipo | F8: Categoría Mensaje | G8: Título Mensaje | H8: Contenido Mensaje | I8: Parámetros
A9: Sede | B9: 4 | C9: =RIGHT("0000"&B9,5) -> 00004 | D9: =IF(AND(EXACT(LEN(TRIM(H9)),0), EXACT(LEN(TRIM(G9)),0)),"",A9&"_"&VLOOKUP(E9,Valores!$D$3:$E$4,2,FALSE)&"_"&VLOOKUP(F9,Valores!$A$3:$B$8,2,FALSE)&"_"&C9) -> Sede_USU_EXI_00004 | E9: Usuario final | F9: Éxito | G9: ¡Sede actualizada exitosamente! | H9: La sede “${0}” fue actualizada correctamente y ya se refleja en el listado de sedes. | I9: ${0}: Nombre de la sede

Sheet CatalogoMensajes re,co,m vent 
A1: Modelo | B1: Número Mensaje | C1: Número Mensaje | D1: Código mensaje | E1: Tipo | F1: Categoría Mensaje | G1: Título Mensaje | H1: Contenido Mensaje | I1: Parámetros
A2: Venta | B2: 1 | C2: =RIGHT("0000"&B2,5) -> 00001 | D2: =IF(AND(EXACT(LEN(TRIM(H2)),0), EXACT(LEN(TRIM(G2)),0)),"",A2&"_"&VLOOKUP(E2,Valores!$D$3:$E$4,2,FALSE)&"_"&VLOOKUP(F2,Valores!$A$3:$B$8,2,FALSE)&"_"&C2) -> Venta_USU_EXI_00001 | E2: Usuario final | F2: Éxito | G2: Venta registrada | H2: La venta #${0} para el cliente “${1}” fue registrada correctamente. | I2: ${0}: Consecutivo/código de la venta; ${1}: Nombre del cliente
A3: Venta | B3: 2 | C3: =RIGHT("0000"&B3,5) -> 00002 | D3: =IF(AND(EXACT(LEN(TRIM(H3)),0), EXACT(LEN(TRIM(G3)),0)),"",A3&"_"&VLOOKUP(E3,Valores!$D$3:$E$4,2,FALSE)&"_"&VLOOKUP(F3,Valores!$A$3:$B$8,2,FALSE)&"_"&C3) -> Venta_USU_ERR_00002 | E3: Usuario final | F3: Error | G3: Dato requerido no diligenciado | H3: Debes registrar un valor para el campo “${0}”, el cual es obligatorio. | I3: ${0}: Nombre del campo
A4: Venta | B4: 3 | C4: =RIGHT("0000"&B4,5) -> 00003 | D4: =IF(AND(EXACT(LEN(TRIM(H4)),0), EXACT(LEN(TRIM(G4)),0)),"",A4&"_"&VLOOKUP(E4,Valores!$D$3:$E$4,2,FALSE)&"_"&VLOOKUP(F4,Valores!$A$3:$B$8,2,FALSE)&"_"&C4) -> Venta_USU_ERR_00003 | E4: Usuario final | F4: Error | G4: Error de validación de campo | H4: El campo “${0}” es inválido. Detalle: ${1}. | I4: ${0}: Nombre del campo; ${1}: Descripción del error (formato/rango/longitud.)
A5: Venta | B5: 4 | C5: =RIGHT("0000"&B5,5) -> 00004 | D5: =IF(AND(EXACT(LEN(TRIM(H5)),0), EXACT(LEN(TRIM(G5)),0)),"",A5&"_"&VLOOKUP(E5,Valores!$D$3:$E$4,2,FALSE)&"_"&VLOOKUP(F5,Valores!$A$3:$B$8,2,FALSE)&"_"&C5) -> Venta_USU_EXI_00004 | E5: Usuario final | F5: Éxito | G5: Stock insuficiente | H5: No hay stock suficiente para “${0}”. Solicitado: ${1}. Disponible: ${2}. Ajusta la cantidad. | I5: ${0}: Producto; ${1}: Cantidad solicitada; ${2}: Stock disponible
A6: Venta | B6: 5 | C6: =RIGHT("0000"&B6,5) -> 00005 | D6: =IF(AND(EXACT(LEN(TRIM(H6)),0), EXACT(LEN(TRIM(G6)),0)),"",A6&"_"&VLOOKUP(E6,Valores!$D$3:$E$4,2,FALSE)&"_"&VLOOKUP(F6,Valores!$A$3:$B$8,2,FALSE)&"_"&C6) -> Venta_USU_INF_00005 | E6: Usuario final | F6: Información | G6: Cliente asociado a la venta | H6: El cliente “${0}” (${1}) fue asociado a la venta. | I6: ${0}: Nombre del cliente; ${1}: Tipo (Existente/Nuevo)
A7: Venta | B7: 6 | C7: =RIGHT("0000"&B7,5) -> 00006 | D7: =IF(AND(EXACT(LEN(TRIM(H7)),0), EXACT(LEN(TRIM(G7)),0)),"",A7&"_"&VLOOKUP(E7,Valores!$D$3:$E$4,2,FALSE)&"_"&VLOOKUP(F7,Valores!$A$3:$B$8,2,FALSE)&"_"&C7) -> Venta_USU_ERR_00006 | E7: Usuario final | F7: Error | G7: Cliente no válido | H7: No fue posible asociar el cliente. Detalle: ${0}. | I7: ${0}: Motivo/error (no encontrado, datos incompletos.)
A10: Consultar venta HU6
A12: Modelo | B12: Número Mensaje | C12: Número Mensaje | D12: Código mensaje | E12: Tipo | F12: Categoría Mensaje | G12: Título Mensaje | H12: Contenido Mensaje | I12: Parámetros
A13: Venta | B13: 7 | C13: =RIGHT("0000"&B13,5) -> 00007 | D13: =IF(AND(EXACT(LEN(TRIM(H13)),0), EXACT(LEN(TRIM(G13)),0)),"",A13&"_"&VLOOKUP(E13,Valores!$D$3:$E$4,2,FALSE)&"_"&VLOOKUP(F13,Valores!$A$3:$B$8,2,FALSE)&"_"&C13) -> Venta_USU_INF_00007 | E13: Usuario final | F13: Información | G13: Filtros activos. | H13: Se aplicaron los filtros seleccionados. Resultados: ${0} venta(s). | I13: ${0}: Número de resultados
A14: Venta | B14: 8 | C14: =RIGHT("0000"&B14,5) -> 00008 | D14: =IF(AND(EXACT(LEN(TRIM(H14)),0), EXACT(LEN(TRIM(G14)),0)),"",A14&"_"&VLOOKUP(E14,Valores!$D$3:$E$4,2,FALSE)&"_"&VLOOKUP(F14,Valores!$A$3:$B$8,2,FALSE)&"_"&C14) -> Venta_USU_INF_00008 | E14: Usuario final | F14: Información | G14: Venta no encontrada | H14: No se encontró la venta #${0} o su detalle no está disponible. Verifica el criterio de búsqueda. | I14: ${0}: Consecutivo/código buscado (opcional)
A15: Venta | B15: 9 | C15: =RIGHT("0000"&B15,5) -> 00009 | D15: =IF(AND(EXACT(LEN(TRIM(H15)),0), EXACT(LEN(TRIM(G15)),0)),"",A15&"_"&VLOOKUP(E15,Valores!$D$3:$E$4,2,FALSE)&"_"&VLOOKUP(F15,Valores!$A$3:$B$8,2,FALSE)&"_"&C15) -> Venta_USU_INF_00009 | E15: Usuario final | F15: Información | G15: Sin resultados | H15: No hay ventas que coincidan con los filtros aplicados. Ajusta los criterios y vuelve a intentar. | I15: –
A17: Actualizar venta HU7
A19: Modelo | B19: Número Mensaje | C19: Número Mensaje | D19: Código mensaje | E19: Tipo | F19: Categoría Mensaje | G19: Título Mensaje | H19: Contenido Mensaje | I19: Parámetros
A20: Venta | B20: 11 | C20: =RIGHT("0000"&B20,5) -> 00011 | D20: =IF(AND(EXACT(LEN(TRIM(H20)),0), EXACT(LEN(TRIM(G20)),0)),"",A20&"_"&VLOOKUP(E20,Valores!$D$3:$E$4,2,FALSE)&"_"&VLOOKUP(F20,Valores!$A$3:$B$8,2,FALSE)&"_"&C20) -> Venta_USU_EXI_00011 | E20: Usuario final | F20: Éxito | G20: Venta actualizada | H20: La venta #${0} fue actualizada correctamente. | I20: ${0}: Consecutivo/código de la venta
A21: Venta | B21: 12 | C21: =RIGHT("0000"&B21,5) -> 00012 | D21: =IF(AND(EXACT(LEN(TRIM(H21)),0), EXACT(LEN(TRIM(G21)),0)),"",A21&"_"&VLOOKUP(E21,Valores!$D$3:$E$4,2,FALSE)&"_"&VLOOKUP(F21,Valores!$A$3:$B$8,2,FALSE)&"_"&C21) -> Venta_USU_EXI_00012 | E21: Usuario final | F21: Éxito | G21: Stock insuficiente al aumentar | H21: No hay stock suficiente para “${0}”. Adicional solicitado: ${1}. Disponible: ${2}. | I21: ${0}: Producto; ${1}: Cantidad adicional solicitada; ${2}: Stock disponible
A22: Venta | B22: 13 | C22: =RIGHT("0000"&B22,5) -> 00013 | D22: =IF(AND(EXACT(LEN(TRIM(H22)),0), EXACT(LEN(TRIM(G22)),0)),"",A22&"_"&VLOOKUP(E22,Valores!$D$3:$E$4,2,FALSE)&"_"&VLOOKUP(F22,Valores!$A$3:$B$8,2,FALSE)&"_"&C22) -> Venta_USU_ADV_00013 | E22: Usuario final | F22: Advertencia | G22: Edición no permitida | H22: La venta #${0} está finalizada/pagada en su totalidad. No es posible editarla. | I22: ${0}: Consecutivo/código de la venta

Sheet CatalogoMensajes Envio
A1: Modelo | B1: Número Mensaje | C1: Número Mensaje | D1: Código mensaje | E1: Tipo | F1: Categoría Mensaje | G1: Título Mensaje | H1: Contenido Mensaje | I1: Parámetros
A2: Envio | B2: 1 | C2: =RIGHT("0000"&B2,5) -> 00001 | D2: =IF(AND(EXACT(LEN(TRIM(H2)),0), EXACT(LEN(TRIM(G2)),0)),"",A2&"_"&VLOOKUP(E2,Valores!$D$3:$E$4,2,FALSE)&"_"&VLOOKUP(F2,Valores!$A$3:$B$8,2,FALSE)&"_"&C2) -> Envio_USU_EXI_00001 | E2: Usuario final | F2: Éxito | G2: Envío registrado | H2: Se registró el envío para la venta #${0} con fecha ${1} y estado “Pendiente”. Quedó asociado correctamente a la venta. | I2: ${0}: Consecutivo/código de la venta; ${1}: Fecha de envío
A3: Envio | B3: 2 | C3: =RIGHT("0000"&B3,5) -> 00002 | D3: =IF(AND(EXACT(LEN(TRIM(H3)),0), EXACT(LEN(TRIM(G3)),0)),"",A3&"_"&VLOOKUP(E3,Valores!$D$3:$E$4,2,FALSE)&"_"&VLOOKUP(F3,Valores!$A$3:$B$8,2,FALSE)&"_"&C3) -> Envio_USU_ERR_00002 | E3: Usuario final | F3: Error | G3: Dato requerido no diligenciado | H3: Debes registrar un valor para el campo “${0}”, el cual es obligatorio. | I3: ${0}: Nombre del campo (Fecha/Dirección/Valor/Estado)
A4: Envio | B4: 3 | C4: =RIGHT("0000"&B4,5) -> 00003 | D4: =IF(AND(EXACT(LEN(TRIM(H4)),0), EXACT(LEN(TRIM(G4)),0)),"",A4&"_"&VLOOKUP(E4,Valores!$D$3:$E$4,2,FALSE)&"_"&VLOOKUP(F4,Valores!$A$3:$B$8,2,FALSE)&"_"&C4) -> Envio_USU_ERR_00003 | E4: Usuario final | F4: Error | G4: Fecha de envío inválida | H4: La fecha de envío ${0} es anterior a la fecha de la venta ${1}. Ajusta la fecha para continuar. | I4: ${0}: Fecha de envío; ${1}: Fecha de la venta
A5: Envio | B5: 4 | C5: =RIGHT("0000"&B5,5) -> 00004 | D5: =IF(AND(EXACT(LEN(TRIM(H5)),0), EXACT(LEN(TRIM(G5)),0)),"",A5&"_"&VLOOKUP(E5,Valores!$D$3:$E$4,2,FALSE)&"_"&VLOOKUP(F5,Valores!$A$3:$B$8,2,FALSE)&"_"&C5) -> Envio_USU_INF_00004 | E5: Usuario final | F5: Información | G5: Envíos asociados a la venta | H5: Se han registrado ${0} envío(s) asociados a la venta #${1}. | I5: ${0}: Número total de envíos; ${1}: Consecutivo/código de la venta
A8: Actualizar Envio HU32
A10: Modelo | B10: Número Mensaje | C10: Número Mensaje | D10: Código mensaje | E10: Tipo | F10: Categoría Mensaje | G10: Título Mensaje | H10: Contenido Mensaje | I10: Parámetros
A11: Envio | B11: 5 | C11: =RIGHT("0000"&B11,5) -> 00005 | D11: =IF(AND(EXACT(LEN(TRIM(H11)),0), EXACT(LEN(TRIM(G11)),0)),"",A11&"_"&VLOOKUP(E11,Valores!$D$3:$E$4,2,FALSE)&"_"&VLOOKUP(F11,Valores!$A$3:$B$8,2,FALSE)&"_"&C11) -> Envio_USU_EXI_00005 | E11: Usuario final | F11: Éxito | G11: Envío actualizado | H11: El envío #${0} de la venta #${1} fue actualizado correctamente. Los cambios ya se reflejan en la venta asociada y en el listado de envíos. | I11: ${0}: Consecutivo/código del envío; ${1}: Consecutivo/código de la venta
A12: Envio | B12: 6 | C12: =RIGHT("0000"&B12,5) -> 00006 | D12: =IF(AND(EXACT(LEN(TRIM(H12)),0), EXACT(LEN(TRIM(G12)),0)),"",A12&"_"&VLOOKUP(E12,Valores!$D$3:$E$4,2,FALSE)&"_"&VLOOKUP(F12,Valores!$A$3:$B$8,2,FALSE)&"_"&C12) -> Envio_USU_INF_00006 | E12: Usuario final | F12: Información | G12: Edición restringida por estado | H12: El envío está en estado “${0}”. Solo es posible editar campos no críticos (${1}). Los datos clave (destino, fecha, vehículo) no se pueden modificar. | I12: ${0}: Estado (Entregado/Cancelado); ${1}: Campos editables permitidos (precio, observaciones)

Sheet CatalogoMensajes Producto
A1: Modelo | B1: Número Mensaje | C1: Número Mensaje | D1: Código mensaje | E1: Tipo | F1: Categoría Mensaje | G1: Título Mensaje | H1: Contenido Mensaje | I1: Parámetros
A2: Producto | B2: 1 | C2: =RIGHT("0000"&B2,5) -> 00001 | D2: =IF(AND(EXACT(LEN(TRIM(H2)),0), EXACT(LEN(TRIM(G2)),0)),"",A2&"_"&VLOOKUP(E2,Valores!$D$3:$E$4,2,FALSE)&"_"&VLOOKUP(F2,Valores!$A$3:$B$8,2,FALSE)&"_"&C2) -> Producto_USU_EXI_00001 | E2: Usuario final | F2: Éxito | G2: ¡Producto registrado exitosamente! | H2: El producto “${0}” fue creado correctamente y ya esta disponible catálogo de productos. | I2: ${0}: Nombre del producto
A3: Producto | B3: 2 | C3: =RIGHT("0000"&B3,5) -> 00002 | D3: =IF(AND(EXACT(LEN(TRIM(H3)),0), EXACT(LEN(TRIM(G3)),0)),"",A3&"_"&VLOOKUP(E3,Valores!$D$3:$E$4,2,FALSE)&"_"&VLOOKUP(F3,Valores!$A$3:$B$8,2,FALSE)&"_"&C3) -> Producto_USU_ERR_00002 | E3: Usuario final | F3: Error | G3: Producto ya existente | H3: Ya existe un producto con el nombre “${0}”. No se permite registrar duplicados. | I3: ${0}: Nombre del producto
A4: Producto | B4: 3 | C4: =RIGHT("0000"&B4,5) -> 00003 | D4: =IF(AND(EXACT(LEN(TRIM(H4)),0), EXACT(LEN(TRIM(G4)),0)),"",A4&"_"&VLOOKUP(E4,Valores!$D$3:$E$4,2,FALSE)&"_"&VLOOKUP(F4,Valores!$A$3:$B$8,2,FALSE)&"_"&C4) -> Producto_USU_ERR_00003 | E4: Usuario final | F4: Error | G4: Dato requerido no diligenciado | H4: Debes registrar un valor para el campo “${0}”, el cual es obligatorio. | I4: ${0}: Nombre del campo (Nombre/UnidadMedida/PrecioUnitario/Stock/Estado/Categoría)
A5: Producto | B5: 4 | C5: =RIGHT("0000"&B5,5) -> 00004 | D5: =IF(AND(EXACT(LEN(TRIM(H5)),0), EXACT(LEN(TRIM(G5)),0)),"",A5&"_"&VLOOKUP(E5,Valores!$D$3:$E$4,2,FALSE)&"_"&VLOOKUP(F5,Valores!$A$3:$B$8,2,FALSE)&"_"&C5) -> Producto_USU_ERR_00004 | E5: Usuario final | F5: Error | G5: Valor inválido (debe ser positivo) | H5: El campo “${0}” debe ser un número positivo. Valor ingresado: ${1}. No se guardó el producto. | I5: ${0}: Campo (PrecioUnitario/Stock); ${1}: Valor ingresado
A8: Actualizar Producto HU 12
A10: Modelo | B10: Número Mensaje | C10: Número Mensaje | D10: Código mensaje | E10: Tipo | F10: Categoría Mensaje | G10: Título Mensaje | H10: Contenido Mensaje | I10: Parámetros
A11: Producto | B11: 5 | C11: =RIGHT("0000"&B11,5) -> 00005 | D11: =IF(AND(EXACT(LEN(TRIM(H11)),0), EXACT(LEN(TRIM(G11)),0)),"",A11&"_"&VLOOKUP(E11,Valores!$D$3:$E$4,2,FALSE)&"_"&VLOOKUP(F11,Valores!$A$3:$B$8,2,FALSE)&"_"&C11) -> Producto_USU_EXI_00005 | E11: Usuario final | F11: Éxito | G11: Producto actualizado | H11: El producto “${0}” fue actualizado correctamente. | I11: ${0}: Nombre del producto
A12: Producto | B12: 6 | C12: =RIGHT("0000"&B12,5) -> 00006 | D12: =IF(AND(EXACT(LEN(TRIM(H12)),0), EXACT(LEN(TRIM(G12)),0)),"",A12&"_"&VLOOKUP(E12,Valores!$D$3:$E$4,2,FALSE)&"_"&VLOOKUP(F12,Valores!$A$3:$B$8,2,FALSE)&"_"&C12) -> Producto_USU_ERR_00006 | E12: Usuario final | F12: Error | G12: Error de validación de campo | H12: El campo “${0}” es inválido. Detalle: ${1}. | I12: ${0}: Nombre del campo; ${1}: Descripción del error (formato/rango/longitud, etc.)
A15: Modificar estado producto HU 30
A17: Modelo | B17: Número Mensaje | C17: Número Mensaje | D17: Código mensaje | E17: Tipo | F17: Categoría Mensaje | G17: Título Mensaje | H17: Contenido Mensaje | I17: Parámetros
A18: Producto | B18: 7 | C18: =RIGHT("0000"&B18,5) -> 00007 | D18: =IF(AND(EXACT(LEN(TRIM(H18)),0), EXACT(LEN(TRIM(G18)),0)),"",A18&"_"&VLOOKUP(E18,Valores!$D$3:$E$4,2,FALSE)&"_"&VLOOKUP(F18,Valores!$A$3:$B$8,2,FALSE)&"_"&C18) -> Producto_USU_EXI_00007 | E18: Usuario final | F18: Éxito | G18: Estado de producto actualizado | H18: El estado del producto “${0}” fue actualizado de ${1} a ${2}. | I18: ${0}: Nombre del producto; ${1}: Estado anterior; ${2}: Nuevo estado
A19: Producto | B19: 8 | C19: =RIGHT("0000"&B19,5) -> 00008 | D19: =IF(AND(EXACT(LEN(TRIM(H19)),0), EXACT(LEN(TRIM(G19)),0)),"",A19&"_"&VLOOKUP(E19,Valores!$D$3:$E$4,2,FALSE)&"_"&VLOOKUP(F19,Valores!$A$3:$B$8,2,FALSE)&"_"&C19) -> Producto_USU_ADV_00008 | E19: Usuario final | F19: Advertencia | G19: Acción no permitida | H19: No tienes permisos para modificar el estado de productos. Esta acción está habilitada únicamente para el rol Administrador. | I19: –

Sheet CatalogoMensajes Produccion
A1: Modelo | B1: Número Mensaje | C1: Número Mensaje | D1: Código mensaje | E1: Tipo | F1: Categoría Mensaje | G1: Título Mensaje | H1: Contenido Mensaje | I1: Parámetros
A2: Produccion | B2: 1 | C2: =RIGHT("0000"&B2,5) -> 00001 | D2: =IF(AND(EXACT(LEN(TRIM(H2)),0), EXACT(LEN(TRIM(G2)),0)),"",A2&"_"&VLOOKUP(E2,Valores!$D$3:$E$4,2,FALSE)&"_"&VLOOKUP(F2,Valores!$A$3:$B$8,2,FALSE)&"_"&C2) -> Produccion_USU_EXI_00001 | E2: Usuario final | F2: Éxito | G2: Producción creada | H2: Se registró la producción de ${0} unidad(es) del producto “${1}” para la fecha ${2}. Se descontaron los insumos y se actualizó el stock del producto. | I2: ${0}: Cantidad producida; ${1}: Producto; ${2}: Fecha
A3: Produccion | B3: 2 | C3: =RIGHT("0000"&B3,5) -> 00002 | D3: =IF(AND(EXACT(LEN(TRIM(H3)),0), EXACT(LEN(TRIM(G3)),0)),"",A3&"_"&VLOOKUP(E3,Valores!$D$3:$E$4,2,FALSE)&"_"&VLOOKUP(F3,Valores!$A$3:$B$8,2,FALSE)&"_"&C3) -> Produccion_USU_ERR_00002 | E3: Usuario final | F3: Error | G3: Registro de producción duplicado | H3: Ya existe un registro de producción para el producto “${0}” en la fecha ${1}. No se permiten duplicados. | I3: ${0}: Producto; ${1}: Fecha
A4: Produccion | B4: 3 | C4: =RIGHT("0000"&B4,5) -> 00003 | D4: =IF(AND(EXACT(LEN(TRIM(H4)),0), EXACT(LEN(TRIM(G4)),0)),"",A4&"_"&VLOOKUP(E4,Valores!$D$3:$E$4,2,FALSE)&"_"&VLOOKUP(F4,Valores!$A$3:$B$8,2,FALSE)&"_"&C4) -> Produccion_USU_ERR_00003 | E4: Usuario final | F4: Error | G4: Error de validación de campo | H4: El campo “${0}” es inválido. Detalle: ${1}. | I4: ${0}: Nombre del campo; ${1}: Descripción del error (formato/rango/existencia, etc.)
A5: Produccion | B5: 4 | C5: =RIGHT("0000"&B5,5) -> 00004 | D5: =IF(AND(EXACT(LEN(TRIM(H5)),0), EXACT(LEN(TRIM(G5)),0)),"",A5&"_"&VLOOKUP(E5,Valores!$D$3:$E$4,2,FALSE)&"_"&VLOOKUP(F5,Valores!$A$3:$B$8,2,FALSE)&"_"&C5) -> Produccion_USU_ERR_00004 | E5: Usuario final | F5: Error | G5: Cantidad producida inválida | H5: La cantidad producida debe ser un número mayor que cero. Valor ingresado: ${0}. | I5: ${0}: Cantidad ingresada
A6: Produccion | B6: 5 | C6: =RIGHT("0000"&B6,5) -> 00005 | D6: =IF(AND(EXACT(LEN(TRIM(H6)),0), EXACT(LEN(TRIM(G6)),0)),"",A6&"_"&VLOOKUP(E6,Valores!$D$3:$E$4,2,FALSE)&"_"&VLOOKUP(F6,Valores!$A$3:$B$8,2,FALSE)&"_"&C6) -> Produccion_USU_ERR_00005 | E6: Usuario final | F6: Error | G6: Insumos insuficientes | H6: No hay insumos suficientes para producir ${0} de “${1}”. Insumo afectado: ${2}. Requerido: ${3}. Disponible: ${4}. Corrige lo valores | I6: ${0}: Cantidad a producir; ${1}: Producto; ${2}: Insumo; ${3}: Cantidad requerida; ${4}: Cantidad disponible
A8: Actualizar producción HU 16
A10: Modelo | B10: Número Mensaje | C10: Número Mensaje | D10: Código mensaje | E10: Tipo | F10: Categoría Mensaje | G10: Título Mensaje | H10: Contenido Mensaje | I10: Parámetros
A11: Produccion | B11: 6 | C11: =RIGHT("0000"&B11,5) -> 00006 | D11: =IF(AND(EXACT(LEN(TRIM(H11)),0), EXACT(LEN(TRIM(G11)),0)),"",A11&"_"&VLOOKUP(E11,Valores!$D$3:$E$4,2,FALSE)&"_"&VLOOKUP(F11,Valores!$A$3:$B$8,2,FALSE)&"_"&C11) -> Produccion_USU_EXI_00006 | E11: Usuario final | F11: Éxito | G11: Producción actualizada | H11: La producción #${0} del producto “${1}” fue actualizada correctamente. Se ajustaron los stocks del producto e insumos según el cambio. | I11: ${0}: Código/consecutivo de la producción; ${1}: Producto
A12: Produccion | B12: 7 | C12: =RIGHT("0000"&B12,5) -> 00007 | D12: =IF(AND(EXACT(LEN(TRIM(H12)),0), EXACT(LEN(TRIM(G12)),0)),"",A12&"_"&VLOOKUP(E12,Valores!$D$3:$E$4,2,FALSE)&"_"&VLOOKUP(F12,Valores!$A$3:$B$8,2,FALSE)&"_"&C12) -> Produccion_USU_ERR_00007 | E12: Usuario final | F12: Error | G12: Disminución supera stock disponible | H12: No es posible disminuir ${0} unidad(es) del producto “${1}” porque solo hay ${2} disponible en stock. Ajusta la cantidad. No se guardaron cambios. | I12: ${0}: Cantidad a disminuir; ${1}: Producto; ${2}: Stock disponible
A13: Produccion | B13: 8 | C13: =RIGHT("0000"&B13,5) -> 00008 | D13: =IF(AND(EXACT(LEN(TRIM(H13)),0), EXACT(LEN(TRIM(G13)),0)),"",A13&"_"&VLOOKUP(E13,Valores!$D$3:$E$4,2,FALSE)&"_"&VLOOKUP(F13,Valores!$A$3:$B$8,2,FALSE)&"_"&C13) -> Produccion_USU_INF_00008 | E13: Usuario final | F13: Información | G13: Insumos devueltos al stock | H13: Se devolvieron ${0} unidad(es) de insumos al stock para la producción #${1}. | I13: ${0}: Total de unidades devueltas; ${1}: Código/consecutivo de la producción
A14: Produccion | B14: 9 | C14: =RIGHT("0000"&B14,5) -> 00009 | D14: =IF(AND(EXACT(LEN(TRIM(H14)),0), EXACT(LEN(TRIM(G14)),0)),"",A14&"_"&VLOOKUP(E14,Valores!$D$3:$E$4,2,FALSE)&"_"&VLOOKUP(F14,Valores!$A$3:$B$8,2,FALSE)&"_"&C14) -> Produccion_USU_ERR_00009 | E14: Usuario final | F14: Error | G14: Stock insuficiente (defectuosos) | H14: El incremento de Cantidad_Defectuosas (Δ = ${0}) supera el stock disponible del producto “${1}”. Disponible: ${2}. Corrige los valores. | I14: ${0}: Diferencia nuevo−anterior; ${1}: Producto; ${2}: Stock disponible del producto
A16: Eliminar producción HU 17
A18: Modelo | B18: Número Mensaje | C18: Número Mensaje | D18: Código mensaje | E18: Tipo | F18: Categoría Mensaje | G18: Título Mensaje | H18: Contenido Mensaje | I18: Parámetros
A19: Produccion | B19: 10 | C19: =RIGHT("0000"&B19,5) -> 00010 | D19: =IF(AND(EXACT(LEN(TRIM(H19)),0), EXACT(LEN(TRIM(G19)),0)),"",A19&"_"&VLOOKUP(E19,Valores!$D$3:$E$4,2,FALSE)&"_"&VLOOKUP(F19,Valores!$A$3:$B$8,2,FALSE)&"_"&C19) -> Produccion_USU_EXI_00010 | E19: Usuario final | F19: Éxito | G19: Producción eliminada | H19: La producción #${0} del producto “${1}” fue eliminada correctamente. Se revirtieron los movimientos de inventario (−${2} al producto fabricado y +${3} a los insumos). | I19: ${0}: Código/consecutivo de la producción; ${1}: Producto; ${2}: Cantidad fabricada revertida; ${3}: Total de insumos devueltos

Sheet CatalogoMensajes Proveedor
A1: Modelo | B1: Número Mensaje | C1: Número Mensaje | D1: Código mensaje | E1: Tipo | F1: Categoría Mensaje | G1: Título Mensaje | H1: Contenido Mensaje | I1: Parámetros
A2: Proveedor | B2: 1 | C2: =RIGHT("0000"&B2,5) -> 00001 | D2: =IF(AND(EXACT(LEN(TRIM(H2)),0), EXACT(LEN(TRIM(G2)),0)),"",A2&"_"&VLOOKUP(E2,Valores!$D$3:$E$4,2,FALSE)&"_"&VLOOKUP(F2,Valores!$A$3:$B$8,2,FALSE)&"_"&C2) -> Proveedor_USU_EXI_00001 | E2: Usuario final | F2: Éxito | G2: ¡Proveedor registrado exitosamente! | H2: El proveedor “${0}” (Tipo: ${1}, Doc.: ${2}-${3}) fue registrado correctamente. | I2: ${0}: Nombre mostrado (Razón social o Nombre completo); ${1}: Tipo de proveedor (Persona jurídica/Natural); ${2}: Tipo de documento; ${3}: Número de documento
A3: Proveedor | B3: 2 | C3: =RIGHT("0000"&B3,5) -> 00002 | D3: =IF(AND(EXACT(LEN(TRIM(H3)),0), EXACT(LEN(TRIM(G3)),0)),"",A3&"_"&VLOOKUP(E3,Valores!$D$3:$E$4,2,FALSE)&"_"&VLOOKUP(F3,Valores!$A$3:$B$8,2,FALSE)&"_"&C3) -> Proveedor_USU_ERR_00002 | E3: Usuario final | F3: Error | G3: Documento duplicado | H3: Ya existe un proveedor con el tipo y número de documento ${2}-“${3}”. | I3: ${2}: Tipo de documento; ${3}: Número de documento
A4: Proveedor | B4: 3 | C4: =RIGHT("0000"&B4,5) -> 00003 | D4: =IF(AND(EXACT(LEN(TRIM(H4)),0), EXACT(LEN(TRIM(G4)),0)),"",A4&"_"&VLOOKUP(E4,Valores!$D$3:$E$4,2,FALSE)&"_"&VLOOKUP(F4,Valores!$A$3:$B$8,2,FALSE)&"_"&C4) -> Proveedor_USU_ERR_00003 | E4: Usuario final | F4: Error | G4: Razón social obligatoria | H4: Para persona jurídica, el campo Razón social es obligatorio. No se guardó el registro. | I4: –
A5: Proveedor | B5: 4 | C5: =RIGHT("0000"&B5,5) -> 00004 | D5: =IF(AND(EXACT(LEN(TRIM(H5)),0), EXACT(LEN(TRIM(G5)),0)),"",A5&"_"&VLOOKUP(E5,Valores!$D$3:$E$4,2,FALSE)&"_"&VLOOKUP(F5,Valores!$A$3:$B$8,2,FALSE)&"_"&C5) -> Proveedor_USU_ERR_00004 | E5: Usuario final | F5: Error | G5: Nombre completo solo para persona natural | H5: El campo Nombre completo solo se permite para persona natural. Para persona jurídica, usa Razón social. | I5: –
A6: Proveedor | B6: 5 | C6: =RIGHT("0000"&B6,5) -> 00005 | D6: =IF(AND(EXACT(LEN(TRIM(H6)),0), EXACT(LEN(TRIM(G6)),0)),"",A6&"_"&VLOOKUP(E6,Valores!$D$3:$E$4,2,FALSE)&"_"&VLOOKUP(F6,Valores!$A$3:$B$8,2,FALSE)&"_"&C6) -> Proveedor_USU_ERR_00005 | E6: Usuario final | F6: Error | G6: Formato de correo inválido | H6: El correo “${0}” tiene un formato inválido o contiene caracteres no permitidos. | I6: ${0}: Correo ingresado
A7: Proveedor | B7: 6 | C7: =RIGHT("0000"&B7,5) -> 00006 | D7: =IF(AND(EXACT(LEN(TRIM(H7)),0), EXACT(LEN(TRIM(G7)),0)),"",A7&"_"&VLOOKUP(E7,Valores!$D$3:$E$4,2,FALSE)&"_"&VLOOKUP(F7,Valores!$A$3:$B$8,2,FALSE)&"_"&C7) -> Proveedor_USU_ERR_00006 | E7: Usuario final | F7: Error | G7: Celular debe ser numérico | H7: El campo Celular debe ser numérico. Valor ingresado: “${0}”. | I7: ${0}: Valor ingresado
A8: Proveedor | B8: 7 | C8: =RIGHT("0000"&B8,5) -> 00007 | D8: =IF(AND(EXACT(LEN(TRIM(H8)),0), EXACT(LEN(TRIM(G8)),0)),"",A8&"_"&VLOOKUP(E8,Valores!$D$3:$E$4,2,FALSE)&"_"&VLOOKUP(F8,Valores!$A$3:$B$8,2,FALSE)&"_"&C8) -> Proveedor_USU_ERR_00007 | E8: Usuario final | F8: Error | G8: Campos obligatorios incompletos | H8: Faltan campos obligatorios según el tipo de proveedor: ${0}. Completa la información para continuar. | I8: ${0}: Lista de campos faltantes
A10: Actualizar proveedor HU 22
A12: Modelo | B12: Número Mensaje | C12: Número Mensaje | D12: Código mensaje | E12: Tipo | F12: Categoría Mensaje | G12: Título Mensaje | H12: Contenido Mensaje | I12: Parámetros
A13: Proveedor | B13: 8 | C13: =RIGHT("0000"&B13,5) -> 00008 | D13: =IF(AND(EXACT(LEN(TRIM(H13)),0), EXACT(LEN(TRIM(G13)),0)),"",A13&"_"&VLOOKUP(E13,Valores!$D$3:$E$4,2,FALSE)&"_"&VLOOKUP(F13,Valores!$A$3:$B$8,2,FALSE)&"_"&C13) -> Proveedor_USU_EXI_00008 | E13: Usuario final | F13: Éxito | G13: Proveedor actualizado | H13: El proveedor “${0}” fue actualizado correctamente. | I13: ${0}: Nombre mostrado (Razón social o Nombre completo)
A14: Proveedor | B14: 9 | C14: =RIGHT("0000"&B14,5) -> 00009 | D14: =IF(AND(EXACT(LEN(TRIM(H14)),0), EXACT(LEN(TRIM(G14)),0)),"",A14&"_"&VLOOKUP(E14,Valores!$D$3:$E$4,2,FALSE)&"_"&VLOOKUP(F14,Valores!$A$3:$B$8,2,FALSE)&"_"&C14) -> Proveedor_USU_ADV_00009 | E14: Usuario final | F14: Advertencia | G14: Edición bloqueada: proveedor inactivo | H14: El proveedor “${0}” se encuentra inactivo. No es posible editar su información. Actívalo para habilitar la edición. | I14: ${0}: Nombre mostrado
A15: Proveedor | B15: 10 | C15: =RIGHT("0000"&B15,5) -> 00010 | D15: =IF(AND(EXACT(LEN(TRIM(H15)),0), EXACT(LEN(TRIM(G15)),0)),"",A15&"_"&VLOOKUP(E15,Valores!$D$3:$E$4,2,FALSE)&"_"&VLOOKUP(F15,Valores!$A$3:$B$8,2,FALSE)&"_"&C15) -> Proveedor_USU_ERR_00010 | E15: Usuario final | F15: Error | G15: Error de validación de campo | H15: El campo “${0}” es inválido. Detalle: ${1}. | I15: ${0}: Nombre del campo; ${1}: Descripción del error (formato/rango/longitud, etc.)
A17: Modificar estado proveedor HU31
A19: Modelo | B19: Número Mensaje | C19: Número Mensaje | D19: Código mensaje | E19: Tipo | F19: Categoría Mensaje | G19: Título Mensaje | H19: Contenido Mensaje | I19: Parámetros
A20: Proveedor | B20: 11 | C20: =RIGHT("0000"&B20,5) -> 00011 | D20: =IF(AND(EXACT(LEN(TRIM(H20)),0), EXACT(LEN(TRIM(G20)),0)),"",A20&"_"&VLOOKUP(E20,Valores!$D$3:$E$4,2,FALSE)&"_"&VLOOKUP(F20,Valores!$A$3:$B$8,2,FALSE)&"_"&C20) -> Proveedor_USU_EXI_00011 | E20: Usuario final | F20: Éxito | G20: Estado de proveedor actualizado | H20: El estado del proveedor “${0}” fue actualizado de ${1} a ${2}. El cambio ya se refleja en la lista y en las reglas de selección para abastecimientos. | I20: ${0}: Nombre del proveedor; ${1}: Estado anterior (Habilitado/Inhabilitado); ${2}: Nuevo estado (Habilitado/Inhabilitado)
A21: Proveedor | B21: 12 | C21: =RIGHT("0000"&B21,5) -> 00012 | D21: =IF(AND(EXACT(LEN(TRIM(H21)),0), EXACT(LEN(TRIM(G21)),0)),"",A21&"_"&VLOOKUP(E21,Valores!$D$3:$E$4,2,FALSE)&"_"&VLOOKUP(F21,Valores!$A$3:$B$8,2,FALSE)&"_"&C21) -> Proveedor_USU_ADV_00012 | E21: Usuario final | F21: Advertencia | G21: Acción no permitida | H21: No tienes permisos para modificar el estado de proveedores. Esta acción está disponible únicamente para el rol Administrador. | I21: –

Sheet CatalogoMensajes Categoria
A1: Modelo | B1: Número Mensaje | C1: Número Mensaje | D1: Código mensaje | E1: Tipo | F1: Categoría Mensaje | G1: Título Mensaje | H1: Contenido Mensaje | I1: Parámetros
A2: Categoria | B2: 1 | C2: =RIGHT("0000"&B2,5) -> 00001 | D2: =IF(AND(EXACT(LEN(TRIM(H2)),0), EXACT(LEN(TRIM(G2)),0)),"",A2&"_"&VLOOKUP(E2,Valores!$D$3:$E$4,2,FALSE)&"_"&VLOOKUP(F2,Valores!$A$3:$B$8,2,FALSE)&"_"&C2) -> Categoria_USU_EXI_00001 | E2: Usuario final | F2: Éxito | G2: ¡Categoría registrada exitosamente! | H2: La categoría “${0}” fue creada correctamente. | I2: ${0}: Nombre de la categoría
A3: Categoria | B3: 2 | C3: =RIGHT("0000"&B3,5) -> 00002 | D3: =IF(AND(EXACT(LEN(TRIM(H3)),0), EXACT(LEN(TRIM(G3)),0)),"",A3&"_"&VLOOKUP(E3,Valores!$D$3:$E$4,2,FALSE)&"_"&VLOOKUP(F3,Valores!$A$3:$B$8,2,FALSE)&"_"&C3) -> Categoria_USU_ERR_00002 | E3: Usuario final | F3: Error | G3: Campo obligatorio faltante | H3: Faltan campos obligatorios: ${0}. Completa la información para continuar. | I3: ${0}: Lista de campos faltantes (p. ej., Nombre)
A4: Categoria | B4: 3 | C4: =RIGHT("0000"&B4,5) -> 00003 | D4: =IF(AND(EXACT(LEN(TRIM(H4)),0), EXACT(LEN(TRIM(G4)),0)),"",A4&"_"&VLOOKUP(E4,Valores!$D$3:$E$4,2,FALSE)&"_"&VLOOKUP(F4,Valores!$A$3:$B$8,2,FALSE)&"_"&C4) -> Categoria_USU_ERR_00003 | E4: Usuario final | F4: Error | G4: Nombre de categoría duplicado | H4: Ya existe una categoría con el nombre “${0}”. No se permite duplicidad. | I4: ${0}: Nombre de la categoría
A6: Actualizar proveedor HU 22
A8: Modelo | B8: Número Mensaje | C8: Número Mensaje | D8: Código mensaje | E8: Tipo | F8: Categoría Mensaje | G8: Título Mensaje | H8: Contenido Mensaje | I8: Parámetros
A9: Categoria | B9: 4 | C9: =RIGHT("0000"&B9,5) -> 00004 | D9: =IF(AND(EXACT(LEN(TRIM(H9)),0), EXACT(LEN(TRIM(G9)),0)),"",A9&"_"&VLOOKUP(E9,Valores!$D$3:$E$4,2,FALSE)&"_"&VLOOKUP(F9,Valores!$A$3:$B$8,2,FALSE)&"_"&C9) -> Categoria_USU_EXI_00004 | E9: Usuario final | F9: Éxito | G9: ¡Categoría actualizada exitosamente! | H9: La categoría “${0}” fue actualizada correctamente. La lista de categorías se actualizó de inmediato. | I9: ${0}: Nombre de la categoría

Sheet CatalogoMensajesPersona
A1: Modelo | B1: Número Mensaje | C1: Número Mensaje | D1: Código mensaje | E1: Tipo | F1: Categoría Mensaje | G1: Título Mensaje | H1: Contenido Mensaje | I1: Parámetros
A2: Persona | B2: 1 | C2: =RIGHT("0000"&B2,5) -> 00001 | D2: =IF(AND(EXACT(LEN(TRIM(H2)),0), EXACT(LEN(TRIM(G2)),0)),"",A2&"_"&VLOOKUP(E2,Valores!$D$3:$E$4,2,FALSE)&"_"&VLOOKUP(F2,Valores!$A$3:$B$8,2,FALSE)&"_"&C2) -> Persona_USU_EXI_00001 | E2: Usuario final | F2: Éxito | G2: ¡Persona registrada exitosamente! | H2: La Persona“${0}” fue creada correctamente. | I2: ${0}: Nombre de la persona
A4: Actualizar proveedor HU 22
A6: Modelo | B6: Número Mensaje | C6: Número Mensaje | D6: Código mensaje | E6: Tipo | F6: Categoría Mensaje | G6: Título Mensaje | H6: Contenido Mensaje | I6: Parámetros
A7: Persona | B7: 2 | C7: =RIGHT("0000"&B7,5) -> 00002 | D7: =IF(AND(EXACT(LEN(TRIM(H7)),0), EXACT(LEN(TRIM(G7)),0)),"",A7&"_"&VLOOKUP(E7,Valores!$D$3:$E$4,2,FALSE)&"_"&VLOOKUP(F7,Valores!$A$3:$B$8,2,FALSE)&"_"&C7) -> Persona_USU_EXI_00002 | E7: Usuario final | F7: Éxito | G7: ¡Persona actualizada exitosamente! | H7: La Persona“${0}” fue actualizada correctamente. | I7: ${0}: Nombre de la persona
