Workbook

Sheet Modelo de dominio anémico

Sheet Listado Objetos de Dominio
A1: Nombre | B1: Muestreo | C1: Descripción
A2: Proveedor | B2: <<muestreo>> | C2: Entidad que representa a las empresas o personas que suministran el abastecimiento del negocio.
A3: Administrador | B3: <<muestreo>> | C3: Entidad que representa Usuario con privilegios totales sobre la plataforma. Se encarga de configurar parámetros globales, gestionar roles y permisos de Trabajadores y supervisar la generación de Reportes.
A4: Abastecimiento | B4: <<muestreo>> | C4: Proceso y registro de la adquisición interna de insumos para producción. Documenta las órdenes de compra, fechas de entrega, cantidades solicitadas y precios que alimentaran el Inventario
A5: Reporte | B5: <<muestreo>> | C5: Informe que consolida información de los distintos procesos (ventas, compras/abastecimientos, producción, inventario). Generado por Administradores o Trabajadores para apoyar la toma de decisiones estratégicas.
A6: Trabajador | B6: <<muestreo>> | C6: Empleado del negocio que dispone de un Usuario en el sistema. Ejecuta operaciones como registrar Ventas, registrar Producción, gestionar Abastecimientos y atender consultas.
A7: Cliente | B7: <<muestreo>> | C7: Comprador de bloques y materiales. Registra datos de contacto, histórico de pedidos, métodos de pago y preferencias de entrega. Puede interactuar con el portal para ver catálogo y solicitar atención.
A8: Información de interes | B8: <<muestreo>> | C8: Hace referencia a la información relevante sobre el perfil y finalidad del cliente en relación con los productos, incluyendo el uso previsto y su rol dentro del sector, como constructor, contratista, revendedor, entre otros
A9: Producción | B9: <<muestreo>> | C9: Registro diario de bloques fabricados: cantidad producida, lote, fecha, insumos y trabajadores responsables.
A10: Producto | B10: <<muestreo>> | C10: Definición de cada artículo que el negocio ofrece a sus clientes.
A11: Venta | B11: <<muestreo>> | C11: Corresponde a la transaccion comercial en la que un cliente adquiere uno o mas productos o servicios a cambio de un pago.
A12: Estado Producto | B12: <<muestreo>> | C12: Corresponde a cada uno de los tipos de estados que puede tener un producto.
... A26: Devolución | B26: <<muestreo>> | C26: Registra la devolución total o parcial de productos de una Venta, con su motivo y el ajuste de inventario correspondiente.

Sheet Pago
A1: <-Volver al inicio
A2: Objeto de Dominio: | B2: ='Listado Objetos de Dominio'!A23 -> Pago
A3: Descripción: | B3: ='Listado Objetos de Dominio'!$C$23 -> Objeto de dominio que representa el pago a una venta
A4: Atributo | B4: Tipo de Dato | C4: Longitud mínima | D4: Longitud máxima | E4: Precisión | F4: Rango Inicial | G4: Rango Final | H4: Formato | I4: Valor por defecto | J4: Regla especial | K4: ¿Auto generado? | L4: ¿Calculado? | M4: ¿Obligatorio? | N4: ¿Sensible? | O4: ¿Identifica al registro? | P4: Descripción | Q4: =A20 -> Generar Pago | R4: =A21 -> Consultar Pago | S4: =A22 -> Editar Pago
A5: IdPago | B5: Numerico | D5: 36 | J5: Único en el sistema | M5: Si | N5: No | O5: SI | P5: Identificador único del pago | Q5: Si | R5: Si | S5: Si
A6: Monto | B6: Numerico | E6: 2 | H6: Decimal | J6: Debe ser mayor que cero | M6: Si | N6: No | O6: No | P6: Monto pagado | Q6: Si | R6: Si | S6: Si
A7: Forma_pago | B7: Forma de pago | H7: FK | J7: Debe existir en el catálogo de formas de pago | M7: Si | N7: No | O7: No | P7: Forma de pago utilizada (Efectivo, tarjeta, etc) | Q7: Si | R7: Si | S7: Si
A8: Observaciones | B8: Texto | D8: 250 | H8: Texto | J8: Texto libre | K8: No | L8: No | M8: No | N8: No | O8: No | P8: Comentarios adicionales al pago | Q8: Si | R8: Si | S8: Si
A9: Trabajador | B9: Trabajador | H9: FK | J9: Debe estar registrado en el sistema | M9: Si | N9: No | O9: No | P9: Usuario responsable del registro del pago | Q9: Si | R9: Si | S9: NO
A10: Venta | B10: Venta | C10: 1 | D10: 12 | H10: FK | J10: Relación obligatoria | M10: Si | N10: No | O10: No | P10: Venta a la que se asocia este pago | Q10: Si | R10: Si | S10: Si
A11: Fecha_pago | B11: Fecha | H11: Fecha | I11: Fecha actual | J11: No puede ser futura | M11: Si | N11: No | O11: No | P11: Fecha en la que se realizó el pago | Q11: Si | R11: Si | S11: Si
A12: Estado_pago | B12: Boolean | H12: Boolean | M12: Si | N12: No | O12: No | P12: Estado en el que se encuentra un pago | Q12: Si | R12: Si | S12: Si
A14: Combinaciones únicas
A15: Nombre combinación | B15: Descripción | C15: Atributos
A16: Codigo único | B16: Identificador único del pago | C16: Codigo
A18: Responsabilidad | C18: Descripción | G18: Entradas | J18: Salida | O18: Políticas (Reglas de Negocio) | Q18: Excepción
G19: Parámetro | H19: Tipo de dato | I19: Descripción | J19: Tipo de Dato | K19: Descripción | O19: Política | P19: Descripción | Q19: Detalle | R19: ¿Qué hago?
A20: Generar Pago | C20: Permite generar un pago a una venta | G20: Pago | H20: Pago | I20: Datos completos para generar el pago | J20: Pago | K20: Pago generado correctamente | O20: El monto de un pago no puede exceder el valor total de la venta. La suma de todos los pagos registrados no debe superar el total de la venta | P20: Completa los campos obligatorios, la suma de los pagos supera el monto total de la venta | Q20: EL monto total del pago excede el monto total de la venta, campos obligatorios faltantes, formato invalido | R20: Mostrar mensaje de error con el detalle
A21: Consultar Pago | C21: Permite consultar el pago | G21: Venta, Trabajador, Forma_pago | H21: Pago | I21: Información del pago | J21: Pago | K21: Permite consultar un pago por venta, trabajador y forma de pago | O21: Validar existencia de pago | P21: Validar que el pago asociado a la operación exista en el sistema antes de continuar | Q21: venta invalida, trabajador invalido y forma de pago no encontrada | R21: Mostrar mensaje de error con el detalle
A22: Editar Pago | C22: Permite modificar los datos de un pago registrado | G22: Monto | H22: Numerico | I22: Campos que se pueden modificar de un pago a realizado de una venta | J22: Pago | K22: Pago modificado exitosamente | O22: Verificar el estado de la venta no este completado No se permite ingresar datos negativos en el monto | P22: No se puede modificar un pago si la venta se encuentra en un estado completado y adicional en el monto a pagar no modificar con valores negativos o cero | Q22: Pago no modificable , por estado completado asociado de la venta, Valor negativo ingresado, venta completada | R22: Mostrar mensaje de error: No se puede modificar un pago de una venta en estado completado
G23: Forma_pago | H23: Forma de pago
G24: Observaciones | H24: Texto
G25: Venta | H25: Venta
G26: Fecha_pago | H26: Fecha
G27: Estado_pago | H27: Boolean
A28: <<Muestreo de datos>>

Sheet Muestreo Pago
A1: <-Volver al inicio
A3: Código | B3: Monto | C3: Forma_pago_ID | D3: Observaciones | E3: Trabajador_ID | F3: Venta_ID | G3: Fecha_pago
A4: 9001 | B4: 480000 | C4: 1 | D4: Pago realizado en efectivo | E4: TRB001 | F4: VNT001 | G4: 45787
A5: 9002 | B5: 320000 | C5: 3 | D5: Tarjeta débito | E5: TRB002 | F5: VNT002 | G5: 45788
A6: 9003 | B6: 150000 | C6: 2 | D6: Transferencia desde Bancolombia | E6: TRB001 | F6: VNT003 | G6: 45789
A7: 9004 | B7: 600000 | C7: 1 | D7: Pago parcial, queda pendiente | E7: TRB003 | F7: VNT004 | G7: 45790
A8: 9005 | B8: 800000 | C8: 2 | D8: Cliente solicitó factura | E8: TRB002 | F8: VNT005 | G8: 45791

Sheet Forma de pago
A1: <-Volver al inicio
A2: Objeto de Dominio: | B2: ='Listado Objetos de Dominio'!A24 -> Forma de pago
A3: Descripción: | B3: ='Listado Objetos de Dominio'!$C$24 -> Objeto de dominio que representa las diferentes formas de pago
A4: Atributo | B4: Tipo de Dato | C4: Longitud mínima | D4: Longitud máxima | E4: Precisión | F4: Rango Inicial | G4: Rango Final | H4: Formato | I4: Valor por defecto | J4: Regla especial | K4: ¿Auto generado? | L4: ¿Calculado? | M4: ¿Obligatorio? | N4: ¿Sensible? | O4: ¿Identifica al registro? | P4: Descripción
A5: Codigo | B5: Numerico | D5: 36 | H5: Entero | I5: Ninguno | J5: Único entre formas de pago | K5: Sí | L5: No | M5: Sí | N5: No | O5: Sí | P5: Código identificador de la forma de pago
A6: Nombre | B6: Alfanumerico | D6: 50 | H6: Texto | I6: Ninguno | J6: Debe ser único | K6: No | L6: No | M6: Sí | N6: No | O6: No | P6: Nombre representativo de la forma de pago (ej. "Efectivo")
A8: Combinaciones únicas
A9: Nombre combinación | B9: Descripción | C9: Atributos
A10: Codigo unico | B10: Codigo unico de una forma de pago | C10: Codigo
A12: <<Muestreo de datos>>

Sheet Muestreo Formas de pago
A1: <-Volver al inicio
E3: Codigo | F3: Nombre
E4: 1 | F4: Efectivo
E5: 2 | F5: Transferencia
E6: 3 | F6: Tarjeta debito
E7: 4 | F7: Tarjeta Credito
E8: 5 | F8: Pago con codigo QR

Sheet Envio
A1: <-Volver al inicio
A2: Objeto de Dominio: | B2: ='Listado Objetos de Dominio'!A13 -> Envio
A3: Descripción: | B3: ='Listado Objetos de Dominio'!$C$13 -> Entidad que representa el servicio de transportar los productos adquiridos por un cliente hacia un destino.
A4: Atributo | B4: Tipo de Dato | C4: Longitud mínima | D4: Longitud máxima | E4: Precisión | F4: Rango Inicial | G4: Rango Final | H4: Formato | I4: Valor por defecto | J4: Regla especial | K4: ¿Auto generado? | L4: ¿Calculado? | M4: ¿Obligatorio? | N4: ¿Sensible? | O4: ¿Identifica al registro? | P4: Descripción | Q4: =A20 -> Registrar envío | R4: =A21 -> Actualizar estado del envio | S4: =A23 -> Editar Envio | T4: =A29 -> Consultar Envio
A5: idEnvio | B5: Numérico | D5: 36 | F5: 1 | H5: Entero autoincremental | J5: Identificador único del envío | K5: Sí | L5: No | M5: Sí | N5: No | O5: Sí | P5: Código único del servicio de envío | Q5: SI | R5: NO | S5: NO | T5: Si
A6: Pais | B6: Pais | K6: No | L6: No | M6: Sí | N6: No | O6: No | P6: Dirección a la cual se entregarán los productos (Pais-Departamento-CIudad) | Q6: SI | R6: SI | S6: SI | T6: Si
A7: FechaEnvio | B7: DateTime | H7: yyyy-MM-dd | K7: No | L7: No | M7: Sí | N7: No | O7: No | P7: Fecha para realizar el envío | Q7: SI | R7: SI | S7: SI | T7: Si
A8: EstadoEnvio | B8: Estado Envio | C8: 3 | H8: Lista (Ej: Pendiente, Entregado) | I8: Pendiente | J8: Estados predefinidos | K8: No | L8: No | M8: Sí | N8: No | O8: No | P8: Estado actual del envío en la operación logística | Q8: SI | R8: SI | S8: SI | T8: Si
A9: Valor | B9: Numérico | E9: 2 | H9: Decimal | K9: No | L9: No | M9: Sí | N9: No | O9: No | P9: Valor por el envio | Q9: SI | R9: NO | S9: NO | T9: Si
A10: Placa Vehiculo | B10: Texto | K10: No | L10: No | M10: Sí | N10: No | O10: No | P10: Placa del Vehiculo que transporta el envio | Q10: NO | R10: SI | S10: SI | T10: Si
A11: observaciones | B11: Texto | C11: 0 | D11: 255 | H11: Texto libre | I11: "" | K11: No | L11: No | M11: No | N11: No | O11: No | P11: Comentarios internos del envío (novedades, advertencias, etc.) | Q11: NO | R11: SI | S11: SI | T11: Si
A12: Direccion | B12: Texto | C12: 0 | D12: 255 | H12: Texto libre | I12: "" | K12: No | L12: No | M12: No | N12: No | O12: No | P12: complemento a la dirección especifica a la cual se entregarán los productos | Q12: NO | R12: SI | S12: SI | T12: Si
A14: Combinaciones únicas
A15: Nombre combinación | B15: Descripción | C15: Atributos
A16: Id_unico | B16: el id de envio debe ser unico | C16: idEnvio
A18: Responsabilidad | C18: Descripción | G18: Entradas | J18: Salida | O18: Políticas (Reglas de Negocio) | Q18: Excepción
G19: Parámetro | H19: Tipo de dato | I19: Descripción | J19: Tipo de Dato | K19: Descripción | O19: Política | P19: Descripción | Q19: Detalle | R19: ¿Qué hago?
A20: Registrar envío | C20: Registrar un nuevo Envio de entrega programado para una venta | G20: FechaEnvio | H20: String, DateTime | I20: Dirección y fecha del envío | J20: Envío | K20: Envío registrado con estado "Pendiente" | O20: Validar disponibilidad logística | P20: No se puede registrar un envío con fecha anterior a fecha de la venta | Q20: Fecha inválida | R20: Notificar error de fecha invalida
A21: Actualizar estado del envio | C21: Actualizar el estado de un envío según avance del transporte | G21: idEnvio | H21: Numérico | I21: ID Envio | J21: Envío | K21: Estado actualizado correctamente | O21: Validar transición válida de estados | P21: No se puede pasar de “Entregado” a “Pendiente” | Q21: Transición de estado inválida | R21: Rechazar con mensaje de política de negocio
G22: estado | H22: Texto | I22: nuevo estado | J22: Boolean
A23: Editar Envio | C23: Permite modificar los datos de un envío registrado | G23: Pais | H23: Pais | I23: Campos que se pueden modificar a un envío | J23: Envío | K23: Envío modificado correctamente | O23: Validar el estado del envio | P23: No se puede modificar un envio con estado entregado | Q23: Estado no modificable | R23: Mostrar mensaje de error: "no se puede modficar un envío ya entregado"
G24: FechaEnvio | H24: DateTime
G25: Valor | H25: Numérico
G26: Placa Vehiculo | H26: Texto
G27: observaciones | H27: Texto
G28: Direccion | H28: Texto
A29: Consultar Envio | C29: Permite consultar la información de un envio | G29: IdEnvio | H29: Numérico | I29: Código único del Envio | J29: Envío | K29: Datos completos del envío | O29: Solo usuarios con acceso pueden ver los Envios. | P29: Envio no encontrada | Q29: No hay envios con el código proporcionado | R29: Mostrar mensaje: "Envío no encontrada con ese código."
A32: <<Muestreo de datos>>

Sheet Muestreo Envio
A1: <-Volver al inicio
A3: idEnvio | B3: País_ID | C3: FechaEnvio | D3: EstadoEnvio | E3: Valor | F3: Placa Vehiculo | G3: Observaciones
A4: 1 | B4: CO | C4: 45444 | D4: Pendiente | E4: 35000 | F4: XYZ123 | G4: Entrega programada para mañana
A5: 2 | B5: CO | C5: 45446 | D5: Entregado | E5: 50000 | F5: ABC987 | G5: Sin novedades
A6: 3 | B6: CO | C6: 45448 | D6: Pendiente | E6: 120000 | F6: RST456 | G6: Vehículo asignado, esperando despacho
A7: 4 | B7: CO | C7: 45449 | D7: Entregado | E7: 40000 | F7: MNO321 | G7: Entregado en obra 1, sin inconvenientes
A8: 5 | B8: CO | C8: 45450 | D8: Pendiente | E8: 35000 | F8: DEF789 | G8: Cliente solicita notificación por WhatsApp

Sheet Estado Envio
A1: <-Volver al inicio
A2: Objeto de Dominio: | B2: ='Listado Objetos de Dominio'!A22 -> Estado Envio
A3: Descripción: | B3: ='Listado Objetos de Dominio'!$C$22 -> Objeto de dominio que representa cada estado de envio de una venta
A4: Atributo | B4: Tipo de Dato | C4: Longitud mínima | D4: Longitud máxima | E4: Precisión | F4: Rango Inicial | G4: Rango Final | H4: Formato | I4: Valor por defecto | J4: Regla especial | K4: ¿Auto generado? | L4: ¿Calculado? | M4: ¿Obligatorio? | N4: ¿Sensible? | O4: ¿Identifica al registro? | P4: Descripción
A5: idEstadoEnvio | B5: Numerico | D5: 36 | H5: Entero | I5: Ninguno | J5: Único de estado de un envio | K5: Sí | L5: No | M5: Sí | N5: No | O5: Sí | P5: Código identificador de la Estado Envio
A6: Nombre | B6: Alfanumerico | D6: 50 | H6: Texto | I6: Ninguno | J6: Debe ser único | K6: No | L6: No | M6: Sí | N6: No | O6: No | P6: Nombre representativo de la Estado Envio (ej. "Pendiente, Completado")
A7: Descripción | B7: Alfanumerico | C7: 0 | D7: 150 | H7: Texto | I7: Ninguno | J7: Puede estar vacío | K7: No | L7: No | M7: Opcional | N7: No | O7: No | P7: Detalle adicional o aclaración sobre la Estado Envio
A9: Combinaciones únicas
A10: Nombre combinación | B10: Descripción | C10: Atributos
A11: idEstadoEnvio unico | B11: Codigo unico de una Estado Envio | C11: idEstadoEnvio
A14: <<Muestreo de datos>>

Sheet Muestreo Estado Envio
A1: <-Volver al inicio
E3: Codigo | F3: Nombre | G3: Descripcion
E4: 1 | F4: Pendiente | G4: El envio ha sido registrada pero aún no entregado.
E5: 2 | F5: Entregado | G5: El producto o envio ya fue entregado al cliente.

Sheet Unidad de Medida
A1: <-Volver al inicio
A2: Objeto de Dominio: | B2: ='Listado Objetos de Dominio'!A21 -> Unidad de medida
A3: Descripción: | B3: ='Listado Objetos de Dominio'!$C$21 -> Objeto de dominio que representa cada unidad de medida que puede tener un producto
A4: Atributo | B4: Tipo de Dato | C4: Longitud mínima | D4: Longitud máxima | E4: Precisión | F4: Rango Inicial | G4: Rango Final | H4: Formato | I4: Valor por defecto | J4: Regla especial | K4: ¿Auto generado? | L4: ¿Calculado? | M4: ¿Obligatorio? | N4: ¿Sensible? | O4: ¿Identifica al registro? | P4: Descripción
A5: Codigo | B5: Númerico | D5: 10 | H5: Código numérico | J5: PK | K5: SI | L5: No | M5: SI | N5: No | O5: SI | P5: Corresponde al identificador único de cada unidad de medida.
A6: Sigla | B6: Texto | C6: 2 | D6: 5 | H6: Letras en mayúsculas | J6: No puede repetirse | K6: No | L6: No | M6: SI | N6: No | O6: No | P6: Corresponde a la sigla de cada unidad de medida (ej: kg, un, Ll).
A7: Nombre | B7: Texto | C7: 5 | D7: 100 | H7: Texto libre | J7: No puede repetirse | K7: No | L7: No | M7: SI | N7: No | O7: No | P7: Corresponde al nombre completo de una unidad de medida (ej: Kilogramos).
A9: Combinaciones únicas
A10: Nombre combinación | B10: Descripción | C10: Atributos
A11: UQ_sigla | B11: Evita que se repita la sigla (ej. “UN”, “KG”, etc.) | C11: Sigla
A12: UQ_nombre | B12: Asegura que el nombre de cada tipo sea único | C12: Nombre
A15: <<Muestreo de datos>>

Sheet Muestreo Unidad de medida
A1: <-Volver al inicio
E4: Identificador | F4: Sigla | G4: Nombre
E5: 1 | F5: IN | G5: Pulgadas
E6: 2 | F6: KG | G6: Kilogramos
E7: 3 | F7: G | G7: Gramos
E8: 4 | F8: M³ | G8: Metros cubicos
E9: 5 | F9: UN | G9: Unidad

Sheet Insumo
A1: <-Volver al inicio
A2: Objeto de Dominio: | B2: ='Listado Objetos de Dominio'!A20 -> Insumo
A3: Descripción: | B3: ='Listado Objetos de Dominio'!$C$20 -> Objeto de dominio que representa el producto consumido para una producción | Q3: =A16 -> Responsabilidad | R3: =A20 -> Editar insumo | S3: =A21 -> Consultar Insumo
A4: Atributo | B4: Tipo de Dato | C4: Longitud mínima | D4: Longitud máxima | E4: Precisión | F4: Rango Inicial | G4: Rango Final | H4: Formato | I4: Valor por defecto | J4: Regla especial | K4: ¿Auto generado? | L4: ¿Calculado? | M4: ¿Obligatorio? | N4: ¿Sensible? | O4: ¿Identifica al registro? | P4: Descripción | Q4: Si | R4: No | S4: Si
A5: idInsumo | B5: Número | C5: 1 | D5: 20 | K5: Si | M5: Si | N5: No | O5: Si | P5: Identificador unico del insumo | Q5: Si | R5: Si | S5: Si
A6: Producto | B6: Producto | K6: No | M6: Si | N6: No | O6: No | P6: Productos registrados en el insumo | Q6: Si | R6: Si | S6: Si
A7: Produccion | B7: Producción | K7: No | M7: Si | N7: No | O7: No | P7: Produccion asociada en el insumo | Q7: Si | R7: Si | S7: Si
A8: CantidadUsada | B8: Número | K8: No | M8: Si | N8: No | O8: No | P8: Cantidad usada del producto asociado | Q8: Si | R8: Si | S8: Si
A9: FechaCreacion | B9: Fecha | H9: yyyy-MM-dd HH:mm:ss | I9: now() | K9: Si | M9: Si | N9: No | O9: No | P9: Fecha en la se registro el insumo | Q9: Si | R9: No | S9: Si
A11: Combinaciones únicas
A12: Nombre combinación | B12: Descripción | C12: Atributos
A13: idInsumo | B13: El insumo debe tener código único | C13: idInsumo
A16: Responsabilidad | C16: Descripción | G16: Entradas | J16: Salida | O16: Políticas (Reglas de Negocio) | Q16: Excepción
G17: Parámetro | H17: Tipo de dato | I17: Descripción | J17: Tipo de Dato | K17: Descripción | O17: Política | P17: Descripción | Q17: Detalle | R17: ¿Qué hago?
A18: Registrar Insumo | C18: Registro de un nuevo insumo | G18: insumo | H18: insumo | I18: Datos completos del nuevo insumo | J18: insumo | K18: insumo creado exitosamente | O18: No se puede crear un insumo que en su entidad producción sea mayor a la cantidad disponible en el inventario | P18: Validar cantidades de un producto disponible | Q18: La cantidad de productos registrados en el insumo no esta disponible | R18: Mostrar mensaje de error con detalle del producto no disponible
A20: Editar insumo | C20: Permite editar la entidad de un insumo | G20: id, | H20: insumo | I20: se puede modificar los atributos producto y producción | J20: insumo | K20: insumo actualizado exitosamente | O20: No se puede editar un insumo que en su entidad producción sea mayor a la cantidad disponible en el inventario | P20: Validar cantidades de un producto disponible | Q20: La cantidad de productos registrados en el insumo no esta disponible | R20: Mostrar mensaje de error con detalle del producto no disponible
A21: Consultar Insumo | C21: Recupera toda la información de una Insumo específico. | G21: idInsumo | H21: Numerico | I21: Código único del Insumo | J21: Insumo | K21: Datos completos del Insumo | O21: Solo usuarios con acceso pueden ver los insumos. | P21: Insumo no encontrado | Q21: No hay Insumo con el código proporcionado | R21: Mostrar mensaje: "Insumo no encontrada con ese código."
A22: <<Muestreo de datos>>

Sheet Muestreo insumo
A1: <-Volver al inicio
A3: Código | B3: Producto_ID | C3: Producción_ID | D3: CantidadUsada | E3: FechaCreacion
A4: 4001 | B4: 123 | C4: 5001 | D4: 15.5 | E4: 45413.358
A5: 4002 | B5: 124 | C5: 5002 | D5: 10.0 | E5: 45414.382
A6: 4003 | B6: 125 | C6: 5003 | D6: 12.75 | E6: 45414.597
A7: 4004 | B7: 126 | C7: 5004 | D7: 18.0 | E7: 45415.326
A8: 4005 | B8: 127 | C8: 5005 | D8: 11.25 | E8: 45415.42

Sheet Abastecimiento
A1: <-Volver al inicio
A2: Objeto de Dominio: | B2: ='Listado Objetos de Dominio'!A4 -> Abastecimiento
A3: Descripción: | B3: ='Listado Objetos de Dominio'!$C$4 -> Proceso y registro de la adquisición interna de insumos para producción. Documenta las órdenes de compra, fechas de entrega, cantidades solicitadas y precios que alimentaran el Inventario
A4: Atributo | B4: Tipo de Dato | C4: Longitud mínima | D4: Longitud máxima | E4: Precisión | F4: Rango Inicial | G4: Rango Final | H4: Formato | I4: Valor por defecto | J4: Regla especial | K4: ¿Auto generado? | L4: ¿Calculado? | M4: ¿Obligatorio? | N4: ¿Sensible? | O4: ¿Identifica al registro? | P4: Descripción | Q4: =A21 -> Crear | R4: =A22 -> Consultar | S4: =A23 -> ModificarCantidadesyproductos
A5: CódigoAbastecimiento | B5: numérico | H5: UUID | K5: si | L5: No | M5: Si | N5: No | O5: Si | P5: código que identifica un abastecimiento | Q5: Si | R5: Si | S5: Si
A6: Proveedor | B6: Proveedor | H6: Fk | K6: No | L6: No | M6: Si | N6: No | O6: No | P6: Relaciona el proveedor | Q6: Si | R6: No | S6: No
A7: Producto | B7: producto | H7: Fk | K7: No | L7: No | M7: Si | N7: No | O7: No | P7: Relaciona el producto que se va a abastecer | Q7: Si | R7: No | S7: Si
A8: Cantidad_Producto | B8: Numérico | H8: Numérico | K8: No | L8: No | M8: Si | N8: No | O8: No | P8: Cantidad del producto | Q8: Si | R8: No | S8: Si
A9: Precio_compra_Producto | B9: Decimal | H9: Decimal | K9: No | L9: No | M9: Si | N9: No | O9: No | P9: precio al que se compro el producto | Q9: Si | R9: No | S9: No
A10: NroFactura | B10: Texto | H10: Texto | K10: No | L10: No | M10: No | N10: No | O10: Si | P10: número de factura que entrega el proveedor | Q10: Si | R10: No | S10: No
A11: Fecha_Registro | B11: Fecha | H11: Fecha | I11: Fecha actual del sistema | K11: si | L11: No | M11: Si | N11: No | O11: No | P11: Fecha en la que se realiza el registro | Q11: Si | R11: Si | S11: No
A12: Estado_pago_abastecimiento | B12: Booleano | H12: Booleano | K12: No | L12: No | M12: Si | N12: No | O12: NO | P12: Identifica si ya se ha pagado el abastecimiento | Q12: Si | R12: Si | S12: SI
A14: Combinaciones únicas
A15: Nombre combinación | B15: Descripción | C15: Atributos
A16: Factura única proveedor | B16: Evita registrar dos abastecimientos con la misma factura del mismo proveedor. | C16: Proveedor, NroFactura
A17: Código Abastecimiento | B17: Identificador único del abastecimiento dentro del sistema. | C17: CódigoAbastecimiento
A19: Responsabilidad | C19: Descripción | G19: Entradas | J19: Salida | O19: Políticas (Reglas de Negocio) | Q19: Excepción
G20: Parámetro | H20: Tipo de dato | I20: Descripción | J20: Tipo de Dato | K20: Descripción | O20: Política | P20: Descripción | Q20: Detalle | R20: ¿Qué hago?
A21: Crear | C21: Registra un nuevo abastecimiento en el sistema. | G21: Proveedor Producto Cantidad_Producto Precio_compra_Producto NroFactura | H21: Proveedor Producto Numérico Decimal Texto | J21: Abastecimiento | K21: ID generado automáticamente | O21: No se puede registrar con cantidad o precio <= 0 | P21: No se puede registrar con cantidad o precio <= 0 | Q21: Datos incompletos, proveedor inexistente, Producto inexistente | R21: Mostrar mensaje de error
A22: Consultar | C22: Permite visualizar registros de abastecimientos. | G22: CódigoAbastecimiento Rango de fechas | H22: Numérico Fecha | I22: Lista de registros | J22: Abastecimiento | K22: Registros que coinciden con la búsqueda | O22: la fecha inicial no debe ser mayor a la fecha fin | P22: Rango de fechas válidas, abastecimiento no encontrado por código | Q22: Las fechas ingresadas deben ser válidas y el código debe existir | R22: Mostrar mensaje "Error en la consulta"
A23: ModificarCantidadesyproductos | C23: Modifica cantidades y productos de un abastecimiento existente. | G23: CódigoAbastecimiento Producto nuevo Nueva cantidad | H23: Numérico Producto Numérico | I23: Registro actualizado | J23: Abastecimiento | K23: Registro actualizado | O23: Mostrar inventario actualizado | P23: Cada consulta debe mostrar el estado de inventario posterior al abastecimiento Verificar las cantidades no sean menor a cero | Q23: No se puede registrar con cantidad o precio < =0 | R23: Mostrar mensaje de error
A26: <<Muestreo de datos>>

Sheet Muestreo Abastecimiento
A1: <-Volver al inicio
A3: CódigoAbastecimiento | B3: Proveedor_ID | C3: Producto_ID | D3: Cantidad_Producto | E3: Precio_compra_Producto | F3: NroFactura | G3: Fecha_Registro
A4: ABS001 | B4: 123 | C4: 123 | D4: 500 | E4: 1800.50 | F4: FAC-104 | G4: 45444.375
A5: ABS002 | B5: 124 | C5: 124 | D5: 750 | E5: 2200.00 | F5: FAC-105 | G5: 45446.615
A6: ABS003 | B6: 125 | C6: 125 | D6: 600 | E6: 2000.00 | F6: FAC-106 | G6: 45448.465
A7: ABS004 | B7: 126 | C7: 126 | D7: 400 | E7: 1500.00 | F7: FAC-107 | G7: 45449.354
A8: ABS005 | B8: 127 | C8: 127 | D8: 300 | E8: 1750.00 | F8: FAC-108 | G8: 45450.667

Sheet Proveedor
A1: <-Volver al inicio
A2: Objeto de Dominio: | B2: ='Listado Objetos de Dominio'!A2 -> Proveedor
A3: Descripción: | B3: ='Listado Objetos de Dominio'!$C$2 -> Entidad que representa a las empresas o personas que suministran el abastecimiento del negocio.
A4: Atributo | B4: Tipo de Dato | C4: Longitud mínima | D4: Longitud máxima | E4: Precisión | F4: Rango Inicial | G4: Rango Final | H4: Formato | I4: Valor por defecto | J4: Regla especial | K4: ¿Auto generado? | L4: ¿Calculado? | M4: ¿Obligatorio? | N4: ¿Sensible? | O4: ¿Identifica al registro? | P4: Descripción | Q4: =A23 -> Registrar un nuevo proveedor | R4: =A31 -> Modificar un proveedor existente | S4: =A37 -> Consultar proveedor | T4: =A40 -> CambiarEstadoProveedor
A5: IdProveedor | B5: Alfanumérico | D5: 36 | K5: Sí | L5: No | M5: Sí | N5: No | O5: Sí | P5: Identificador único del proveedor | Q5: SI | R5: No | S5: Si | T5: Si
A6: TipoProveedor | B6: Referencia | J6: Persona Natural o Jurídica | K6: No | L6: No | M6: Sí | N6: No | O6: No | P6: Define si el proveedor es una persona natural o jurídica | Q6: SI | R6: No | S6: Si | T6: No
A7: RazonSocial | B7: Alfanumérico | D7: 100 | H7: Texto libre | J7: Obligatorio si TipoProveedor = Persona Jurídica | K7: No | L7: No | M7: Condicional | N7: No | O7: No | P7: Nombre legal de la empresa (solo si es persona jurídica) | Q7: SI | R7: Si | S7: Si | T7: No
A8: NombreCompleto | B8: Alfanumérico | D8: 100 | H8: Texto libre | J8: Obligatorio si TipoProveedor = Persona Natural | K8: No | L8: No | M8: Condicional | N8: No | O8: No | P8: Nombre completo (solo si es persona natural) | Q8: SI | R8: Si | S8: Si | T8: No
A9: Tipo_Identificacion | B9: Tipo_Identificación | D9: 50 | H9: Sólo letras y espacios | J9: Validar contra catálogo de tipos (NIT, CC, CE, etc.) | K9: No | L9: No | M9: Si | N9: No | O9: No | P9: Corresponde al tipo de identificación de cada uno de los Proveedores | Q9: SI | R9: Si | S9: Si | T9: No
A10: Numero_Identificacion | B10: Numérico Entero | D10: 50 | H10: Numérico puro | J10: Único por tipo de documento | K10: No | L10: No | M10: Si | N10: Sí | O10: No | P10: corresponde al número de identificación de cada uno de los Proveedores | Q10: SI | R10: Si | S10: Si | T10: No
A11: CorreoElectronico | B11: Alfanumérico | D11: 250 | H11: Formato de correo electrónico | J11: Asegurar que no se ingresen caracteres fuera de lo común, que puedan apuntar a que sea un posible ataque de SQL Injection o Cross Scripting. | K11: No | L11: No | M11: No | N11: Sí | O11: No | P11: Correo electrónico principal del proveedor | Q11: SI | R11: Si | S11: Si | T11: No
A12: Celular | B12: Numérico | D12: 15 | H12: Dígitos numéricos | K12: No | L12: No | M12: No | O12: No | P12: Teléfono móvil de contacto del proveedor | Q12: SI | R12: Si | S12: Si | T12: No
A13: RepresentanteLegal | B13: Alfanumérico | D13: 100 | H13: Texto libre | J13: Obligatorio solo si es persona jurídica | K13: No | L13: No | M13: Opcional | O13: No | P13: Persona que actúa legalmente en nombre del proveedor (solo para personas jurídicas) | Q13: SI | R13: Si | S13: Si | T13: No
A14: Activo | B14: boolean | C14: 10 | D14: 15 | H14: true / false | I14: true | K14: No | L14: No | M14: Sí | O14: No | P14: Indica si el proveedor está habilitado | Q14: SI | R14: Si | S14: Si | T14: Si
A15: fechaRegistro | B15: Fecha | I15: Fecha actual | J15: Fecha del sistema al momento de creación | K15: Sí | L15: No | M15: Sí | O15: No | P15: Fecha de creación del proveedor | Q15: SI | R15: No | S15: Si | T15: No
A17: Combinaciones únicas
A18: Nombre combinación | B18: Descripción | C18: Atributos
A19: DocumentoIdentificacionUnico | B19: No puede existir más de un proveedor con el mismo tipo y número de identificación | C19: Tipo_Identificacion, Numero_Identificacion
A21: Responsabilidad | C21: Descripción | G21: Entradas | J21: Salida | O21: Políticas (Reglas de Negocio) | Q21: Excepción
G22: Parámetro | H22: Tipo de dato | I22: Descripción | J22: Tipo de Dato | K22: Descripción | O22: Política | P22: Descripción | Q22: Detalle | R22: ¿Qué hago?
A23: Registrar un nuevo proveedor | C23: Permite crear un nuevo proveedor con la información obligatoria y opcional según su tipo | G23: tipoProveedor | H23: Referencia | I23: Persona Natural o Persona Jurídica | J23: Objeto Proveedor | K23: Proveedor creado con su ID asignado | O23: Validar documento único | P23: No puede existir otro proveedor con el mismo tipo y número de documento | Q23: Formato de correo inválido Falta campo obligatorio según tipo Documento duplicado | R23: Lanzar error - Proveedor ya registrado Lanzar error- Campos obligatorios no informados según su tipo Lanzar error - Formato inválido
G24: razonSocial | H24: Alfanumérico | I24: Requerido si tipoProveedor = Persona Jurídica
G25: nombreCompleto | H25: Alfanumérico | I25: Requerido si tipoProveedor = Persona Natural | O25: Validar condición por tipo | P25: Si es persona jurídica → razonSocial es obligatoria
G26: tipoIdentificacion | H26: Tipo_Identificación | I26: Tipo de documento
G27: numeroIdentificacion | H27: Numérico Entero | I27: Número de documento | O27: Validar campos | P27: Correo debe tener formato válido, sin caracteres maliciosos Celular que se numerico y no texto
G28: correoElectronico | H28: Alfanumérico | I28: Correo válido
G29: celular | H29: Numérico | I29: Número celular (opcional) | O29: Restricción lógica de campos | P29: nombreCompleto solo permitido si es persona natural
G30: representanteLegal | H30: Alfanumérico | I30: Opcional para persona jurídica
A31: Modificar un proveedor existente | C31: Permite modificar los datos de contacto, nombre o representante legal de un proveedor existente | G31: idProveedor | H31: UUID / Alfanumérico | I31: ID del proveedor a actualizar | J31: Objeto Proveedor | K31: Proveedor actualizado | O31: Validar existencia previa por nunero Identificación Si el tipoProveedor original es Jurídica, mantener la validez de razonSocial Validar nuevo correo si se proporciona | P31: Validar existencia previa por Identificación Si el tipoProveedor original es Jurídica, mantener la validez de razonSocial Validar nuevo correo si se proporciona | Q31: Numero de identificación no existe Datos mal estructurados | R31: Retornar error Proveedor no existe Retornar error Entrada inválida
G32: razonSocial | H32: Alfanumérico | I32: Nueva razón social (si aplica)
G33: nombreCompleto | H33: Alfanumérico | I33: Nuevo nombre completo (si aplica)
G34: correoElectronico | H34: Alfanumérico | I34: Nuevo correo electrónico
G35: celular | H35: Numérico | I35: Nuevo celular (opcional)
G36: representanteLegal | H36: Alfanumérico | I36: Nuevo representante legal (si aplica)
A37: Consultar proveedor | C37: Permite consultar un proveedor por su ID o por su tipo y número de identificación | G37: idProveedor | H37: UUID / Alfanumérico | I37: (Opcional) ID del proveedor | J37: Objeto Proveedor | K37: Información del proveedor | P37: Proveedor no encontrado | Q37: No hay coincidencia en búsqueda | R37: Retornar error Proveedor no existe
G38: tipoIdentificacion | H38: Alfanumérico | I38: (Requerido si no se envía ID) Tipo de documento | P38: Entrada incompleta | Q38: Entrada incompleta | R38: Retornar error Parámetros requeridos
G39: numeroIdentificacion | H39: Alfanumérico | I39: (Requerido si no se envía ID) Número de identificación
A40: CambiarEstadoProveedor | C40: Permite activar o inactivar un proveedor para uso en procesos de abastecimiento | G40: idProveedor | H40: UUID / Alfanumérico | I40: ID del proveedor | J40: Objeto Proveedor | K40: Proveedor con nuevo estado aplicado | O40: Solo se aceptan valores true o false para el estado | P40: Valor inválido | Q40: Estado distinto de booleano | R40: Retornar error Estado inválido
G41: nuevoEstado | H41: Boolean | I41: true para activar, false para desactivar | O41: Validar que el proveedor exista | P41: Proveedor no encontrado | Q41: ID inválido | R41: Retornar error Proveedor no existente
A44: <<Muestreo de datos>>

Sheet Muestreo Proveedor
A1: <-Volver al inicio
D3: IdProveedor | E3: Tipo Proveedor | F3: Razon Social | G3: Nombre Completo | H3: Tipo_Identificacion | I3: Numero_Identificacion | J3: CorreoElectronico | K3: Celular | L3: Representante legal | M3: Activo | N3: Fecha Registro
D4: 123 | E4: Jurídica | F4: Inversiones Andina S.A.S | H4: NIT | I4: 900123456 | J4: contacto@andina.com.co | K4: 3001234567 | L4: Carlos Gómez | M4: true | N4: 2025-06-04T09:00:00Z
D5: 124 | E5: Natural | G5: Laura Martínez | H5: CC | I5: 1020304050 | J5: laura.martinez@gmail.com | K5: 3102345678 | M5: true | N5: 2025-06-04T09:01:00Z
D6: 125 | E6: Jurídica | F6: Soluciones Integrales SAS | H6: NIT | I6: 901112233 | J6: info@solucionesintegrales.co | K6: 3203456789 | L6: Marta Rodríguez | M6: false | N6: 2025-06-04T09:02:00Z
D7: 126 | E7: Natural | G7: Jaime Rincón | H7: CC | I7: 123456789 | J7: jaime.rincon@hotmail.com | K7: 3114567890 | M7: true | N7: 2025-06-04T09:03:00Z
D8: 127 | E8: Jurídica | F8: Distribuciones Norte LTDA | H8: NIT | I8: 800987654 | J8: ventas@dnltda.com | K8: 3005678901 | L8: Andrea Pérez | M8: true | N8: 2025-06-04T09:04:00Z

Sheet Administrador
A1: <-Volver al inicio
A2: <-Volver al inicio | B2: ='Listado Objetos de Dominio'!A3 -> Administrador
A3: Descripción: | B3: ='Listado Objetos de Dominio'!$C$3 -> Entidad que representa Usuario con privilegios totales sobre la plataforma. Se encarga de configurar parámetros globales, gestionar roles y permisos de Trabajadores y supervisar la generación de Reportes.
A4: Atributo | B4: Tipo de Dato | C4: Longitud mínima | D4: Longitud máxima | E4: Precisión | F4: Rango Inicial | G4: Rango Final | H4: Formato | I4: Valor por defecto | J4: Regla especial | K4: ¿Auto generado? | L4: ¿Calculado? | M4: ¿Obligatorio? | N4: ¿Sensible? | O4: ¿Identifica al registro? | P4: Descripción | Q4: =A25 -> Registrar Administrador | R4: =A27 -> Editar administrador
A5: Código | B5: Numérico Entero | H5: Almacena números enteros | K5: Si | L5: No | M5: Si | N5: No | O5: Si | P5: Corresponde al identificador | Q5: Si | R5: No
A6: Usuario | B6: Alfanumerico | D6: 20 | K6: No | L6: No | M6: Si | N6: No | O6: No | P6: Corresponde a la usuario de inicio de sesión de cada uno de los administradores | Q6: SI | R6: No
A7: Contrasena | B7: Alfanumerico | D7: 15 | K7: No | L7: No | M7: Si | N7: Si | O7: No | P7: Corresponde a la contraseña de inicio de sesión de cada uno de los administradores | Q7: SI | R7: Si
A8: Primer_Nombre | B8: Texto | D8: 100 | H8: Sólo letras y espacios | K8: No | L8: No | M8: Si | N8: No | O8: No | P8: Corresponde al primer nombre de cada uno de los administradores | Q8: SI | R8: Si
A9: Segundo_Nombre | B9: Texto | D9: 100 | H9: Sólo letras y espacios | K9: No | L9: No | M9: No | N9: No | O9: No | P9: Corresponde al segundo nombre de cada uno de los administradores | Q9: Opcional | R9: Si
A10: Primer_Apellido | B10: Texto | D10: 100 | H10: Sólo letras y espacios | K10: No | L10: No | M10: Si | N10: No | O10: No | P10: Corresponde al primer apellido de cada uno de los administradores | Q10: SI | R10: Si
A11: Segundo_Apellido | B11: Texto | D11: 100 | H11: Sólo letras y espacios | K11: No | L11: No | M11: No | N11: No | O11: No | P11: Corresponde al segundo apellido de cada uno de los administradores | Q11: Opcional | R11: Si
A12: Tipo_Identificacion | B12: Tipo_Identificación | D12: 50 | H12: Sólo letras y espacios | K12: No | L12: No | M12: Si | N12: No | O12: No | P12: Corresponde al tipo de identificación de cada uno de los administradores | Q12: SI | R12: No
A13: Numero_Identificacion | B13: Numérico Entero | D13: 15 | K13: No | L13: No | M13: Si | N13: No | O13: No | P13: corresponde al número de identificación de cada uno de los administradores | Q13: SI | R13: No
A14: Correo | B14: Alfanumerico | D14: 250 | H14: Formato de correo electrónico | J14: Asegurar que no se ingresen caracteres fuera de lo común, que puedan apuntar a que sea un posible ataque de SQL Injection o Cross Scripting. | K14: No | L14: No | M14: Si | N14: No | O14: No | P14: Corresponde al correo de cada uno de los administradores | Q14: SI | R14: Si
A15: Celular | B15: Numérico | D15: 10 | K15: No | L15: No | M15: Si | N15: No | O15: No | P15: Corresponde al número de celular de cada uno de los administradores | Q15: SI | R15: Si
A16: Fecha_creacion | B16: DateTime | K16: No | L16: No | M16: Si | N16: No | O16: No | P16: Corresponde a la fecha en que se creo cada uno de los administradores | Q16: SI(Asignada por el sistema) | R16: No
A17: Estado_Usuario | B17: Estado_Usuario | K17: No | L17: No | M17: Si | N17: No | O17: No | P17: Corresponde al estado de un administrador | Q17: SI | R17: Si
A19: Combinaciones únicas
A20: Nombre combinación | B20: Descripción | C20: Atributos
A21: Usuario Tipo_Identificación + Numero_Identificación Correo | C21: Usuario Tipo_Identificacion Numero_identificacion Correo
A23: Responsabilidad | C23: Descripción | G23: Entradas | J23: Salida | O23: Políticas (Reglas de Negocio) | Q23: Excepción
G24: Parámetro | H24: Tipo de dato | I24: Descripción | J24: Tipo de Dato | K24: Descripción | O24: Política | P24: Descripción | Q24: Detalle | R24: ¿Qué hago?
A25: Registrar Administrador | C25: Registro de un nuevo administrador que tendra privilegios en el sistema | G25: Administrador | H25: Administrador | I25: Datos completos del nuevo administrador | J25: Administrador | K25: Administrador creado exitosamente | O25: Validaciones de unicidad, formato y seguridad de campos obligatorios. | P25: Validar unicidad de: Usuario, correo, Número de identificación - Validar longitud mínima y máxima de los campos - Validar contraseña segura (8-15 caracteres) | Q25: Usuario Ya registrado, Campos obligatorios faltantes, Formato inválido | R25: Mostrar mensaje de error con detalle del campo inválido. No registrar hasta corregir.
A27: Editar administrador | C27: Permite editar la entidad de un administrador | G27: id, usuario | H27: Administrador | I27: Solo se puede modificar los atributos (celular, correo, contraseña, estado_Usuario) | J27: Administrador | K27: Administrador actualizado exitosamente | O27: Validaciones de formato y seguridad. | P27: Validar unicidad de: correo - Validar contraseña segura (8-15 caracteres) - Validar formato correcto de correo electronico | Q27: Contraseña inválida, correo inválido, correo ya registrado | R27: Mostrar error si el administrador no existe o si se intenta modificar campos no permitidos. Validar cada campo antes de guardar
A30: <<Muestreo de datos>>

Sheet Muestreo Administrador
A1: <-Volver al inicio
A3: Código | B3: Usuario | C3: Contraseña | D3: Primer_Nombre | E3: Segundo_Nombre | F3: Primer_Apellido | G3: Segundo_Apellido | H3: Tipo_Identificación | I3: Nº Identificación | J3: Correo | K3: Celular | L3: Fecha_Creación | M3: Estado_Usuario
A4: 1001 | B4: jhernandez | C4: ********** | D4: Juan | E4: carlos | F4: Hernandez | G4: Perez | H4: 1 (CC) | I4: 1032456789 | J4: jhernandez@bloquera.com | K4: 3114567890 | L4: 45792.356 | M4: ACT (Activo)
A5: 1002 | B5: ihenao | C5: ********** | D5: Ismenia | F5: Henao | H5: 2 (NIT) | I5: 900123456 | J5: ihenao@bloquera.com | K5: 3207654321 | L5: 45871.591 | M5: INA (Inactivo)
A6: 1003 | B6: aorrego | C6: ********** | D6: Andrés | E6: Felipe | F6: Orrego | G6: Gómez | H6: 3 (CE) | I6: 123456789CE | J6: andres.orrego@bloquera.com | K6: 3009876543 | L6: 45301.375 | M6: LIC (Licencia)

Sheet Cliente
A1: <-Volver al inicio
A2: Objeto de Dominio: | B2: ='Listado Objetos de Dominio'!A7 -> Cliente
A3: Descripción: | B3: ='Listado Objetos de Dominio'!$C$7 -> Comprador de bloques y materiales. Registra datos de contacto, histórico de pedidos, métodos de pago y preferencias de entrega. Puede interactuar con el portal para ver catálogo y solicitar atención.
A4: Atributo | B4: Tipo de Dato | C4: Longitud mínima | D4: Longitud máxima | E4: Precisión | F4: Rango Inicial | G4: Rango Final | H4: Formato | I4: Valor por defecto | J4: Regla especial | K4: ¿Auto generado? | L4: ¿Calculado? | M4: ¿Obligatorio? | N4: ¿Sensible? | O4: ¿Identifica al registro? | P4: Descripción | Q4: =A23 -> Registrar Cliente | R4: =A24 -> Actualizar Cliente | S4: =A25 -> Historial Cliente
A5: CódigoCliente | B5: Numérico | H5: Numero Entero | K5: Si | L5: No | M5: Si | N5: No | O5: Si | P5: Corresponde al identificador de un cliente | Q5: SI | R5: NO | S5: SI
A6: TipoIdentificacion | B6: Tipo Identificacion | H6: FK | K6: No | L6: No | M6: Si | N6: No | O6: No | P6: Corresponde al tipo de identificación de cada uno de los Clientes | Q6: SI | R6: NO | S6: SI
A7: NumeroIdentificacion | B7: Alfanumérico | C7: 10 | D7: 15 | K7: No | L7: No | M7: Si | N7: No | O7: No | P7: corresponde al número de identificación de cada uno de los Clientes | Q7: SI | R7: NO | S7: SI
A8: PrimerNombre | B8: Texto | D8: 100 | K8: No | L8: No | M8: Si | N8: No | O8: No | P8: Corresponde al primer nombre de cada uno de los Clientes | Q8: SI | R8: Si | S8: SI
A9: SegundoNombre | B9: Texto | D9: 100 | K9: No | L9: No | M9: No | N9: No | O9: No | P9: Corresponde al segundo nombre de cada uno de los Clientes | Q9: Opcional | R9: Si | S9: SI
A10: PrimerApellido | B10: Texto | D10: 100 | K10: No | L10: No | M10: Si | N10: No | O10: No | P10: Corresponde al primer apellido de cada uno de los Clientes | Q10: SI | R10: Si | S10: SI
A11: SegundoApellido | B11: Texto | D11: 100 | K11: No | L11: No | M11: No | N11: No | O11: No | P11: Corresponde al segundo apellido de cada uno de los Clientes | Q11: Opcional | R11: Si | S11: SI
A12: Direccion | B12: Texto | D12: 50 | K12: No | L12: No | M12: Si | N12: No | O12: No | P12: Corresponde a la dirección de cada uno de los Clientes | Q12: SI | R12: Si | S12: NO
A13: Celular | B13: Numérico | D13: 15 | K13: No | L13: No | M13: Si | N13: No | O13: No | P13: Corresponde al número de celular de cada uno de los clientes | Q13: SI | R13: Si | S13: NO
A14: Correo | B14: Alfanumerico | D14: 250 | H14: Formato de correo electrónico | J14: Asegurar que no se ingresen caracteres fuera de lo común, que puedan apuntar a que sea un posible ataque de SQL Injection o Cross Scripting. | K14: No | L14: No | M14: Si | N14: No | O14: No | P14: Corresponde al correo de cada uno de los Clientes | Q14: SI | R14: Si | S14: NO
A15: Informacion_Interes | B15: Informacion de interes | H15: FK | K15: No | L15: No | M15: Opcional | N15: No | O15: No | P15: Corresponde a el catalogo de información de interes que pueda tener cada uno de los clientes | Q15: SI | R15: Si | S15: SI
A17: Combinaciones únicas
A18: Nombre combinación | B18: Descripción | C18: Atributos
A19: cliente_unico_documento | B19: No se permiten duplicados por tipo y número | C19: TipoIdentificacion + NumeroIdentificacion
A21: Responsabilidad | C21: Descripción | G21: Entradas | J21: Salida | O21: Políticas (Reglas de Negocio) | Q21: Excepción
G22: Parámetro | H22: Tipo de dato | I22: Descripción | J22: Tipo de Dato | K22: Descripción | O22: Política | P22: Descripción | Q22: Detalle | R22: ¿Qué hago?
A23: Registrar Cliente | C23: Registro de cliente en el sistema con validaciones básicas | G23: TipoIdentificación, NúmeroIdentificación, Nombres, Apellidos, Dirección, Celular, Correo | H23: TipoIdentificacion, Texto,Texto,Texto,Texto, Numerico,Texto | I23: Datos requeridos para crear un nuevo cliente con sus datos de identificación y contacto | J23: Numérico | K23: ID único generado para el nuevo cliente | O23: No duplicidad por documento | P23: No se puede registrar cliente con tipo y número de identificación ya existentes | Q23: Cliente con documento duplicado | R23: Rechazar registro y mostrar mensaje de error
A24: Actualizar Cliente | C24: Validación y actualización de datos de contacto | G24: CódigoCliente | H24: Numerico | I24: Código del cliente con los nuevos datos de contacto a modificar | J24: Objeto Cliente | K24: Datos del cliente actualizados | O24: Validar existencia del cliente | P24: Solo se puede actualizar si el cliente existe | Q24: Cliente no existe | R24: Rechazar actualización o retornar error
A25: Historial Cliente | C25: Gestión del historial del cliente: pedidos realizados, forma de pago utilizada, interacciones previas | G25: CódigoCliente | H25: Numerico | I25: ID del cliente para consultar su historial | J25: Lista de Objetos | K25: Lista de pedidos, pagos y actividades del cliente | O25: NO se puede generar historial si no se ha hecho ninguna transaccción | P25: El historial no se puede modificar manualmente. Se genera desde pedidos y transacciones | Q25: Historial no disponible o inconsistente | R25: Mostrar mensaje de error si no hay historial
A28: <<Muestreo de datos>>

Sheet Muestreo Cliente
A1: <-Volver al inicio
G2: CódigoCliente | H2: TipoIdentificacion | I2: NumeroIdentificacion | J2: Nombres | K2: Apellidos | L2: Direccion | M2: Celular | N2: Correo | O2: Informacion_Interes
G3: 100 | H3: CE | I3: 93056139 | J3: Jorge | K3: Pérez | L3: Calle 24 #98-27 | M3: 3678279024 | N3: cliente0@dominio.com | O3: 2001
G4: 101 | H4: CC | I4: 41069215 | J4: Carlos | K4: González | L4: Calle 14 #84-6 | M4: 3644956562 | N4: cliente1@dominio.com | O4: 2002
G5: 102 | H5: CC | I5: 67793193 | J5: Diana | K5: Jiménez | L5: Calle 91 #72-40 | M5: 3461039525 | N5: cliente2@dominio.com | O5: 2003
G6: 103 | H6: CC | I6: 55414045 | J6: Sofía | K6: González | L6: Calle 35 #13-76 | M6: 3769046582 | N6: cliente3@dominio.com | O6: 2004
G7: 104 | H7: CE | I7: 72339225 | J7: Laura | K7: Rodríguez | L7: Calle 18 #7-95 | M7: 3470975608 | N7: cliente4@dominio.com | O7: 2005
G8: 105 | H8: PAS | I8: 18051228 | J8: Diana | K8: Martínez | L8: Calle 8 #71-77 | M8: 3986793204 | N8: cliente5@dominio.com | O8: 2001

Sheet Reporte
A1: <-Volver al inicio
A2: Objeto de Dominio: | B2: ='Listado Objetos de Dominio'!A5 -> Reporte
A3: Descripción: | B3: ='Listado Objetos de Dominio'!$C$5 -> Informe que consolida información de los distintos procesos (ventas, compras/abastecimientos, producción, inventario). Generado por Administradores o Trabajadores para apoyar la toma de decisiones estratégicas.
A4: Atributo | B4: Tipo de Dato | C4: Longitud mínima | D4: Longitud máxima | E4: Precisión | F4: Rango Inicial | G4: Rango Final | H4: Formato | I4: Valor por defecto | J4: Regla especial | K4: ¿Auto generado? | L4: ¿Calculado? | M4: ¿Obligatorio? | N4: ¿Sensible? | O4: ¿Identifica al registro? | P4: Descripción | Q4: =A17 -> Generar Reporte
A5: Id | B5: Numerico/UUID | J5: Unico | K5: Si | L5: No | M5: Si | N5: No | O5: Si | P5: Identificador único del reporte | Q5: SI
A6: FechaGeneracion | B6: Fecha | H6: DateTime | K6: Si | L6: No | M6: Si | N6: No | O6: No | P6: Fecha y hora de generación del reporte | Q6: SI
A7: Trabajador Solicitante | B7: Trabajador | H7: FK | K7: No | L7: No | M7: Si | N7: No | O7: No | P7: Trabajador quien solicita el reporte | Q7: SI
A8: Periodo Inicio | B8: Fecha | K8: No | L8: No | M8: Sí | N8: No | O8: No | P8: Fecha de inicio del periodo que abarca el reporte | Q8: SI
A9: Periodo FIn | B9: Fecha | H9: DateTime | K9: No | L9: No | M9: Si | N9: No | O9: No | P9: Fecha de fin del periodo que abarca el reporte | Q9: SI
A11: Combinaciones únicas
A12: Nombre combinación | B12: Descripción | C12: Atributos
A13: ReporteUnicoPorPeriodo | B13: Solo puede existir un reporte para un mismo rango de fechas | C13: PeriodoInicio,PeriodoFin
A15: Responsabilidad | C15: Descripción | G15: Entradas | J15: Salida | O15: Políticas (Reglas de Negocio) | Q15: Excepción
G16: Parámetro | H16: Tipo de dato | I16: Descripción | J16: Tipo de Dato | K16: Descripción | O16: Política | P16: Descripción | Q16: Detalle | R16: ¿Qué hago?
A17: Generar Reporte | C17: Permite generar un nuevo reporte consolidado, asociando la solicitud a un trabajador y dejando trazabilidad sobre la operación. | G17: PeriodoInicio | H17: Fecha | I17: Fecha de inicio del reporte | J17: Reporte | K17: Entidad Reporte | O17: PeriodoInicio < PeriodoFin | P17: La fecha de inicio del periodo no puede ser posterior a la fecha de fin. | Q17: PeriodoInicio mayor que PeriodoFin | R17: Informar al usuario que debe corregir el rango de fechas.
G18: PeriodoFin | H18: Fecha | I18: Fecha de fin del reporte | O18: Ambas fechas obligatorias | P18: PeriodoInicio y PeriodoFin deben estar presentes para generar el reporte. | Q18: Falta alguna de las fechas | R18: Notificar que ambas fechas son requeridas para la generación del reporte.
A21: <<Muestreo de datos>>

Sheet Muestreo Reporte
A1: <-Volver al inicio
G3: Id | H3: FechaGeneracion | I3: TrabajadorSolicitante | J3: PeriodoInicio | K3: PeriodoFin
G4: 1f2e3d4c-5b6a-7980-1234-abcdefabcdef | H4: 2025-06-04T08:00:00Z | I4: T001 | J4: 45778 | K4: 2025-05-31T23:59:59Z
G5: 2a3b4c5d-6e7f-8901-2345-bcdefabcdef0 | H5: 2025-06-01T15:30:00Z | I5: T002 | J5: 45748 | K5: 2025-04-30T23:59:59Z
G6: 3b4c5d6e-7f80-9012-3456-cdefabcde123 | H6: 2025-05-25T09:45:00Z | I6: T003 | J6: 45717 | K6: 2025-03-31T23:59:59Z
G7: 4c5d6e7f-8091-0123-4567-defabcdef456 | H7: 2025-05-10T11:20:00Z | I7: T004 | J7: 45689 | K7: 2025-02-28T23:59:59Z
G8: 5d6e7f80-9123-1234-5678-efabcdef7890 | H8: 2025-04-01T07:10:00Z | I8: T005 | J8: 45658 | K8: 2025-01-31T23:59:59Z

Sheet Trabajador
A1: <-Volver al inicio
A2: Objeto de Dominio: | B2: ='Listado Objetos de Dominio'!A6 -> Trabajador
A3: Descripción: | B3: ='Listado Objetos de Dominio'!$C$6 -> Empleado del negocio que dispone de un Usuario en el sistema. Ejecuta operaciones como registrar Ventas, registrar Producción, gestionar Abastecimientos y atender consultas.
A4: Atributo | B4: Tipo de Dato | C4: Longitud mínima | D4: Longitud máxima | E4: Precisión | F4: Rango Inicial | G4: Rango Final | H4: Formato | I4: Valor por defecto | J4: Regla especial | K4: ¿Auto generado? | L4: ¿Calculado? | M4: ¿Obligatorio? | N4: ¿Sensible? | O4: ¿Identifica al registro? | P4: Descripción | Q4: =A26 -> Registrar Trabajador | R4: =A28 -> Editar Trabajador
A5: Código | B5: Numérico Entero | H5: Almacena números enteros | K5: Si | L5: No | M5: Si | N5: No | O5: Si | P5: Corresponde al identificador | Q5: Si | R5: No
A6: Usuario | B6: Alfanumerico | D6: 20 | K6: No | L6: No | M6: Si | N6: No | O6: No | P6: Corresponde a la usuario de inicio de sesión de cada uno de los Trabajadores | Q6: SI | R6: No
A7: Contrasena | B7: Alfanumerico | D7: 15 | K7: No | L7: No | M7: Si | N7: Si | O7: No | P7: Corresponde a la contraseña de inicio de sesión de cada uno de los Trabajadores | Q7: SI | R7: Si
A8: Primer_Nombre | B8: Texto | D8: 100 | H8: Sólo letras y espacios | K8: No | L8: No | M8: Si | N8: No | O8: No | P8: Corresponde al primer nombre de cada uno de los Trabajadores | Q8: SI | R8: Si
A9: Segundo_Nombre | B9: Texto | D9: 100 | H9: Sólo letras y espacios | K9: No | L9: No | M9: No | N9: No | O9: No | P9: Corresponde al segundo nombre de cada uno de los Trabajadores | Q9: Opcional | R9: Si
A10: Primer_Apellido | B10: Texto | D10: 100 | H10: Sólo letras y espacios | K10: No | L10: No | M10: Si | N10: No | O10: No | P10: Corresponde al primer apellido de cada uno de los Trabajadores | Q10: SI | R10: Si
A11: Segundo_Apellido | B11: Texto | D11: 100 | H11: Sólo letras y espacios | K11: No | L11: No | M11: No | N11: No | O11: No | P11: Corresponde al segundo apellido de cada uno de los Trabajadores | Q11: Opcional | R11: Si
A12: Tipo_Identificacion | B12: Tipo_Identificación | D12: 50 | H12: Sólo letras y espacios | K12: No | L12: No | M12: Si | N12: No | O12: No | P12: Corresponde al tipo de identificación de cada uno de los Trabajadores | Q12: SI | R12: No
A13: Numero_Identificacion | B13: Numérico Entero | D13: 50 | K13: No | L13: No | M13: Si | N13: No | O13: No | P13: corresponde al número de identificación de cada uno de los Trabajadores | Q13: SI | R13: No
A14: Correo | B14: Alfanumerico | D14: 250 | H14: Formato de correo electrónico | J14: Asegurar que no se ingresen caracteres fuera de lo común, que puedan apuntar a que sea un posible ataque de SQL Injection o Cross Scripting. | K14: No | L14: No | M14: Si | N14: No | O14: No | P14: Corresponde al correo de cada uno de los Trabajadores | Q14: SI | R14: Si
A15: Celular | B15: Numérico | D15: 15 | K15: No | L15: No | M15: Si | N15: No | O15: No | P15: Corresponde al número de celular de cada uno de los Trabajadores | Q15: SI | R15: Si
A16: Fecha_creacion | B16: DateTime | K16: No | L16: No | M16: Si | N16: No | O16: No | P16: Corresponde a la fecha en que se creo cada uno de los Trabajadores | Q16: SI(Asignada por el sistema) | R16: No
A17: Estado_Usuario | B17: Estado_Usuario | K17: No | L17: No | M17: Si | N17: No | O17: No | P17: Corresponde al estado de un Trabajador | Q17: SI | R17: Si
A20: Combinaciones únicas
A21: Nombre combinación | B21: Descripción | C21: Atributos
A22: Usuario Tipo_Identificación + Numero_Identificación Correo | C22: Usuario Tipo_Identificacion Numero_identificacion Correo
A24: Responsabilidad | C24: Descripción | G24: Entradas | J24: Salida | O24: Políticas (Reglas de Negocio) | Q24: Excepción
G25: Parámetro | H25: Tipo de dato | I25: Descripción | J25: Tipo de Dato | K25: Descripción | O25: Política | P25: Descripción | Q25: Detalle | R25: ¿Qué hago?
A26: Registrar Trabajador | C26: Registro de un nuevo Trabajador | G26: Trabajador | H26: Trabajador | I26: Datos completos del nuevo Trabajador | J26: Trabajador | K26: Trabajador creado exitosamente | O26: Validaciones de unicidad, formato y seguridad de campos obligatorios. | P26: Validar unicidad de: Usuario, correo, Número de identificación - Validar longitud mínima y máxima de los campos - Validar contraseña segura (8-15 caracteres) | Q26: Usuario Ya registrado, Campos obligatorios faltantes, Formato inválido | R26: Mostrar mensaje de error con detalle del campo inválido. No registrar hasta corregir.
A28: Editar Trabajador | C28: Permite editar la entidad de un Trabajador | G28: id, usuario | H28: Trabajador | I28: Solo se puede modificar los atributos (celular, correo, contraseña, estado_Usuario) | J28: Trabajador | K28: Trabajador actualizado exitosamente | O28: Validaciones de formato y seguridad. | P28: Validar unicidad de: correo - Validar contraseña segura (8-15 caracteres) - Validar formato correcto de correo electronico | Q28: Contraseña inválida, correo inválido, correo ya registrado | R28: Mostrar error si el Trabajador no existe o si se intenta modificar campos no permitidos. Validar cada campo antes de guardar
A30: <<Muestreo de datos>>

Sheet Muestreo Trabajador
A1: <-Volver al inicio
F3: Código | G3: Usuario | H3: Contrasena | I3: Primer_Nombre | J3: Segundo_Nombre | K3: Primer_Apellido | L3: Segundo_Apellido | M3: Tipo_Identificacion | N3: Numero_Identificacion | O3: Correo | P3: Celular | Q3: Fecha_creacion | R3: Estado_Usuario
F4: 1 | G4: jrojas | H4: ********** | I4: Juan | J4: Camilo | K4: Rojas | L4: Pérez | M4: CC | N4: 1020304050 | O4: juan.rojas@bloquera.com | P4: 3001112233 | Q4: 2025-06-04T08:00:00Z | R4: ACT
F5: 2 | G5: lmendoza | H5: ********** | I5: Laura | K5: Mendoza | L5: Gómez | M5: CC | N5: 1122334455 | O5: laura.mendoza@bloquera.com | P5: 3102223344 | Q5: 2025-06-04T08:05:00Z | R5: INA
F6: 3 | G6: fcortes | H6: ********** | I6: Felipe | J6: Andrés | K6: Cortés | M6: CE | N6: 9988776655 | O6: felipe.cortes@bloquera.com | P6: 3113334455 | Q6: 2025-06-04T08:10:00Z | R6: VAC
F7: 4 | G7: mbernal | H7: ********** | I7: Mariana | J7: Alejandra | K7: Bernal | L7: López | M7: CC | N7: 1234567890 | O7: mariana.bernal@bloquera.com | P7: 3124445566 | Q7: 2025-06-04T08:15:00Z | R7: ACT
F8: 5 | G8: hrivera | H8: ********** | I8: Héctor | K8: Rivera | L8: Rodríguez | M8: TI | N8: 456789123 | O8: hector.rivera@bloquera.com | P8: 3135556677 | Q8: 2025-06-04T08:20:00Z | R8: LIC

Sheet Información de interes
A1: <-Volver al inicio
A2: Objeto de Dominio: | B2: ='Listado Objetos de Dominio'!A8 -> Información de interes
A3: Descripción: | B3: ='Listado Objetos de Dominio'!$C$8 -> Hace referencia a la información relevante sobre el perfil y finalidad del cliente en relación con los productos, incluyendo el uso previsto y su rol dentro del sector, como constructor, contratista, revendedor, entre otros
A4: Atributo | B4: Tipo de Dato | C4: Longitud mínima | D4: Longitud máxima | E4: Precisión | F4: Rango Inicial | G4: Rango Final | H4: Formato | I4: Valor por defecto | J4: Regla especial | K4: ¿Auto generado? | L4: ¿Calculado? | M4: ¿Obligatorio? | N4: ¿Sensible? | O4: ¿Identifica al registro? | P4: Descripción
A5: Código | B5: Numérico | C5: 1 | D5: 36 | H5: UUID | J5: Identificador único | K5: Sí | L5: No | M5: Sí | N5: No | O5: Sí | P5: Identificador único del registro de información de interés
A6: Actividad Realizada | B6: Lista | C6: 3 | D6: 50 | H6: Texto | J6: Debe seleccionarse de una lista predefinida | K6: No | L6: No | M6: Sí | N6: No | O6: No | P6: Actividad principal del cliente (Ej: Constructor, Contratista, etc.)
A7: Uso_Material | B7: Lista | C7: 3 | D7: 100 | H7: Texto | J7: Lista de finalidades posibles | K7: No | L7: No | M7: Sí | N7: No | O7: No | P7: Uso previsto del material (Ej: Construcción propia, reventa, proyectos)
A9: Combinaciones únicas
A10: Nombre combinación | B10: Descripción | C10: Atributos
A11: Cliente + código | B11: No se debe repetir la combinación | C11: Código Cliente
A15: <<Muestreo de datos>>

Sheet Muestreo Información de interes
A1: <-Volver al inicio
A3: Código | B3: Cliente_ID | C3: Actividad Realizada | D3: Uso_Material
A4: 2001 | B4: 100 | C4: Constructor | D4: Construcción propia
A5: 2002 | B5: 102 | C5: Contratista | D5: Proyectos de terceros
A6: 2003 | B6: 103 | C6: Revendedor | D6: Reventa de materiales
A7: 2004 | B7: 104 | C7: Arquitecto | D7: Uso en remodelaciones
A8: 2005 | B8: 105 | C8: Maestro de obra | D8: Construcción propia

Sheet Producción
A1: <-Volver al inicio
A2: Objeto de Dominio: | B2: ='Listado Objetos de Dominio'!A9 -> Producción
A3: Descripción: | B3: ='Listado Objetos de Dominio'!$C$9 -> Registro diario de bloques fabricados: cantidad producida, lote, fecha, insumos y trabajadores responsables.
A4: Atributo | B4: Tipo de Dato | C4: Longitud mínima | D4: Longitud máxima | E4: Precisión | F4: Rango Inicial | G4: Rango Final | H4: Formato | I4: Valor por defecto | J4: Regla especial | K4: ¿Auto generado? | L4: ¿Calculado? | M4: ¿Obligatorio? | N4: ¿Sensible? | O4: ¿Identifica al registro? | P4: Descripción | Q4: =A21 -> Registrar Producción | R4: =A24 -> Consultar Producción | S4: =A25 -> Actualizar Producción | T4: =A31 -> Eliminar Producción
A5: IdProduccion | B5: Numérico Entero | H5: UUID | J5: único | K5: Sí | L5: No | M5: Sí | N5: No | O5: Sí | P5: Identificador único de la producción | Q5: Si | R5: No | S5: No | T5: Si
A6: Fecha_Produccion | B6: Fecha | H6: Fecha | I6: Fecha actual | J6: Fecha del sistema al momento de creación | K6: Sí | L6: No | M6: Sí | N6: No | O6: No | P6: Fecha de creación de la producción | Q6: Si | R6: Si | S6: Si | T6: Si
A7: Producto | B7: Producto | H7: FK | J7: incrementa la cantidad de un producto | K7: No | L7: Si | M7: Si | N7: No | O7: No | P7: Relaciona el producto que se debe incrementar la cantidad | Q7: Si | R7: No | S7: Si | T7: Si
A8: Tablas_producidas | B8: Numérico | H8: Entero | K8: No | L8: No | M8: Si | N8: No | O8: No | P8: Cantidad numérico de tablas producidas | Q8: Si | R8: No | S8: Si | T8: Si
A9: Cantidad_Defectuosas | B9: Numérico | H9: Entero | K9: No | L9: No | M9: No | N9: No | O9: No | P9: Cantidad de productos defectuosos en esta producción | Q9: Si | R9: No | S9: Si | T9: Si
A10: Cantidad_producida | B10: Numérico | H10: Entero | K10: No | L10: No | M10: Si | N10: No | O10: No | P10: Cantidad de productos en esta producción | Q10: Si | R10: No | S10: Si | T10: Si
A11: Trabajador | B11: Trabajador | H11: Fk | J11: Dado por el sistema | K11: No | L11: No | M11: Si | N11: No | O11: No | P11: Trabajador que registra la producción | Q11: Si | R11: No | S11: No | T11: Si
A12: Insumo | B12: Insumo | C12: 100 | D12: 250 | K12: No | L12: No | M12: No | N12: No | O12: No | P12: Observaciones adicionales que se requieran segun una producción | Q12: Si | R12: No | S12: Si | T12: Si
A13: Observaciones | B13: Texto
A15: Combinaciones únicas
A16: Nombre combinación | B16: Descripción | C16: Atributos
A17: PK - código único | B17: El código debe ser único | C17: IdProduccion
A19: Responsabilidad | C19: Descripción | G19: Entradas | J19: Salida | O19: Políticas (Reglas de Negocio) | Q19: Excepción
G20: Parámetro | H20: Tipo de dato | I20: Descripción | J20: Tipo de Dato | K20: Descripción | O20: Política | P20: Descripción | Q20: Detalle | R20: ¿Qué hago?
A21: Registrar Producción | C21: Permite ingresar en el sistema una nueva producción de bloques, incluyendo fecha, producto, cantidad producida, tablas generadas e insumos utilizados. | G21: Fecha_Produccion Producto Tablas_producidas Cantidad_producida Insumo Trabajador_responsable (*) | H21: Fecha Fk Producto Numérico Numérico FkInsumo FkTrabajado | I21: Campos necesarios para Registrar una producción | J21: Producción | K21: Produccion registrada | O21: La cantidad producida no puede ser negativa ni cero Se debe especificar al menos un insumo asociado El producto relacionado debe existir y estar activo El registro debe incrementar automáticamente el stock del producto Se debe restar la cantidad del insumo asociado | P21: No se selecciona un producto | Q21: Producto nulo o inexistente | R21: Mostrar mensaje de error
P22: No se asocian insumos | Q22: Lista vacía | R22: Notificar que se deben ingresar insumos
P23: Cantidad inválida | Q23: Cero o negativa | R23: Validar valor antes de guardar
A24: Consultar Producción | C24: Permite visualizar el historial de registros de producción, con filtros por fecha, producto, trabajador o insumo utilizado. | G24: Fecha Producto Trabajador | H24: Fecha Fk Producto Fk Trabajdor | I24: Campos para consultar la producción | J24: Producción | K24: Produccion consultada | O24: Solo usuarios con rol autorizado pueden consultar registros Los resultados deben poder ordenarse por fecha o cantidad producida | P24: Fechas mal ingresada. Sin resultados | Q24: Fecha fin < fecha inicio No hay coincidencias | R24: Mostrar mensaje de error Mostrar aviso: “No se encontraron registros”
A25: Actualizar Producción | C25: Permite modificar los datos de una producción registrada (cantidad, insumos, trabajador, etc.) | G25: IdProduccion | H25: Numérico Entero | I25: Campos necesarios para modificar una producción | J25: Producción | K25: Produccion Modificada | O25: Cumplir con acceso autorizado Modificar Stock Valores permitidos | P25: Solo usuarios autorizados pueden modificar Actualizar stock si cambian cantidades/insumos Las cantidades modificadas no pueden ser negativas | Q25: Permiso denegado Cantidad ingresada incorrecta | R25: Mostrar mensaje: Permiso denegado Cantidad ingresada incorrecta
G26: Producto | H26: Producto
G27: Tablas_producidas | H27: Numérico
G28: Catidad_Produccion | H28: Numérico
G29: Cantidad defectuosas | H29: Numérico
G30: Insumo | H30: Insumo
A31: Eliminar Producción | C31: Permite eliminar del sistema un registro de producción y revertir los movimientos de stock asociados. | G31: Produccion | H31: Produccion | I31: se eliminan todos los campos de una producción | J31: Producción | K31: Produccion Eliminada | O31: Al eliminar, revertir el stock del producto y de los insumos | P31: Se deben restar los productos registrados en la producción e incrementar los insumos en el stock | Q31: Cantidad no valida que genere inconsistencia en los datos como valores negativos no se permite ingresar si la producción es de hace más de una semana, ya no se podra eliminar | R31: Mostrar mensaje:"Datos Invalidos" Mostrar mensaje:"no es posible eliminar la producción contacte el administrador"
A33: <<Muestreo de datos>>

Sheet Muestreo Producción
A1: <-Volver al inicio
A3: Código | B3: Fecha_Producción | C3: Producto_ID | D3: Tablas_producidas | E3: Cantidad_producida | F3: Trabajador_ID | G3: Insumo_ID
A4: 5001 | B4: 45778 | C4: 123 | D4: 335 | E4: =Tabla11[[#This Row],[Tablas_producidas]]*3 -> 1005 | F4: 1 | G4: 4001
A5: 5002 | B5: 45779 | C5: 123 | D5: 250 | E5: =Tabla11[[#This Row],[Tablas_producidas]]*3 -> 750 | F5: 2 | G5: 4002
A6: 5003 | B6: 45780 | C6: 123 | D6: 432 | E6: =Tabla11[[#This Row],[Tablas_producidas]]*3 -> 1296 | F6: 3 | G6: 4003
A7: 5004 | B7: 45781 | C7: 123 | D7: 60 | E7: =Tabla11[[#This Row],[Tablas_producidas]]*3 -> 180 | F7: 4 | G7: 4004
A8: 5005 | B8: 45782 | C8: 123 | D8: 234 | E8: =Tabla11[[#This Row],[Tablas_producidas]]*4 -> 936 | F8: 5 | G8: 4005

Sheet Producto
A1: <-Volver al inicio
A2: Objeto de Dominio: | B2: ='Listado Objetos de Dominio'!A10 -> Producto
A3: Descripción: | B3: ='Listado Objetos de Dominio'!$C$10 -> Definición de cada artículo que el negocio ofrece a sus clientes.
A4: Atributo | B4: Tipo de Dato | C4: Longitud mínima | D4: Longitud máxima | E4: Precisión | F4: Rango Inicial | G4: Rango Final | H4: Formato | I4: Valor por defecto | J4: Regla especial | K4: ¿Auto generado? | L4: ¿Calculado? | M4: ¿Obligatorio? | N4: ¿Sensible? | O4: ¿Identifica al registro? | P4: Descripción | Q4: =A20 -> Registrar Producto | R4: =A21 -> Actualizar Producto | S4: =A23 -> Consultar Producto | T4: =A24 -> Inactivar Producto
A5: CódigoProducto | B5: Numerico | D5: 36 | H5: UUID | J5: Único | K5: Sí | L5: No | M5: Sí | N5: No | O5: Sí | P5: Identificador único del producto | Q5: Si | R5: No | S5: SI | T5: SI
A6: Nombre | B6: Alfanumerico | C6: 3 | D6: 100 | H6: Texto | J6: No duplicado | K6: No | L6: No | M6: Sí | N6: No | O6: No | P6: Nombre comercial del producto (ej. Bloque 10x20x40) | Q6: Si | R6: Si | S6: SI | T6: NO
A7: Descripción | B7: Alfanumerico | C7: 0 | D7: 255 | H7: Texto | J7: Opcional | K7: No | L7: No | M7: No | N7: No | O7: No | P7: Descripción adicional del producto | Q7: Si | R7: Si | S7: SI | T7: NO
A8: UnidadMedida | B8: Unidad de Medida | H8: FK | J8: Según catálogo de unidades | K8: No | L8: No | M8: Sí | N8: No | O8: No | P8: Unidad en la que se comercializa (UND, M2, KG, etc.) | Q8: Si | R8: Si | S8: SI | T8: NO
A9: PrecioUnitario | B9: Numérico | C9: 1 | D9: 12 | E9: 2 | F9: 0 | G9: 999999.99 | H9: Decimal | J9: Mayor a cero | K9: No | L9: No | M9: Sí | N9: No | O9: No | P9: Precio unitario de venta del producto | Q9: Si | R9: Si | S9: SI | T9: NO
A10: Stock | B10: Numérico | H10: Entero | J10: Que no sea menor que cero | K10: No | L10: Si | M10: Si | N10: No | O10: No | P10: Cantidad disponible de un producto para realizar una venta | Q10: Si | R10: Si | S10: SI | T10: NO
A11: Estado | B11: Estado Producto | H11: FK | J11: Del catálogo de estados | K11: No | L11: No | M11: Sí | N11: No | O11: No | P11: Estado del producto | Q11: Si | R11: Si | S11: SI | T11: SI
A12: Categoria | B12: Categoria | H12: FK | J12: Del catálogo de Categorias | K12: No | L12: No | M12: Sí | N12: No | O12: No | P12: Categoria del producto | Q12: Si | R12: Si | S12: SI | T12: NO
A14: Combinaciones únicas
A15: Nombre combinación | B15: Descripción | C15: Atributos
A16: nombre_unico | B16: Evita que se duplique el nombre | C16: Nombre
A18: Responsabilidad | C18: Descripción | G18: Entradas | J18: Salida | O18: Políticas (Reglas de Negocio) | Q18: Excepción
G19: Parámetro | H19: Tipo de dato | I19: Descripción | J19: Tipo de Dato | K19: Descripción | O19: Política | P19: Descripción | Q19: Detalle | R19: ¿Qué hago?
A20: Registrar Producto | C20: Registrar un nuevo producto que pueda ser comercializado | G20: Producto | H20: Producto | I20: Objeto de producto | J20: Producto | K20: Producto creado exitosamente | O20: Nombre único | P20: No se permite crear productos duplicados | Q20: Nombre ya registrado | R20: Mostrar error y mensaje de producto ya registrado
A21: Actualizar Producto | C21: Actualizar los datos del producto, como precio, unidad o estado | G21: CódigoProducto | H21: UUID | I21: Código del producto a modificar | J21: Boolean | K21: True si la actualización fue exitosa | Q21: Producto no encontrado | R21: Mostrar error
G22: Campos editables | H22: Texto/Numérico | I22: UnidadMedida, PrecioUnitario, Estado
A23: Consultar Producto | C23: Consultar el catálogo de productos disponibles | G23: Estado (opcional) | H23: Booleano | I23: Activo, Inactivo | J23: Array | K23: Todos los productos que cumplen el filtro | O23: Orden alfabético por nombre | P23: Mejora experiencia del usuario | Q23: Sin resultados | R23: Mostrar mensaje: “No hay productos”
A24: Inactivar Producto | C24: Inactivar un producto sin eliminarlo del historial | G24: CódigoProducto | H24: UUID | I24: Código del producto | J24: Estado Producto | K24: Nuevo estado: Inactivo | O24: No eliminar productos | P24: Se mantiene el histórico | Q24: Producto no existe o ya inactivo | R24: Mostrar alerta al usuario
A28: <<Muestreo de datos>>

Sheet Muestreo Producto
A1: <-Volver al inicio
H2: CódigoProducto | I2: Nombre | J2: Descripción | K2: UnidadMedida_ID | L2: PrecioUnitario | M2: CantidadDisponible | N2: Estado | O2: Categoria
H3: 123 | I3: Bloque 10x20x40 | J3: Bloque estructural estándar | K3: 5 (UN) | L3: 2500 | M3: 1200 | N3: 1 | O3: 1
H4: 124 | I4: Cemento Gris | J4: Cemento uso general | K4: 2 (KG) | L4: 55000 | M4: 340 | N4: 1 | O4: 2
H5: 125 | I5: Arena Lavada | J5: Arena para mezcla de concreto | K5: 4 (M³) | L5: 90000 | M5: 75 | N5: 1 | O5: 3
H6: 126 | I6: Varilla 1/2" | J6: Acero de refuerzo para columnas | K6: 1 (IN) | L6: 38000 | M6: 150 | N6: 3 | O6: 4
H7: 127 | I7: Pegante Cerámico Blanco | J7: Para instalación de cerámica | K7: 3 (G) | L7: 12000 | M7: 80 | N7: 2 | O7: 5

Sheet Estado Producto
A1: <-Volver al inicio
A2: Objeto de Dominio: | B2: ='Listado Objetos de Dominio'!A12 -> Estado Producto
A3: Descripción: | B3: ='Listado Objetos de Dominio'!$C$12 -> Corresponde a cada uno de los tipos de estados que puede tener un producto.
A4: Atributo | B4: Tipo de Dato | C4: Longitud mínima | D4: Longitud máxima | E4: Precisión | F4: Rango Inicial | G4: Rango Final | H4: Formato | I4: Valor por defecto | J4: Regla especial | K4: ¿Auto generado? | L4: ¿Calculado? | M4: ¿Obligatorio? | N4: ¿Sensible? | O4: ¿Identifica al registro? | P4: Descripción
A5: CódigoEstado | B5: Numerico | C5: 2 | D5: 10 | H5: Numerico / UUID | J5: Único | K5: Sí | L5: No | M5: Sí | N5: No | O5: Sí | P5: Código único del estado
A6: NombreEstado | B6: Texto | C6: 3 | D6: 50 | H6: Texto | J6: No duplicado | K6: No | L6: No | M6: Sí | N6: No | O6: No | P6: Nombre descriptivo del estado del producto (ej. Activo, Inactivo)
A8: Combinaciones únicas
A9: Nombre combinación | B9: Descripción | C9: Atributos
A10: estado_producto_unico | B10: No se permiten estados duplicados | C10: NombreEstado
A15: <<Muestreo de datos>>

Sheet Muestreo EstadoProducto
A1: <-Volver al inicio
E3: Codigo | F3: Nombre
E4: 1 | F4: Activo
E5: 2 | F5: Inactivo
E6: 3 | F6: Descontinuado

Sheet Venta
A1: <-Volver al inicio
A2: Objeto de Dominio: | B2: ='Listado Objetos de Dominio'!A11 -> Venta
A3: Descripción: | B3: ='Listado Objetos de Dominio'!$C$11 -> Corresponde a la transaccion comercial en la que un cliente adquiere uno o mas productos o servicios a cambio de un pago.
A4: Atributo | B4: Tipo de Dato | C4: Longitud mínima | D4: Longitud máxima | E4: Precisión | F4: Rango Inicial | G4: Rango Final | H4: Formato | I4: Valor por defecto | J4: Regla especial | K4: ¿Auto generado? | L4: ¿Calculado? | M4: ¿Obligatorio? | N4: ¿Sensible? | O4: ¿Identifica al registro? | P4: Descripción | Q4: =A21 -> Registrar nueva venta | R4: =A25 -> Consultar venta | S4: =A26 -> Cambiar Estado de Venta | T4: =A28 -> Modificar venta
A5: CódigoVenta | B5: Numerico /UUID | C5: 0 | D5: 36 | H5: UUID | J5: Único | K5: Sí | L5: No | M5: Sí | N5: No | O5: Sí | P5: Identificador único de la venta | Q5: SI | R5: SI | S5: SI | T5: Si
A6: FechaVenta | B6: Fecha-Hora | H6: DD/MM/AAAA HH:mm | I6: Fecha del sistema (Now) | J6: No puede ser futura | K6: Sí | L6: No | M6: Sí | N6: No | O6: No | P6: Fecha y hora en que se realizó la venta | Q6: SI | R6: SI | S6: NO | T6: NO
A7: Producto | B7: Producto | J7: Fk a entidad Producto | K7: No | L7: No | M7: Si | N7: No | O7: No | P7: Productos asociados a la venta (relación uno a muchos) | Q7: SI | R7: SI | S7: NO | T7: Si
A8: Cliente | B8: Cliente | J8: FK a entidad Cliente | K8: No | L8: No | M8: Sí | N8: No | O8: No | P8: Identificación del cliente asociado a la venta | Q8: SI | R8: SI | S8: NO | T8: NO
A9: TotalVenta | B9: Numerico | C9: 1 | D9: 12 | F9: 0 | G9: 99999999.99 | H9: Decimal | I9: 0 | J9: Calculado a partir del detalle | K9: No | L9: Sí | M9: Sí | N9: No | O9: No | P9: Monto total cobrado al cliente, incluyendo productos y servicios | Q9: SI | R9: SI | S9: NO | T9: Si
A10: Envio | B10: Envio | J10: fk a entidad Envio | K10: No | L10: No | M10: No | N10: No | O10: No | P10: Identificador del envío asociado, si aplica | Q10: SI | R10: SI | S10: NO | T10: Si
A11: Pago | B11: Pago | J11: Debe coincidir con catálogo pago | K11: No | L11: No | M11: Sí | N11: No | O11: No | P11: Método de pago utilizado (Contado, Crédito, Transferencia, etc.) | Q11: SI | R11: SI | S11: NO | T11: Si
A12: EstadoVenta | B12: Estado Venta | J12: Debe coincidir con catálogo Estado Venta | K12: No | L12: No | M12: Si | N12: No | O12: No | P12: Estado actual de la venta (Pendiente, Completada, Cancelada,Parcial etc.) | Q12: SI | R12: SI | S12: SI | T12: SI
A13: Trabajador | B13: Trabajador | H13: Fk | J13: Dado por el sistema | K13: No | L13: No | M13: Si | N13: No | O13: No | P13: Trabajador que registra la Venta | Q13: Si | R13: SI | S13: SI | T13: No
A15: Combinaciones únicas
A16: Nombre combinación | B16: Descripción | C16: Atributos
A17: venta_unica_codigo | B17: Garantiza que cada código de venta sea único | C17: CódigoVenta
A19: Responsabilidad | C19: Descripción | G19: Entradas | J19: Salida | O19: Políticas (Reglas de Negocio) | Q19: Excepción
G20: Parámetro | H20: Tipo de dato | I20: Descripción | J20: Tipo de Dato | K20: Descripción | O20: Política | P20: Descripción | Q20: Detalle | R20: ¿Qué hago?
A21: Registrar nueva venta | C21: Registra una venta con productos | G21: Cliente | H21: Cliente (FK) | I21: Cliente que realiza la compra | J21: Venta | K21: Venta realizada exitosamente | O21: FechaVenta debe ser la fecha actual del sistema | P21: No se puede registrar una venta con fecha futura | Q21: Cliente no registrado | R21: Registrar primero el cliente antes de continuar.
G22: Producto | H22: Lista<Producto> | I22: Productos adquiridos | O22: El método de pago debe estar en catálogo | P22: Validar que el pago sea "Contado", "Crédito", etc. | Q22: Stock insuficiente | R22: Informar al Trabajador y no permitir registrar la venta.
G23: Pago | H23: Pago (FK) | I23: Pago Realizado | O23: TotalVenta se calcula con base en los productos seleccionados | P23: No puede ser ingresado manualmente | Q23: Método de pago no válido | R23: Mostrar catálogo permitido y solicitar selección válida.
G24: Envío (opcional) | H24: Envío (FK) | I24: Envío asociado si aplica | O24: Si se indica envío, debe ser un ID válido | P24: Validar existencia en entidad Envío | Q24: Envío inválido
A25: Consultar venta | C25: Recupera toda la información de una venta específica. | G25: CódigoVenta | H25: Numerico | I25: Código único de la venta | J25: Venta | K25: Datos completos de la venta | O25: Solo usuarios con acceso pueden ver ventas. | P25: Venta no encontrada | Q25: No hay venta con el código proporcionado | R25: Mostrar mensaje: "Venta no encontrada con ese código."
A26: Cambiar Estado de Venta | C26: Permite actualizar el estado de una venta registrada. | G26: Codigo Venta | H26: Numerico | I26: Identificador de la venta | J26: EstadoVenta | K26: Estado actualizado de la venta | O26: - Solo se permite actualizar a estados válidos del catálogo. - No se puede pasar una venta estado completado , si el total de los pagos no es igual al total de la venta | P26: Estado inválido Monto total de venta no cubierto | Q26: Validar contra el catálogo de estados. Verificar existencia antes de cambiar estado si el estado cambia a anulado debe modificar la cantidad del producto en stock | R26: Mostrar error : Estado No existe Mostrar error : Venta No existe
G27: Estado Venta | H27: Texto | I27: Nuevo estado: Confirmada, Cancelada, etc.
A28: Modificar venta | C28: Permite realizar modificaciones a una venta existente | G28: CódigoVenta | H28: Numerico /UUID | I28: Campos presentes una venta | J28: Venta | K28: Venta Modificada exitosamente | O28: No se puede modificar una venta en estado Anulado | P28: No se puede realizar ningun tipo de modificación a una venta que este anulado | Q28: Verificar que el estado no sea anulado para poder modificar la venta | R28: Mostrar mensaje: "no es posible modificar una venta anulada"
G29: Producto | H29: Producto
G30: TotalVenta | H30: Numerico
G31: Envio | H31: Envio
G32: Pago | H32: Pago
G33: EstadoVenta | H33: Estado Venta
A35: <<Muestreo de datos>>

Sheet Muestreo Venta
A1: <-Volver al inicio
F3: CódigoVenta | G3: FechaVenta | H3: Producto(s) | I3: Cliente | J3: TotalVenta | K3: Envio | L3: Pago | M3: EstadoVenta
F4: VNT001 | G4: 45935.375 | H4: [123, 124] | I4: 100 | J4: 480000 | K4: 1 | L4: 9001 | M4: 3
F5: VNT002 | G5: 45966.594 | H5: [125] | I5: 101 | J5: 320000 | L5: 9002 | M5: 3
F6: VNT003 | G6: 45996.479 | H6: [122, 124] | I6: 102 | J6: 150000 | K6: 3 | L6: 9003 | M6: 3
F7: VNT004 | G7: 45790.698 | H7: [126, 127] | I7: 103 | J7: 750000 | K7: 2 | L7: 9004 | M7: 2
F8: VNT005 | G8: 45791.417 | H8: [126, 127] | I8: 104 | J8: 800000 | L8: 9005 | M8: 1

Sheet Estado Venta
A1: <-Volver al inicio
A2: Objeto de Dominio: | B2: ='Listado Objetos de Dominio'!A25 -> Estado Venta
A3: Descripción: | B3: ='Listado Objetos de Dominio'!$C$25 -> Objeto de dominio que representa los diferentes Estados de venta
A4: Atributo | B4: Tipo de Dato | C4: Longitud mínima | D4: Longitud máxima | E4: Precisión | F4: Rango Inicial | G4: Rango Final | H4: Formato | I4: Valor por defecto | J4: Regla especial | K4: ¿Auto generado? | L4: ¿Calculado? | M4: ¿Obligatorio? | N4: ¿Sensible? | O4: ¿Identifica al registro? | P4: Descripción
A5: Codigo | B5: Numerico | D5: 36 | H5: Entero | I5: Ninguno | J5: Codigo unico estado de venta | K5: Sí | L5: No | M5: Sí | N5: No | O5: Sí | P5: Código identificador del estado de venta
A6: Nombre | B6: Alfanumerico | D6: 50 | H6: Texto | I6: Ninguno | J6: Debe ser único | K6: No | L6: No | M6: Sí | N6: No | O6: No | P6: Nombre representativo de un estado de venta(ej. "Parcial")
A8: Combinaciones únicas
A9: Nombre combinación | B9: Descripción | C9: Atributos
A10: Codigo unico | B10: Codigo unico de una estado de venta | C10: Codigo
A13: <<Muestreo de datos>>

Sheet Muestreo EstadoVenta
A1: <-Volver al inicio
E3: Codigo | F3: Nombre
E4: 1 | F4: Pendiente
E5: 2 | F5: Parcial
E6: 3 | F6: Completada
E7: 4 | F7: Anulada

Sheet Tipo Identificación
A1: <-Volver al inicio
A2: Objeto de Dominio: | B2: ='Listado Objetos de Dominio'!A14 -> Tipo Identificación
A3: Descripción: | B3: ='Listado Objetos de Dominio'!$C$14 -> Objeto de dominio que representa a cada uno de los tipos de identificación que puede tener un usuario.
A4: Atributo | B4: Tipo de Dato | C4: Longitud mínima | D4: Longitud máxima | E4: Precisión | F4: Rango Inicial | G4: Rango Final | H4: Formato | I4: Valor por defecto | J4: Regla especial | K4: ¿Auto generado? | L4: ¿Calculado? | M4: ¿Obligatorio? | N4: ¿Sensible? | O4: ¿Identifica al registro? | P4: Descripción
A5: Identificador | B5: Alfanumérico | D5: 10 | H5: Código alfanumérico | J5: Debe ser único | K5: SI | L5: No | M5: SI | N5: No | O5: SI | P5: Corresponde al identificador único de los tipos de identificación exitentes.
A6: Sigla | B6: Texto | C6: 2 | D6: 5 | H6: Letras en mayúsculas | J6: No puede repetirse | K6: No | L6: No | M6: SI | N6: No | O6: No | P6: Corresponde a la sigla de cada tipo de identificación (ej: CC, CE, NIT).
A7: Nombre | B7: Texto | C7: 5 | D7: 100 | H7: Texto libre | J7: No puede repetirse | K7: No | L7: No | M7: SI | N7: No | O7: No | P7: Corresponde al nombre completo del tipo de identificación (ej: Cédula de Ciudadanía).
A9: Combinaciones únicas
A10: Nombre combinación | B10: Descripción | C10: Atributos
A11: UQ_sigla_tipo_id | B11: Evita que se repita la sigla (ej. “CC”, “CE”, etc.) | C11: Sigla
A12: UQ_nombre_tipo_id | B12: Asegura que el nombre de cada tipo sea único | C12: Nombre
A15: <<Muestreo de datos>>

Sheet Muestreo Tipo Identificación
A1: <-Volver al inicio
E3: Identificador | F3: Sigla | G3: Nombre
E4: 1 | F4: CC | G4: Cédula de Ciudadanía
E5: 2 | F5: NIT | G5: Número de Identificación Tributaria
E6: 3 | F6: CE | G6: Cédula de Extranjería
E7: 4 | F7: TI | G7: Tarjeta de Identidad
E8: 5 | F8: PAS | G8: Pasaporte

Sheet Estado Usuario
A1: <-Volver al inicio
A2: Objeto de Dominio: | B2: ='Listado Objetos de Dominio'!A15 -> Estado Usuario
A3: Descripción: | B3: ='Listado Objetos de Dominio'!$C$15 -> Corresponde a cada uno de los estados que puede tener un Administrador o Trabajador
A4: Atributo | B4: Tipo de Dato | C4: Longitud mínima | D4: Longitud máxima | E4: Precisión | F4: Rango Inicial | G4: Rango Final | H4: Formato | I4: Valor por defecto | J4: Regla especial | K4: ¿Auto generado? | L4: ¿Calculado? | M4: ¿Obligatorio? | N4: ¿Sensible? | O4: ¿Identifica al registro? | P4: Descripción
A5: codigo | B5: Texto | C5: 3 | D5: 3 | J5: Único en sistema | K5: SI | L5: No | M5: Sí | N5: No | O5: Sí | P5: Identificador único del estado del trabajador
A6: Nombre | B6: Texto | C6: 3 | D6: 100 | J6: No se debe repetir con otros estados | K6: NO | L6: No | M6: Sí | N6: No | O6: No | P6: Nombre descriptivo del estado del trabajador (ej. Activo)
A8: Combinaciones únicas
A9: Nombre combinación | B9: Descripción | C9: Atributos
A10: UQ_nombre_estado | B10: Asegura que no existan estados repetidos por nombre | C10: Nombre
A14: <<Muestreo de datos>>

Sheet Muestreo  Estado Usuario
A1: <-Volver al inicio
E3: Código | F3: Nombre
E4: ACT | F4: Activo
E5: INA | F5: Inactivo
E6: VAC | F6: Vacaciones
E7: LIC | F7: Licencia

Sheet Categoria
A1: <-Volver al inicio
A2: Objeto de Dominio: | B2: ='Listado Objetos de Dominio'!A16 -> Categoría
A3: Descripción: | B3: ='Listado Objetos de Dominio'!$C$16 -> Categoría mediante la cual se agrupan a los productos según sus características y uso
A4: Atributo | B4: Tipo de Dato | C4: Longitud mínima | D4: Longitud máxima | E4: Precisión | F4: Rango Inicial | G4: Rango Final | H4: Formato | I4: Valor por defecto | J4: Regla especial | K4: ¿Auto generado? | L4: ¿Calculado? | M4: ¿Obligatorio? | N4: ¿Sensible? | O4: ¿Identifica al registro? | P4: Descripción | Q4: =A16 -> Crear Categoria | R4: =A17 -> Editar categoría
A5: Codigo | B5: Alfanumérico | C5: 1 | D5: 20 | J5: Codigo unico | K5: Sí | L5: No | M5: Sí | N5: No | P5: Identificador único de la categoria de un producto | Q5: Sí | R5: No
A6: Nombre | B6: Alfanumérico | C6: 3 | D6: 100 | J6: No puede repetirse con otras categorías | K6: No | L6: No | M6: Sí | N6: No | P6: Nombre representativo de la categoría de un producto | Q6: Sí | R6: Sí/Opcional
A7: Descripción: | B7: Texto | C7: 0 | D7: 250 | J7: Opcional | K7: No | L7: No | M7: No | N7: No | P7: Explicación detallada del uso o enfoque de una categoria | Q7: Opcional | R7: Sí/Opcional
A8: FechaCreacion | B8: DateTime | H8: yyyy-MM-dd HH:mm:ss | I8: now() | J8: Se asigna al momento de crear | K8: Sí | L8: No | M8: Si | N8: No | P8: Fecha y hora en que fue creada la categoría | Q8: Automático | R8: No
A10: Combinaciones únicas
A11: Nombre combinación | B11: Descripción | C11: Atributos
A12: UQ_nombre_categoria | B12: Asegura que no haya dos categorías con el mismo nombre | C12: Nombre
A14: Responsabilidad | C14: Descripción | G14: Entradas | J14: Salida | O14: Políticas (Reglas de Negocio) | Q14: Excepción
G15: Parámetro | H15: Tipo de dato | I15: Descripción | J15: Tipo de Dato | K15: Descripción | O15: Política | P15: Descripción | Q15: Detalle | R15: ¿Qué hago?
A16: Crear Categoria | C16: Crear una nueva categoría en el sistema | G16: nombre | H16: String | I16: Nombre de la categoría | J16: Categoría | K16: Objeto creado con sus atributos | O16: Validar unicidad de nombre | P16: El nombre no debe existir previamente | Q16: Nombre duplicado | R16: Retornar error y mostrar mensaje nombre categoria ya existe
A17: Editar categoría | C17: Editar nombre o descripción de una categoría existente | G17: codigo | H17: String | I17: Código de la categoría | J17: Categoría | K17: Categoría actualizada | O17: No cambiar el código | P17: El código es inmutable una vez creado | Q17: Nuevo nombre ya existe | R17: Retornar error y mantener nombre anterior
G18: nombre | H18: String | I18: Nuevo nombre | O18: Validar unicidad de nombre | P18: Si cambia el nombre, debe ser único
A22: <<Muestreo de datos>>

Sheet Muestreo Categoria
A1: <-Volver al inicio
E3: Código | F3: Nombre
E4: 1 | F4: BLOQUE
E5: 2 | F5: ARENA
E6: 3 | F6: HERRAMIENTAS
E7: 4 | F7: HIERRO
E8: 5 | F8: CEMENTO

Sheet Pais
A1: <-Volver al inicio
A2: Objeto de Dominio: | B2: ='Listado Objetos de Dominio'!A17 -> País
A3: Descripción: | B3: ='Listado Objetos de Dominio'!$C$17 -> Objeto de dominio que representa a un pais al que pertenecen varios departamentos
A4: Atributo | B4: Tipo de Dato | C4: Longitud mínima | D4: Longitud máxima | E4: Precisión | F4: Rango Inicial | G4: Rango Final | H4: Formato | I4: Valor por defecto | J4: Regla especial | K4: ¿Auto generado? | L4: ¿Calculado? | M4: ¿Obligatorio? | N4: ¿Sensible? | O4: ¿Identifica al registro? | P4: Descripción
A5: Identificador | B5: Alfanumérico | C5: 36 | D5: 36 | H5: Formato de un identificador iso | J5: -Quitar espacios en blanco al inicio y al final. -Siempre debe tener 36 caracteres, donde cada uno de ellos puede un dígito o una letra desde la A hasta la F. | K5: No | L5: No | M5: Si | N5: No | O5: Si | P5: Atributo que representa el identificador de País, asegurando que sea único.
A6: Nombre | B6: Texto | C6: 1 | D6: 48 | H6: Sólo letras y espacios | J6: -Quitar espacios en blanco al inicio y al final. | K6: No | L6: No | M6: No | N6: No | O6: No | P6: Atributo que representa el nombre de un País
A8: Combinaciones únicas
A9: Nombre combinación | B9: Descripción | C9: Atributos
A10: Nombre Único | B10: No es posible tener más de un País con el mismo nombre | C10: Nombre
A12: <<Muestreo de datos>>

Sheet Muestreo Pais
A1: <-Volver al inicio
J3: Identificador | K3: Nombre
J4: 169 | K4: Colombia
J5: 211 | K5: Chile
J6: 63 | K6: Argentina

Sheet Departamento
A1: <-Volver al inicio
A2: Objeto de Dominio: | B2: ='Listado Objetos de Dominio'!A18 -> Departamento
A3: Descripción: | B3: ='Listado Objetos de Dominio'!$C$18 -> Objeto de dominio que representa a un departamento al que pertenecen varias ciudades.
A4: Atributo | B4: Tipo de Dato | C4: Longitud mínima | D4: Longitud máxima | E4: Precisión | F4: Rango Inicial | G4: Rango Final | H4: Formato | I4: Valor por defecto | J4: Regla especial | K4: ¿Auto generado? | L4: ¿Calculado? | M4: ¿Obligatorio? | N4: ¿Sensible? | O4: ¿Identifica al registro? | P4: Descripción
A5: Codigo | B5: Numerico | C5: 36 | D5: 36 | H5: Numerico | J5: -Quitar espacios en blanco al inicio y al final. -Siempre debe tener 36 caracteres, donde cada uno de ellos puede un dígito o una letra desde la A hasta la F. | K5: Si | L5: No | M5: Si | N5: No | O5: SI | P5: Código único del departamento (ej: "05" = Antioquia).
A6: Nombre | B6: Alfanumérico | C6: 1 | D6: 42 | H6: Sólo letras y espacios | J6: -Quitar espacios en blanco al inicio y al final. | K6: No | L6: No | M6: Si | N6: No | O6: NO | P6: Nombre oficial (ej: "Antioquia"). No puede repetirse en el mismo país.
A7: País | B7: Pais | K7: No | L7: No | M7: Si | N7: No | O7: NO | P7: Código ISO del país (ej: "CO" = Colombia).
A9: Combinaciones únicas
A10: Nombre combinación | B10: Descripción | C10: Atributos
A11: Nombre + Pais | B11: Combinación única que Evita nombres duplicados dentro del mismo país (ej: dos "Antioquia" en Colombia). | C11: Nombre
C12: País
A16: <<Muestreo de datos>>

Sheet Muestreo Departamento
A1: <-Volver al inicio
I3: Codigo | J3: Nombre | K3: Pais
I4: 1 | J4: Cordoba | K4: Argentina (63)
I5: 2 | J5: Buenos Aires | K5: Argentina (63)
I6: 3 | J6: Antioquia | K6: Colombia (169)
I7: 4 | J7: Bogota | K7: Colombia (169)
I8: 5 | J8: Araucanía | K8: Chile (211)
I9: 6 | J9: Antofagasta | K9: Chile (211)

Sheet Ciudad
A1: <-Volver al inicio
A2: Objeto de Dominio: | B2: ='Listado Objetos de Dominio'!A19 -> Ciudad
A3: Descripción: | B3: ='Listado Objetos de Dominio'!$C$19 -> Objeto de dominio que representa a cada una de las ciudades
A4: Atributo | B4: Tipo de Dato | C4: Longitud mínima | D4: Longitud máxima | E4: Precisión | F4: Rango Inicial | G4: Rango Final | H4: Formato | I4: Valor por defecto | J4: Regla especial | K4: ¿Auto generado? | L4: ¿Calculado? | M4: ¿Obligatorio? | N4: ¿Sensible? | O4: ¿Identifica al registro? | P4: Descripción
A5: Identificador | B5: NUmerico | C5: 36 | D5: 36 | H5: Numerico Entero | J5: -Quitar espacios en blanco al inicio y al final. -Siempre debe tener 36 caracteres, donde cada uno de ellos puede un dígito o una letra desde la A hasta la F. | K5: Si | L5: No | M5: Si | N5: No | O5: Si | P5: Atributo que representa el identificador de una Ciudad, asegurando que sea único.
A6: Nombre | B6: Alfanumérico | C6: 1 | D6: 20 | H6: Sólo letras y espacios | J6: -Quitar espacios en blanco al inicio y al final. | K6: No | L6: No | M6: Si | N6: No | O6: No | P6: Atributo que representa el nombre de una Ciudad.
A7: Departamento | B7: Departamento | K7: No | L7: No | M7: Si | N7: No | O7: No | P7: Atributo que representa el Departamento al que pertenece una Ciudad.
A10: Combinaciones únicas
A11: Nombre combinación | B11: Descripción | C11: Atributos
A16: <<Muestreo de datos>>

Sheet Muestreo Ciudad
A1: <-Volver al inicio
I5: Identificador | J5: Nombre | K5: Departamento
I6: 1 | J6: Medellín | K6: 3
I7: 2 | J7: Envigado | K7: 3
I8: 3 | J8: Antofagasta | K8: 6
I9: 4 | J9: Villarrica | K9: 5
I10: 5 | J10: Mar del plata | K10: 2
I11: 6 | J11: Bahía Blanca | K11: 2

Sheet Devolución
A1: <-Volver al inicio
A2: Objeto de Dominio: | B2: ='Listado Objetos de Dominio'!A26 -> Devolución
A3: Descripción: | B3: ='Listado Objetos de Dominio'!$C$26 -> Registra la devolución total o parcial de productos de una Venta, con su motivo y el ajuste de inventario correspondiente.
A4: Atributo | B4: Tipo de Dato | C4: Longitud mínima | D4: Longitud máxima | E4: Precisión | F4: Rango Inicial | G4: Rango Final | H4: Formato | I4: Valor por defecto | J4: Regla especial | K4: ¿Auto generado? | L4: ¿Calculado? | M4: ¿Obligatorio? | N4: ¿Sensible? | O4: ¿Identifica al registro? | P4: Descripción | Q4: =A22 -> Registrar Nueva dovolución | R4: =A27 -> Consultar devolución | S4: =A28 -> Modificar Devolución
A5: CódigoDevolución | B5: Serial | C5: 0 | D5: 36 | H5: UUID | J5: Único | K5: Sí | L5: No | M5: Sí | N5: No | O5: Sí | P5: Identificador único de la devolución | Q5: SI | R5: SI | S5: NO
A6: FechaDevolución | B6: Fecha | H6: DD/MM/AAAA | I6: Fecha del sistema (Now) | J6: No puede ser futura | K6: No | L6: No | M6: Sí | N6: No | O6: No | P6: Fecha y hora de registro de la devolución | Q6: SI | R6: SI | S6: Si
A7: Venta | B7: Venta | J7: FK a entidad Venta | K7: No | L7: No | M7: Sí | N7: No | O7: No | P7: Venta a la que pertenece la devolución | Q7: SI | R7: SI | S7: NO
A8: Cliente | B8: Cliente | J8: Tomado de la Venta | K8: No | L8: Sí | M8: Sí | N8: No | O8: No | P8: Cliente asociado | Q8: SI | R8: SI | S8: NO
A9: Producto | B9: Producto | J9: Fk Producto | K9: No | L9: No | M9: Sí | N9: No | O9: No | P9: Productos devueltos | Q9: SI | R9: SI | S9: SI
A10: TotalDevuelto | B10: Numérico | E10: 2 | F10: 0 | H10: Decimal | I10: 0 | J10: Suma de subtotales aceptados de los ítems | K10: No | L10: Sí | M10: Sí | N10: No | O10: No | P10: Valor monetario de lo aceptado a devolver | Q10: SI | R10: SI | S10: SI
A11: Observaciones | B11: Texto | C11: 0 | D11: 500 | J11: Observaciones de la devolución | K11: No | L11: No | M11: Sí | N11: No | O11: No | P11: Comentarios de la devolución | Q11: SI | R11: SI | S11: SI
A12: Precio | B12: Numérico | H12: Decimal | J12: Precio de cada uno de los productos | K12: No | L12: No | M12: Sí | N12: No | O12: No | P12: precio de los productos de la devolución | Q12: SI | R12: SI | S12: SI
A13: CantidadProductoDevuelto | B13: Numérico | J13: Cantidad del producto regresado en la devolución | K13: No | L13: No | M13: Sí | N13: No | O13: No | P13: Cantidad del producto devuelto | Q13: SI | R13: SI | S13: SI
A14: Trabajador | B14: Trabajador | I14: Dado por el sistema | J14: FK a usuario que registra | K14: No | L14: No | M14: Sí | N14: No | O14: No | P14: Trabajador/administrador que registra la devolución | Q14: SI | R14: SI | S14: No
A16: Combinaciones únicas
A17: Nombre combinación | B17: Descripción | C17: Atributos
A18: Devolución_unica_codigo | B18: Garantiza que cada código de devolución sea único | C18: CódigoDevolución
A20: Responsabilidad | C20: Descripción | G20: Entradas | J20: Salida | O20: Políticas (Reglas de Negocio) | Q20: Excepción Excepción
A21: Responsabilidad | C21: Descripción | G21: Parámetro | H21: Tipo de dato | I21: Descripción | J21: Salida Tipo de Dato | K21: Salida Descripción | O21: Reglas de negocio Política | P21: Reglas de negocio Descripción | Q21: Excepción Detalle | R21: Excepción ¿Qué hago?
A22: Registrar Nueva dovolución | C22: Registra una devolución (total o parcial) asociada a una venta existente. | G22: Venta | H22: Venta (FK) | I22: Venta a la que pertenece la devolución. | J22: Devolución | K22: Devolución realizada exitosamente | O22: La venta debe existir y estar en estado que permita devolución. | P22: Venta no existe o está anulada | Q22: Venta no registrada | R22: Mostrar mensaje de venta no encontrada
G23: Producto | H23: Lista<Producto> | I23: Ítems a devolver: Producto (FK), CantidadDevuelta, PrecioAplicado. | O23: Cada producto del detalle debe existir en la venta original. | P23: Los productos solo deben corresponder con los adjuntados en la venta | Q23: Producto no pertenece a la venta | R23: Mostrar mensaje de error producto no encontrado en la venta
G24: Pago | H24: Pago (FK) | I24: Pago Realizado | O24: Estado de venta invalido | P24: No permite realizar una devolución a una venta en estado pendiente o cancelada | Q24: No se puede realizar una devolución a una vetna pendiente o cancelada | R24: Mostrar mensaje de error estado de venta invalido para realizar una devolución
G25: Observaciones | H25: Texto | I25: Motivo de devolución.
G26: TotalDevuelto | H26: Númerico | I26: Valor total devolución
A27: Consultar devolución | C27: Recupera toda la información de una devolución específica. | G27: CódigoDevolución | H27: Numérico/UUID | I27: Identificador único de la devolución. | J27: Devolución | K27: Datos completos de la devolución. | O27: La devolución debe existir. | P27: Devolución no encontrada | Q27: No hay Devolución con el código proporcionado | R27: Mostrar mensaje: "Devolución no encontrada con ese código."
A28: Modificar Devolución | C28: Permite ajustar una devolución no procesada (detalle, motivo o método). | G28: Venta | H28: Venta (FK) | I28: Campos presentes una Devolución | J28: Devolución | K28: Devolución Modificada exitosamente | O28: Topes y pertenencia | P28: Respetar topes de cantidad y pertenencia de productos a la venta | Q28: Cantidad supera tope / Producto fuera de la venta | R28: Mostrar mensaje: "no es posible modificar una Devolución que supera la cantidad total en venta"
G29: Producto | H29: Lista<Producto>
G30: Pago | H30: Pago (FK)
G31: Observaciones | H31: Texto
G32: TotalDevuelto | H32: Númerico
A35: <<Muestreo de datos>>

Sheet Muestreo Devolucion
A1: <-Volver al inicio
E4: CódigoDevolución | F4: FechaDevolución | G4: Venta | H4: Cliente | I4: Producto | J4: Precio | K4: CantidadProductoDevuelto | L4: TotalDevuelto | M4: Observaciones | N4: Trabajador
E5: DEV001 | F5: 45792.396 | G5: VNT003 | H5: 102 | I5: [124] | J5: 100000 | K5: 5 | L5: =Tabla25[[#This Row],[Precio]]*Tabla25[[#This Row],[CantidadProductoDevuelto]] -> 500000 | M5: Defecto en lote recibido | N5: 2001
E6: DEV002 | F6: 45793.424 | G6: VNT001 | H6: 100 | I6: [123] | J6: 99999 | K6: 4 | L6: =Tabla25[[#This Row],[Precio]]*Tabla25[[#This Row],[CantidadProductoDevuelto]] -> 399996 | M6: Cambio por especificación | N6: 2002
E7: DEV003 | F7: 45793.656 | G7: VNT004 | H7: 103 | I7: [126] | J7: 25000 | K7: 4 | L7: =Tabla25[[#This Row],[Precio]]*Tabla25[[#This Row],[CantidadProductoDevuelto]] -> 100000 | M7: Exceso no requerido | N7: 2001
E8: DEV004 | F8: 45794.472 | G8: VNT005 | H8: 104 | I8: [127] | J8: 4300 | K8: 5 | L8: =Tabla25[[#This Row],[Precio]]*Tabla25[[#This Row],[CantidadProductoDevuelto]] -> 21500 | M8: Daño en transporte | N8: 2003
E9: DEV005 | F9: 45795.372 | G9: VNT001 | H9: 100 | I9: [124] | J9: 21111 | K9: 6 | L9: =Tabla25[[#This Row],[Precio]]*Tabla25[[#This Row],[CantidadProductoDevuelto]] -> 126666 | M9: Error de facturación | N9: 2003
