Workbook

Sheet Flujo de eventos anémico

Sheet Listado Objetos de Dominio
A1: Nombre | B1: Descripción | C1: Responsable
A2: Proveedor | B2: Entidad que representa a las empresas o personas que suministran el abastecimiento del negocio. | C2: Alexander
A3: Administrador | B3: Entidad que representa Usuario con privilegios totales sobre la plataforma. Se encarga de configurar parámetros globales, gestionar roles y permisos de Trabajadores y supervisar la generación de Reportes. | C3: Julián
A4: Abastecimiento | B4: Proceso y registro de la adquisición interna de insumos para producción. Documenta las órdenes de compra, fechas de entrega, cantidades solicitadas y precios que alimentaran el Inventario | C4: Alexander
A5: Reporte | B5: Informe que consolida información de los distintos procesos (ventas, compras/abastecimientos, producción, inventario). Generado por Administradores o Trabajadores para apoyar la toma de decisiones estratégicas. | C5: Julián
A6: Trabajador | B6: Empleado del negocio que dispone de un Usuario en el sistema. Ejecuta operaciones como registrar Ventas, registrar Producción, gestionar Abastecimientos y atender consultas. | C6: Alexander
A7: Cliente | B7: Comprador de bloques y materiales. Registra datos de contacto, histórico de pedidos, métodos de pago y preferencias de entrega. Puede interactuar con el portal para ver catálogo y solicitar atención. | C7: Julián
A8: Información de interes | B8: Hace referencia a la información relevante sobre el perfil y finalidad del cliente en relación con los productos, incluyendo el uso previsto y su rol dentro del sector, como constructor, contratista, revendedor, entre otros | C8: Alexander
A9: Producción | B9: Registro diario de bloques fabricados: cantidad producida, lote, fecha, insumos y trabajadores responsables. | C9: Julián
A10: Producto | B10: Definición de cada artículo que el negocio ofrece a sus clientes. | C10: Alexander
A11: Venta | B11: Corresponde a la transaccion comercial en la que un cliente adquiere uno o mas productos o servicios a cambio de un pago. | C11: Julián
A12: Estado Producto | B12: Corresponde a cada uno de los tipos de estados que puede tener un producto. | C12: Alexander
... A26: Devolución | B26: Registra la devolución total o parcial de productos de una Venta, con su motivo,y método de reembolso (si aplica) y el ajuste de inventario correspondiente. | C26: Registra la devolución total o parcial de productos de una Venta, con su motivo,y método de reembolso (si aplica) y el ajuste de inventario correspondiente.

Sheet Proveedor
A1: <-Volver al inicio
A2: Objeto de Dominio: | B2: ='Listado Objetos de Dominio'!$A$2 -> Proveedor
A3: Descripción: | B3: ='Listado Objetos de Dominio'!$B$2 -> Entidad que representa a las empresas o personas que suministran el abastecimiento del negocio.
A4: Actor | B4: Action/Command | D4: Read Model | F4: Business Rule/Policy | H4: External System | I4: Domain Event | J4: Hotspot/questions/Risk | K4: Eventos Previos | L4: Comandos Posteriores
A5: Actor | B5: Acción | C5: Descripción | D5: Información externa | F5: Políticas | H5: Sistema Externo | I5: Evento | J5: Aspectos por solucionar
D6: Información | E6: Descripción | F6: Número | G6: Descripción
A7: Administrador | B7: Registrar Proveedor | C7: Permite registrar la información de un nuevo proveedor. | F7: PROV-POL-001 | G7: No permitir duplicidad de codigo o Razón Social. | I7: Proveedor registrado | K7: Ninguno | L7: Modificar Proveedor
A8: Administrador | B8: Modificar Proveedor | C8: Permite actualizar la información de un proveedor existente. | F8: PROV-POL-002 | G8: No permitir modificación de campos clave. | I8: Proveedor modificado | K8: Proveedor registrado | L8: Consultar Proveedor
A9: Administrador/Trabajador | B9: Consultar Proveedor | C9: Permite consultar información detallada del proveedor, incluyendo historial de abastecimiento y productos asociados. | F9: PROV-POL-004 | G9: Controlar acceso a datos sensibles según perfil de usuario. | I9: Proveedor consultado | J9: Mantener actualizado el historial. | K9: Proveedor registrado | L9: Crear Abastecimiento
A10: Administrador/Trabajador | B10: Consultar lista de Proveedores | C10: Permite consultar todos los proveedores registrados, con filtros por estado. | F10: PROV-POL-005 | G10: Permitir filtros avanzados (activo/inactivo) | I10: Lista de proveedores consultada | J10: Optimizar búsquedas frecuentes. | K10: Proveedor registrado | L10: Consultar Proveedor
A11: Administrador | B11: Cambiar estado proveedor | C11: Permite cambiar el estado de un proveedor (activo, inactivo). | D11: Estados posibles | E11: Activo, Inactivo | F11: PROV-POL-006 | G11: Solo se puede cambiar estado si existe proveedor | I11: Estado de proveedor cambiado | K11: Proveedor creado | L11: Consultar proveedor

Sheet Administrador
A1: <-Volver al inicio
A2: Objeto de Dominio: | B2: ='Listado Objetos de Dominio'!$A$3 -> Administrador
A3: Descripción: | B3: ='Listado Objetos de Dominio'!$B$3 -> Entidad que representa Usuario con privilegios totales sobre la plataforma. Se encarga de configurar parámetros globales, gestionar roles y permisos de Trabajadores y supervisar la generación de Reportes.
A4: Actor | B4: Action/Command | D4: Read Model | F4: Business Rule/Policy | H4: External System | I4: Domain Event | J4: Hotspot/questions/Risk | K4: Eventos Previos | L4: Comandos Posteriores
A5: Actor | B5: Acción | C5: Descripción | D5: Información externa | F5: Políticas | H5: Sistema Externo | I5: Evento | J5: Aspectos por solucionar
D6: Información | E6: Descripción | F6: Número | G6: Descripción
A7: Administrador | B7: Crear administrador | C7: Permite registrar un nuevo usuario administrador. | F7: ADM-POL-001 | G7: Validar que no exista un usuario con el mismo número de identificación y correo electrónico. Validar política de contraseña segura. | I7: Administrador creado | J7: ¿Qué pasa si el correo ya está registrado?, ¿Validar política de contraseña segura? | L7: Consultar administrador
A8: Administrador | B8: Consultar administrador | C8: Permite ver información y detalles de un usuario administrador. | F8: ADM-POL-002 | G8: Mostrar solo datos no sensibles (ej: sin mostrar la contraseña). | I8: Administrador consultado | J8: ¿Quién puede consultar administradores? | K8: Administrador creado | L8: Modificar administrador
A9: Administrador | B9: Modificar administrador | C9: Permite modificar datos de un administrador existente. | F9: ADM-POL-003 | G9: No permitir duplicar correo o número de identificación. Validar cambios en roles y permisos. | I9: Administrador modificado | J9: ¿Qué restricciones para modificar datos críticos? | K9: Administrador creado | L9: Consultar administrador
A10: Administrador | B10: Deshabilitar administrador | C10: Permite cambiar el estado de un administrador a inactivo (no puede acceder). | F10: ADM-POL-004 | G10: No permitir deshabilitar el último administrador activo. | I10: Administrador deshabilitado | J10: ¿Qué hacer si es el único administrador? | K10: Administrador creado | L10: Consultar administrador
A11: Administrador | B11: Cambiar contraseña | C11: Permite restablecer o cambiar la contraseña del administrador. | F11: ADM-POL-005 | G11: Contraseña debe cumplir reglas de seguridad (largo, caracteres especiales, etc). | I11: Contraseña modificada | J11: ¿Política de vencimiento de contraseñas? | K11: Administrador consultado | L11: Iniciar sesión

Sheet Abastecimiento
A1: <-Volver al inicio
A2: Objeto de Dominio: | B2: ='Listado Objetos de Dominio'!$A$4 -> Abastecimiento
A3: Descripción: | B3: ='Listado Objetos de Dominio'!$B$4 -> Proceso y registro de la adquisición interna de insumos para producción. Documenta las órdenes de compra, fechas de entrega, cantidades solicitadas y precios que alimentaran el Inventario
A4: Actor | B4: Action/Command | D4: Read Model | F4: Business Rule/Policy | H4: External System | I4: Domain Event | J4: Hotspot/questions/Risk | K4: Eventos Previos | L4: Comandos Posteriores
A5: Actor | B5: Acción | C5: Descripción | D5: Información externa | F5: Políticas | H5: Sistema Externo | I5: Evento | J5: Aspectos por solucionar
D6: Información | E6: Descripción | F6: Número | G6: Descripción
A7: Administrador /Trabajador | B7: Crear abastecimiento | C7: Registra un nuevo abastecimiento para actualizar el inventario | D7: Producto, Proveedor | E7: Catálogo de productos y proveedores activos | F7: ABAST-POL-001 | G7: No se permite abastecer con cantidad o precio <= 0 | I7: Abastecimiento creado | K7: Proveedor registrado | L7: Generar entrada de inventario
A8: Administrador /Trabajador | B8: Modificar Abastecimiento | C8: Permite actualizar el producto o las cantidades en un abastecimiento | D8: Producto | E8: Catálogo de productos activos | F8: ABAST-POL-002 | G8: No se permite modificar con cantidad <= 0. Solo si el abastecimiento no ha sido cerrado. | I8: Abastecimiento actualizado | K8: Abastecimiento creado | L8: Actualizar inventario
A9: Administrador /Trabajador | B9: Consultar abastecimientos | C9: Permite visualizar los registros de abastecimiento | F9: ABAST-POL-003 | G9: La fecha inicial no debe ser mayor a la fecha final | I9: Abastecimiento Encontrado | K9: Abastecimiento creado | L9: Exportar reporte, ver detalle

Sheet Reporte
A1: <-Volver al inicio
A2: Objeto de Dominio: | B2: ='Listado Objetos de Dominio'!$A$5 -> Reporte
A3: Descripción: | B3: ='Listado Objetos de Dominio'!$B$5 -> Informe que consolida información de los distintos procesos (ventas, compras/abastecimientos, producción, inventario). Generado por Administradores o Trabajadores para apoyar la toma de decisiones estratégicas.
A4: Actor | B4: Action/Command | D4: Read Model | F4: Business Rule/Policy | H4: External System | I4: Domain Event | J4: Hotspot/questions/Risk | K4: Eventos Previos | L4: Comandos Posteriores
A5: Actor | B5: Acción | C5: Descripción | D5: Información externa | F5: Políticas | H5: Sistema Externo | I5: Evento | J5: Aspectos por solucionar
D6: Información | E6: Descripción | F6: Número | G6: Descripción
A7: Administrador | B7: Generar reporte | C7: Permite crear un informe consolidado de ventas, compras, producción e inventario. | D7: Fechas, filtros de información | E7: Parámetros para filtrar la información | F7: REP-POL-001 | G7: Solo usuarios autenticados pueden generar reportes. Datos deben ser exactos y completos. | I7: Reporte generado | J7: ¿Qué procesos incluir?, ¿Periodicidad máxima?, confidencialidad. | K7: Acciones en ventas, compras, etc. | L7: Exportar, consultar
A8: Administrador | B8: Consultar reporte | C8: Permite visualizar reportes generados anteriormente. | D8: Fechas, tipo de reporte | E8: Filtros de búsqueda | F8: REP-POL-002 | G8: Solo administradores con permisos pueden consultar reportes históricos. | I8: Reporte consultado | J8: ¿Dónde se almacenan?, ¿Historial completo o parcial? | K8: Reporte generado | L8: Exportar, eliminar
A9: Administrador | B9: Exportar reporte | C9: Permite exportar el reporte a formatos como PDF o Excel. | D9: Formato de exportación | E9: PDF, Excel, CSV, etc. | F9: REP-POL-004 | G9: Debe respetar formatos estandarizados, incluir metadatos de generación (fecha, usuario). | I9: Reporte exportado | J9: ¿Qué formatos soportar?, ¿Dónde se almacenan los archivos? | K9: Reporte generado | L9: Ninguno

Sheet Trabajador
A1: <-Volver al inicio
A2: Objeto de Dominio: | B2: ='Listado Objetos de Dominio'!$A$6 -> Trabajador
A3: Descripción: | B3: ='Listado Objetos de Dominio'!$B$6 -> Empleado del negocio que dispone de un Usuario en el sistema. Ejecuta operaciones como registrar Ventas, registrar Producción, gestionar Abastecimientos y atender consultas.
A4: Actor | B4: Action/Command | D4: Read Model | F4: Business Rule/Policy | H4: External System | I4: Domain Event | J4: Hotspot/questions/Risk | K4: Eventos Previos | L4: Comandos Posteriores
A5: Actor | B5: Acción | C5: Descripción | D5: Información externa | F5: Políticas | H5: Sistema Externo | I5: Evento | J5: Aspectos por solucionar
D6: Información | E6: Descripción | F6: Número | G6: Descripción
A7: Administrador | B7: Registrar Trabajador | C7: Crea un nuevo trabajador asignándole un usuario en el sistema | F7: TRAB-POL-001 | G7: Un trabajador no puede registrarse sin un usuario y rol válidos | I7: Trabajador registrado | K7: Usuario creado | L7: Activar usuario en sistema
A8: Administrador | B8: Consultar Trabajadores | C8: Permite listar o buscar trabajadores activos o inactivos | F8: TRAB-POL-002 | G8: Validar filtros ingresados. Solo usuarios con permisos pueden consultar. | I8: Resultado de consulta | J8: ¿Muestra también históricos? ¿Requiere paginación si hay muchos registros? | K8: Trabajadores registrados | L8: Ver detalle de trabajador
A9: Administrador | B9: Modificar datos de Trabajador | C9: Actualiza información como rol, estado o área | F9: TRAB-POL-003 | G9: No se puede modificar usuario asignado. Solo se modifican datos administrativos. | I9: Datos de trabajador actualizados | J9: ¿Qué pasa si ya fue desactivado? ¿Se debe notificar al trabajador? | K9: Trabajador registrado | L9: Generar nuevo contrato (opcional)
A10: Administrador | B10: Cambiar estado de trabajador | C10: Permite activar o inactivar trabajadores del sistema | F10: TRAB-POL-004 | G10: No se puede eliminar. Solo se permite cambiar estado. | I10: Estado de trabajador actualizado | J10: ¿Qué pasa si tiene tareas asignadas pendientes? ¿Se notificará al jefe inmediato? | K10: Trabajador registrado | L10: Reasignar funciones si aplica

Sheet Cliente
A1: <-Volver al inicio
A2: Objeto de Dominio: | B2: ='Listado Objetos de Dominio'!$A$7 -> Cliente
A3: Descripción: | B3: ='Listado Objetos de Dominio'!$B$7 -> Comprador de bloques y materiales. Registra datos de contacto, histórico de pedidos, métodos de pago y preferencias de entrega. Puede interactuar con el portal para ver catálogo y solicitar atención.
A4: Actor | B4: Action/Command | D4: Read Model | F4: Business Rule/Policy | H4: External System | I4: Domain Event | J4: Hotspot/questions/Risk | K4: Eventos Previos | L4: Comandos Posteriores
A5: Actor | B5: Acción | C5: Descripción | D5: Información externa | F5: Políticas | H5: Sistema Externo | I5: Evento | J5: Aspectos por solucionar
D6: Información | E6: Descripción | F6: Número | G6: Descripción
A7: Administrador /Trabajador | B7: Registrar cliente | C7: Permite agregar un nuevo cliente (nombre, documento, contacto, tipo, etc.). | D7: Datos del cliente | E7: Nombre, documento, contacto | F7: CLI-POL-001 | G7: Validar que no exista el mismo documento. | I7: Cliente registrado | J7: ¿Validar duplicados? | K7: Ninguno | L7: Actualizar, consultar cliente
A8: Administrador /Trabajador | B8: Actualizar cliente | C8: Modifica datos de un cliente existente. | D8: Nuevo dato del cliente | E8: Cambios en contacto, nombre, etc. | F8: CLI-POL-002 | G8: Solo trabajadores pueden modificar. | I8: Cliente actualizado | J8: ¿Registrar historial de cambios? | K8: Registrar cliente | L8: Consultar cliente
A9: Administrador /Trabajador | B9: Consultar cliente | C9: Permite buscar clientes para asociar a ventas y visualizar historial. | D9: Filtros de búsqueda | E9: Documento, nombre, teléfono | F9: CLI-POL-003 | G9: Solo personal autorizado puede consultar. | I9: Cliente consultado | J9: ¿Paginación?, ¿Búsqueda por varios campos? | K9: Registrar/Actualizar cliente | L9: Asociar cliente a venta

Sheet Produccion
A1: <-Volver al inicio
A2: Objeto de Dominio: | B2: ='Listado Objetos de Dominio'!$A$9 -> Producción
A3: Descripción: | B3: ='Listado Objetos de Dominio'!$B$9 -> Registro diario de bloques fabricados: cantidad producida, lote, fecha, insumos y trabajadores responsables.
A4: Actor | B4: Action/Command | D4: Read Model | F4: Business Rule/Policy | H4: External System | I4: Domain Event | J4: Hotspot/questions/Risk | K4: Eventos Previos | L4: Comandos Posteriores
A5: Actor | B5: Acción | C5: Descripción | D5: Información externa | F5: Políticas | H5: Sistema Externo | I5: Evento | J5: Aspectos por solucionar
D6: Información | E6: Descripción | F6: Número | G6: Descripción
A7: Administrador/Trabajador | B7: Registrar producción | C7: Permite ingresar el registro de la producción diaria: producto, cantidades, insumos. | D7: Producto, Insumo, Trabajador | E7: Datos de producto, insumos utilizados, etc. | F7: PROD-POL-001 | G7: No se puede registrar cantidades menores o iguales a cero. | I7: Producción registrada | J7: ¿Cómo validar insumos usados vs inventario disponible? | K7: Insumos disponibles | L7: Consultar producción, Actualizar producción
A8: Administrador/Trabajador | B8: Consultar producción | C8: Permite visualizar el histórico de registros de producción. | D8: Filtros por fecha, producto | E8: Buscar por fechas, trabajador, producto | F8: PROD-POL-002 | G8: Solo usuarios autorizados pueden consultar. | I8: Producción consultada | J8: ¿Cómo mostrar sólo registros activos? | K8: Producción registrada | L8: Ninguno
A9: Administrador/Trabajador | B9: Actualizar producción | C9: Permite modificar un registro de producción por errores detectados. | D9: Código de producción | E9: Identificador de registro | F9: PROD-POL-003 | G9: Solo se puede modificar si el registro no está asociado a venta. | I9: Producción actualizada | K9: Producción registrada | L9: Consultar producción
A10: Administrador | B10: Eliminar registro producción | C10: Permite eliminar un registro si fue creado por error. | D10: Código de producción | E10: Identificador de registro | F10: PROD-POL-004 | G10: Solo registros del mismo día, y sin ventas asociadas. | I10: Producción eliminada | K10: Producción registrada | L10: Consultar producción

Sheet Información de interes
A1: <-Volver al inicio
A2: Objeto de Dominio: | B2: ='Listado Objetos de Dominio'!$A$8 -> Información de interes
A3: Descripción: | B3: ='Listado Objetos de Dominio'!$B$8 -> Hace referencia a la información relevante sobre el perfil y finalidad del cliente en relación con los productos, incluyendo el uso previsto y su rol dentro del sector, como constructor, contratista, revendedor, entre otros
A4: Actor | B4: Action/Command | D4: Read Model | F4: Business Rule/Policy | H4: External System | I4: Domain Event | J4: Hotspot/questions/Risk | K4: Eventos Previos | L4: Comandos Posteriores
A5: Actor | B5: Acción | C5: Descripción | D5: Información externa | F5: Políticas | H5: Sistema Externo | I5: Evento | J5: Aspectos por solucionar
D6: Información | E6: Descripción | F6: Número | G6: Descripción
A7: Administrador/Trabajador | B7: Registrar información interés | C7: Permite agregar el perfil y finalidad de un cliente (rol, uso previsto, actividad, etc.). | D7: Cliente, productos | E7: Información básica del cliente | F7: INF-POL-001 | G7: No permitir duplicados para un mismo cliente. | I7: Información de interés creada | J7: ¿Qué hacer si ya existe para ese cliente? | K7: Cliente registrado | L7: Actualizar información de interés
A8: Administrador/Trabajador | B8: Actualizar información | C8: Modifica datos sobre el uso de productos o el rol del cliente. | D8: Cliente, nueva actividad | E8: Cambios en actividad o uso | F8: INF-POL-002 | G8: Solo se puede actualizar si existe un registro previo. | I8: Información de interés actualizada | J8: ¿Registrar historial de cambios? | K8: Registrar información interés | L8: Consultar información de interés
A9: Administrador/Trabajador | B9: Consultar información | C9: Permite ver la finalidad y actividad principal de cada cliente. | D9: Filtros por cliente | E9: Búsqueda por nombre, documento | F9: INF-POL-003 | G9: Solo trabajadores pueden consultar información sensible. | I9: Información de interés consultada | J9: ¿Mostrar solo información activa? | K9: Registrar/Actualizar información | L9: Ninguno

Sheet Producto
A1: <-Volver al inicio
A2: Objeto de Dominio: | B2: ='Listado Objetos de Dominio'!$A$10 -> Producto
A3: Descripción: | B3: ='Listado Objetos de Dominio'!$B$10 -> Definición de cada artículo que el negocio ofrece a sus clientes.
A4: Actor | B4: Action/Command | D4: Read Model | F4: Business Rule/Policy | H4: External System | I4: Domain Event | J4: Hotspot/questions/Risk | K4: Eventos Previos | L4: Comandos Posteriores
A5: Actor | B5: Acción | C5: Descripción | D5: Información externa | F5: Políticas | H5: Sistema Externo | I5: Evento | J5: Aspectos por solucionar
D6: Información | E6: Descripción | F6: Número | G6: Descripción
A7: Administrador | B7: Crear producto | C7: Permite registrar un nuevo producto disponible en el negocio | D7: Nombre, Unidad de Medida, Precio | E7: Nombre comercial, categoría, unidad (kg, un, m³), estado inicial (Activo), precio base | F7: PROD-POL-001 | G7: Validar que no exista un producto con el mismo nombre y unidad de medida | H7: No | I7: Producto registrado | J7: ¿Qué hacer si hay productos similares con diferencias mínimas? ¿Se puede clonar productos? | K7: Ninguno | L7: Actualizar producto
A8: Administrador | B8: Modificar producto | C8: Permite actualizar atributos del producto como nombre, unidad, categoría o precio | D8: ID del producto, nuevos datos | E8: Cambios permitidos para productos activos | F8: PROD-POL-002 | G8: Solo se permite modificar si no está vinculado a transacciones abiertas | H8: No | I8: Producto actualizado | J8: ¿Qué pasa si el producto ya fue abastecido o vendido? ¿Se deben registrar versiones? | K8: Producto registrado | L8: Actualizar categoria
A9: Administrador | B9: cambiar estado producto | C9: Permite marcar un producto como inactivo o activo para que no sea ofrecido | D9: ID del producto | E9: Permite cambiar el estado a un producto | F9: PROD-POL-003 | H9: No | I9: Estado producto modificado | K9: Producto registrado | L9: Actualizar disponibilidad
A10: Administrador/Trabajador | B10: Consultar producto | C10: Permite visualizar la información detallada de un producto específico | D10: ID del producto | E10: Retorna todos los datos asociados incluyendo historial de cambios | F10: PROD-POL-004 | G10: Solo accesible para usuarios con permisos adecuados | H10: No | I10: Producto consultado | J10: ¿Debe incluir registros históricos de precio y estado? | K10: Producto registrado | L10: Visualizar historial
A11: Administrador/Trabajador | B11: Buscar productos disponibles | C11: Permite visualizar los productos activos disponibles para la venta | D11: Filtros: nombre, categoría, estado | E11: Se listan solo los productos con estado activo | F11: PROD-POL-005 | G11: Filtrar solo productos activos y con stock disponible | H11: No | I11: Productos listados | J11: ¿Qué hacer si no hay stock? ¿Se puede sugerir sustitutos? | K11: Productos activos | L11: Registrar venta

Sheet Estado Producto
A1: <-Volver al inicio
A2: Objeto de Dominio: | B2: ='Listado Objetos de Dominio'!$A$12 -> Estado Producto
A3: Descripción: | B3: ='Listado Objetos de Dominio'!$B$12 -> Corresponde a cada uno de los tipos de estados que puede tener un producto.
A4: Actor | B4: Action/Command | D4: Read Model | F4: Business Rule/Policy | H4: External System | I4: Domain Event | J4: Hotspot/questions/Risk | K4: Eventos Previos | L4: Comandos Posteriores
A5: Actor | B5: Acción | C5: Descripción | D5: Información externa | F5: Políticas | H5: Sistema Externo | I5: Evento | J5: Aspectos por solucionar
D6: Información | E6: Descripción | F6: Número | G6: Descripción
A7: Administrador/Trabajador | B7: Consultar | C7: Permite visualizar el listado de estados de producto. | D7: - | E7: - | F7: ESTPRO-POL-01 | G7: Solo lectura, no permite crear, modificar ni eliminar datos. | I7: Estados consultados | J7: ¿Qué hacer si no existen estados registrados? | K7: - | L7: Ninguno

Sheet Venta
A1: <-Volver al inicio
A2: Objeto de Dominio: | B2: ='Listado Objetos de Dominio'!$A$11 -> Venta
A3: Descripción: | B3: ='Listado Objetos de Dominio'!$B$11 -> Corresponde a la transaccion comercial en la que un cliente adquiere uno o mas productos o servicios a cambio de un pago.
A4: Actor | B4: Action/Command | D4: Read Model | F4: Business Rule/Policy | H4: External System | I4: Domain Event | J4: Hotspot/questions/Risk | K4: Eventos Previos | L4: Comandos Posteriores
A5: Actor | B5: Acción | C5: Descripción | D5: Información externa | F5: Políticas | H5: Sistema Externo | I5: Evento | J5: Aspectos por solucionar
D6: Información | E6: Descripción | F6: Número | G6: Descripción
A7: Administrador/Trabajador | B7: Registrar venta | C7: Crear una nueva venta, asociando cliente (opcional), listado de productos y cantidades, y posible envío. | D7: Cliente, Producto, Inventario, Envío | E7: Cliente a quien se le vende, productos y stock, envío disponible | F7: VTA-POL-001 | G7: No permitir venta si hay productos sin suficiente stock.Si hay envío, validar datos completos. | I7: Venta registrada | J7: ¿Qué pasa si el stock cambia durante el registro?¿Qué datos mínimos del envío se requieren? | K7: Cliente, productos e inventario existen | L7: Registrar pago, Asignar envío, Consultar ventas
A8: Administrador/Trabajador | B8: Consultar ventas | C8: Ver historial de ventas con detalle de productos, cantidades, cliente, pagos y estado del envío. | D8: Cliente, Producto, Envío, Pago | E8: Filtrar por cliente, producto, estado de envío, fechas, etc. | F8: VTA-POL-002 | G8: Solo usuarios autorizados pueden consultar ventas. | I8: Ventas consultadas | J8: ¿Mostrar solo ventas activas o también anuladas? | K8: Venta registrada | L8: Ninguno
A9: Administrador/Trabajador | B9: Modificar venta | C9: Editar datos de una venta pendiente, incluidos productos, cantidades, cliente o envío. | D9: Código de venta, Cliente, Producto, Envío | E9: Identificador de venta, nuevo cliente, productos o envío | F9: VTA-POL-003 | G9: Solo modificar si la venta está pendiente y sin pagos o entrega. | I9: Venta modificada | J9: ¿Cómo actualizar reserva de inventario y estado del envío? | K9: Venta registrada | L9: Consultar ventas
A10: Trabajador | B10: Asignar envío | C10: Asociar o modificar el envío de una venta. | D10: Envío, Código de venta | E10: Identificador de envío, venta | F10: VTA-POL-005 | G10: Solo si el envío está disponible y la venta está pendiente de entrega. | I10: Envío asignado | J10: ¿Qué pasa si el envío ya está finalizado? | K10: Venta registrada | L10: Modificar venta, Consultar ventas

Sheet Envio
A1: <-Volver al inicio
A2: Objeto de Dominio: | B2: ='Listado Objetos de Dominio'!$A$13 -> Envio
A3: Descripción: | B3: ='Listado Objetos de Dominio'!$B$13 -> Entidad que representa el servicio de transportar los productos adquiridos por un cliente hacia un destino.
A4: Actor | B4: Action/Command | D4: Read Model | F4: Business Rule/Policy | H4: External System | I4: Domain Event | J4: Hotspot/questions/Risk | K4: Eventos Previos | L4: Comandos Posteriores
A5: Actor | B5: Acción | C5: Descripción | D5: Información externa | F5: Políticas | H5: Sistema Externo | I5: Evento | J5: Aspectos por solucionar
D6: Información | E6: Descripción | F6: Número | G6: Descripción
A7: Trabajador | B7: Crear envío | C7: Registrar un nuevo envío, asociándolo a una venta, destino y datos del transporte. | D7: Venta, Ciudad | E7: Venta asociada, datos de destino | F7: ENV-POL-001 | G7: Solo se puede crear envío para ventas con estado “pendiente de envío”. Validar que los datos de dirección sean correctos. | I7: Envío creado | K7: Venta registrada | L7: Consultar envío, Actualizar envío
A8: Trabajador | B8: Consultar envío | C8: Ver detalle del envío, incluyendo estado, destino, y productos transportados. | D8: Venta | E8: Identificar productos enviados, estado y trazabilidad | F8: ENV-POL-002 | G8: Solo usuarios autorizados pueden consultar datos de envío. | I8: Envío consultado | K8: Envío creado | L8: Ninguno
A9: Trabajador | B9: Actualizar estado | C9: Cambiar estado del envío (pendiente, entregado, anulado, etc). | D9: Código de envío | E9: Estado nuevo del envío | F9: ENV-POL-003 | G9: Solo estados válidos (no saltar estados) | I9: Estado actualizado | K9: Envío creado, envío consultado | L9: Consultar envío
A10: Trabajador | B10: Anular envío | C10: Cancelar un envío antes de que sea entregado. | D10: Código de envío | E10: Identificador del envío a anular | F10: ENV-POL-004 | G10: Solo envíos en estado “pendiente” pueden anularse.Actualizar venta asociada. | I10: Envío anulado | K10: Envío creado | L10: Consultar envío
A11: Trabajador | B11: Modificar destino | C11: Cambiar la dirección de entrega si el envío aún no ha salido. | D11: Código de envío, nueva ciudad | E11: Nueva dirección de entrega | F11: ENV-POL-005 | G11: Solo si el envío está “pendiente”. | I11: Destino modificado | J11: ¿Validar costos adicionales?¿Registrar motivo del cambio? | K11: Envío creado, envío consultado | L11: Consultar envío, Actualizar estado

Sheet Tipo Identificacion
A1: <-Volver al inicio
A2: Objeto de Dominio: | B2: ='Listado Objetos de Dominio'!$A$14 -> Tipo Identificación
A3: Descripción: | B3: ='Listado Objetos de Dominio'!$B$14 -> Objeto de dominio que representa a cada uno de los tipos de identificación que puede tener un usuario.
A4: Actor | B4: Action/Command | D4: Read Model | F4: Business Rule/Policy | H4: External System | I4: Domain Event | J4: Hotspot/questions/Risk | K4: Eventos Previos | L4: Comandos Posteriores
A5: Actor | B5: Acción | C5: Descripción | D5: Información externa | F5: Políticas | H5: Sistema Externo | I5: Evento | J5: Aspectos por solucionar
D6: Información | E6: Descripción | F6: Número | G6: Descripción
A7: Administrador | B7: Agregar un nuevo tipo identificación. | C7: Permite registrar la información de un nuevo tipo identificación. | F7: Tipo-identificacion-POL-001 | G7: Asegurar que no exista otro tipo identificación con el mismo identificador. | I7: Nuevo tipo identificación registrado. | L7: Eliminar Tipo Identificación
F8: Tipo-identificacion-POL-002 | G8: Asegurar que no exista otro tipo identificación con el mismo nombre.
F9: Tipo-identificacion-POL-003 | G9: Asegurar que los datos requeridos para llevar a cabo la acción sean válidos a nivel de tipo de dato, longitud, obligatoriedad, formato y rango. | L9: Modificar Tipo identificación
A10: Administrador | B10: Modificar un tipo identificación existente. | C10: Permite modificar la sigla y la descripción de un tipo identificación existente. | F10: Tipo-identificacion-POL-003 | G10: Asegurar que los datos requeridos para llevar a cabo la acción de modificación sean válidos a nivel de tipo de dato, longitud, obligatoriedad, formato y rango. | I10: Tipo identificación modificado. | K10: Tipo Identificación agregado | L10: Eliminar Tipo Identificación
L11: Modificar Tipo identificación
A12: Administrador | B12: Eliminar un tipo identificación existente. | C12: Permite eliminar un tipo identificación existente. | F12: Tipo-identificacion-POL-004 | G12: Asegurar que el Tipo Identificación no esté siendo utilizado por otro Objeto. | I12: Tipo identificación eliminado. | K12: Tipo Identificación agregado | L12: Agregar Tipo Identificación

Sheet Estado Usuario
A1: <-Volver al inicio
A2: Objeto de Dominio: | B2: ='Listado Objetos de Dominio'!$A$15 -> Estado Usuario
A3: Descripción: | B3: ='Listado Objetos de Dominio'!$B$15 -> Corresponde a cada uno de los estados que puede tener un Administrador o Trabajador
A4: Actor | B4: Action/Command | D4: Read Model | F4: Business Rule/Policy | H4: External System | I4: Domain Event | J4: Hotspot/questions/Risk | K4: Eventos Previos | L4: Comandos Posteriores
A5: Actor | B5: Acción | C5: Descripción | D5: Información externa | F5: Políticas | H5: Sistema Externo | I5: Evento | J5: Aspectos por solucionar
D6: Información | E6: Descripción | F6: Número | G6: Descripción
A7: Administrador | B7: Consultar | C7: Permite consultar los estados de usuario disponibles | D7: No aplica | E7: No aplica | F7: ESTUSU-001 | G7: Solo consulta, no permite modificaciones | H7: No aplica | I7: Estados de usuario consultados | K7: Ninguno | L7: Ninguno

Sheet Categoria
A1: <-Volver al inicio
A2: Objeto de Dominio: | B2: ='Listado Objetos de Dominio'!$A$16 -> Categoría
A3: Descripción: | B3: ='Listado Objetos de Dominio'!$B$16 -> Categoría mediante la cual se agrupan a los productos según sus características y uso
A4: Actor | B4: Action/Command | D4: Read Model | F4: Business Rule/Policy | H4: External System | I4: Domain Event | J4: Hotspot/questions/Risk | K4: Eventos Previos | L4: Comandos Posteriores
A5: Actor | B5: Acción | C5: Descripción | D5: Información externa | F5: Políticas | H5: Sistema Externo | I5: Evento | J5: Aspectos por solucionar
D6: Información | E6: Descripción | F6: Número | G6: Descripción
A7: Administrador | B7: Crear categoría | C7: Permite registrar una nueva categoría de productos | D7: Nombre categoría | E7: Nombre que agrupa productos por tipo o uso | F7: CAT-POL-001 | G7: No debe existir otra categoría con el mismo nombre | H7: No | I7: Categoría registrada | J7: ¿Debe validarse por nombre exacto o nombre y tipo de productos asociados? | K7: Ninguno | L7: Asociar productos
A8: Administrador | B8: Modificar categoría | C8: Permite modificar el nombre o descripción de una categoría existente | D8: ID categoría, nuevo nombre | E8: Solo si no está asociada a producto | F8: CAT-POL-002 | G8: No permitir modificación si hay productos activos asociados | H8: No | I8: Categoría actualizada | J8: ¿Qué hacer si hay productos asociados? ¿Permitir solo cambios menores como descripción? | K8: Categoría creada | L8: Asociar productos

Sheet Pais
A1: <-Volver al inicio
A2: Objeto de Dominio: | B2: ='Listado Objetos de Dominio'!$A$17 -> País
A3: Descripción: | B3: ='Listado Objetos de Dominio'!$B$17 -> Objeto de dominio que representa a un pais al que pertenecen varios departamentos
A4: Actor | B4: Action/Command | D4: Read Model | F4: Business Rule/Policy | H4: External System | I4: Domain Event | J4: Hotspot/questions/Risk | K4: Eventos Previos | L4: Comandos Posteriores
A5: Actor | B5: Acción | C5: Descripción | D5: Información externa | F5: Políticas | H5: Sistema Externo | I5: Evento | J5: Aspectos por solucionar
D6: Información | E6: Descripción | F6: Número | G6: Descripción
A7: Trabajador/administrador | B7: Consultar | C7: Permite obtener el listado de países registrados. | D7: No aplica | E7: No aplica | F7: PAIS-001 | G7: Solo consulta, no se permite edición. | H7: No aplica | I7: Países consultados | J7: ¿Qué hacer si no hay países cargados? | K7: Ninguno | L7: Ninguno

Sheet Departamento
A1: <-Volver al inicio
A2: Objeto de Dominio: | B2: ='Listado Objetos de Dominio'!$A$18 -> Departamento
A3: Descripción: | B3: ='Listado Objetos de Dominio'!$B$18 -> Objeto de dominio que representa a un departamento al que pertenecen varias ciudades.
A4: Actor | B4: Action/Command | D4: Read Model | F4: Business Rule/Policy | H4: External System | I4: Domain Event | J4: Hotspot/questions/Risk | K4: Eventos Previos | L4: Comandos Posteriores
A5: Actor | B5: Acción | C5: Descripción | D5: Información externa | F5: Políticas | H5: Sistema Externo | I5: Evento | J5: Aspectos por solucionar
D6: Información | E6: Descripción | F6: Número | G6: Descripción
A7: Trabajador/administrador | B7: Consultar | C7: Permite obtener el listado de Departamentos. | D7: No aplica | E7: No aplica | F7: DEPTO-001 | G7: Solo consulta, no se permite edición. | H7: No aplica | I7: Departamentos consultados | J7: ¿Qué hacer si no hay departamentos? | K7: Ninguno | L7: Ninguno

Sheet Ciudad
A1: <-Volver al inicio
A2: Objeto de Dominio: | B2: ='Listado Objetos de Dominio'!$A$19 -> Ciudad
A3: Descripción: | B3: ='Listado Objetos de Dominio'!$B$19 -> Objeto de dominio que representa a cada una de las ciudades
A4: Actor | B4: Action/Command | D4: Read Model | F4: Business Rule/Policy | H4: External System | I4: Domain Event | J4: Hotspot/questions/Risk | K4: Eventos Previos | L4: Comandos Posteriores
A5: Actor | B5: Acción | C5: Descripción | D5: Información externa | F5: Políticas | H5: Sistema Externo | I5: Evento | J5: Aspectos por solucionar
D6: Información | E6: Descripción | F6: Número | G6: Descripción
A7: Trabajador/administrador | B7: Consultar | C7: Permite obtener el listado de ciudades. | D7: No aplica | E7: No aplica | F7: CIUD-001 | G7: Solo consulta, no se permite edición. | H7: No aplica | I7: ciudades consultados | J7: ¿Qué hacer si no hay Municipios Registrados? | K7: Ninguno | L7: Ninguno

Sheet Insumo
A1: <-Volver al inicio
A2: Objeto de Dominio: | B2: ='Listado Objetos de Dominio'!$A$20 -> Insumo
A3: Descripción: | B3: ='Listado Objetos de Dominio'!$B$20 -> Objeto de dominio que representa el producto consumido para una producción
A4: Actor | B4: Action/Command | D4: Read Model | F4: Business Rule/Policy | H4: External System | I4: Domain Event | J4: Hotspot/questions/Risk | K4: Eventos Previos | L4: Comandos Posteriores
A5: Actor | B5: Acción | C5: Descripción | D5: Información externa | F5: Políticas | H5: Sistema Externo | I5: Evento | J5: Aspectos por solucionar
D6: Información | E6: Descripción | F6: Número | G6: Descripción
A7: Administrador/Trabajador | B7: Registrar insumo | C7: Permite registrar un nuevo insumo utilizado en una producción | D7: Producto, Producción | E7: Insumo registrado | F7: INS-POL-001 | G7: No se puede registrar un insumo sin asociarlo a una producción y un producto. | H7: No | I7: Insumo registrado | J7: ¿Qué ocurre si el insumo ya fue registrado para esa producción? | K7: Producción creada | L7: Consultar insumos, Generar reporte
A8: Administrador/Trabajador | B8: Consultar insumos | C8: Permite visualizar los insumos utilizados en una o varias producciones | D8: Filtro por fecha o producción | E8: Listado de insumos utilizados | F8: INS-POL-002 | G8: Solo usuarios autorizados pueden consultar el historial de insumos. | H8: No | I8: Insumos consultados | J8: ¿Cómo se filtra entre insumos activos e históricos? | K8: Insumos registrados | L8: Exportar reporte, Ver inventario
A9: Administrador/Trabajador | B9: Modificar cantidad | C9: Permite modificar la cantidad usada de un insumo registrado | D9: Código de insumo, nueva cantidad | E9: Insumo actualizado | F9: INS-POL-003 | G9: La cantidad debe ser mayor a cero y no puede superar el stock disponible. | H9: No | I9: Insumo actualizado | J9: ¿Puede modificarse si ya fue reflejado en inventario? | K9: Insumo registrado | L9: Consultar insumo

Sheet Unidad de medida
A1: <-Volver al inicio
A2: Objeto de Dominio: | B2: ='Listado Objetos de Dominio'!$A$21 -> Unidad de medida
A3: Descripción: | B3: ='Listado Objetos de Dominio'!$B$21 -> Objeto de dominio que representa cada unidad de medida que puede tener un producto
A4: Actor | B4: Action/Command | D4: Read Model | F4: Business Rule/Policy | H4: External System | I4: Domain Event | J4: Hotspot/questions/Risk | K4: Eventos Previos | L4: Comandos Posteriores
A5: Actor | B5: Acción | C5: Descripción | D5: Información externa | F5: Políticas | H5: Sistema Externo | I5: Evento | J5: Aspectos por solucionar
D6: Información | E6: Descripción | F6: Número | G6: Descripción
A7: Administrador/Trabajador | B7: Consultar | C7: Permite visualizar el listado de unidades de medida. | D7: - | E7: - | F7: UNDMED-POL-01 | G7: Solo lectura, no permite crear, modificar ni eliminar datos. | I7: Unidades consultadas | J7: ¿Qué hacer si no existen unidades registradas? | L7: Ninguno

Sheet Estado Envio
A1: <-Volver al inicio
A2: Objeto de Dominio: | B2: ='Listado Objetos de Dominio'!$A$22 -> Estado Envio
A3: Descripción: | B3: ='Listado Objetos de Dominio'!$B$22 -> Objeto de dominio que representa cada estado de envio de una venta
A4: Actor | B4: Action/Command | D4: Read Model | F4: Business Rule/Policy | H4: External System | I4: Domain Event | J4: Hotspot/questions/Risk | K4: Eventos Previos | L4: Comandos Posteriores
A5: Actor | B5: Acción | C5: Descripción | D5: Información externa | F5: Políticas | H5: Sistema Externo | I5: Evento | J5: Aspectos por solucionar
D6: Información | E6: Descripción | F6: Número | G6: Descripción
A7: Trabajador | B7: Consultar | C7: Permite consultar los estados de envío disponibles. | D7: No aplica | E7: No aplica | F7: ENV-EST-001 | G7: Solo consulta, no se permite modificación. | H7: No aplica | I7: Estados de envío consultados | J7: ¿Qué hacer si no hay estados definidos? | K7: Ninguno | L7: Ninguno

Sheet Pago
A1: <-Volver al inicio
A2: Objeto de Dominio: | B2: ='Listado Objetos de Dominio'!$A$23 -> Pago
A3: Descripción: | B3: ='Listado Objetos de Dominio'!$B$23 -> Objeto de dominio que representa el pago a una venta
A4: Actor | B4: Action/Command | D4: Read Model | F4: Business Rule/Policy | H4: External System | I4: Domain Event | J4: Hotspot/questions/Risk | K4: Eventos Previos | L4: Comandos Posteriores
A5: Actor | B5: Acción | C5: Descripción | D5: Información externa | F5: Políticas | H5: Sistema Externo | I5: Evento | J5: Aspectos por solucionar
D6: Información | E6: Descripción | F6: Número | G6: Descripción
A7: Administrador/Trabajador | B7: Abonar pago | C7: Permite registrar un pago asociado a una venta. | D7: Catálogo de ventas | E7: Listado de ventas activas | F7: PAG-POL-001 | G7: Validar que la venta exista y esté activa. | H7: - | I7: Pago registrado | J7: ¿Qué hacer si la venta está cerrada? | K7: Venta creada | L7: Consultar pago
A8: Administrador/Trabajador | B8: Registrar pago | C8: Permite registrar un pago con diferentes formas de pago (efectivo, tarjeta). | D8: Catálogo formas de pago | E8: Listado de formas de pago permitidas | F8: PAG-POL-002 | G8: No permitir pago con monto <= 0.Validar forma de pago permitida. | H8: - | I8: Pago registrado correctamente | K8: Venta creada | L8: Consultar pago
A9: Administrador/Trabajador | B9: Consultar pago | C9: Permite visualizar los pagos realizados a una venta o consultar históricos. | D9: Catálogo de pagos | E9: Listado histórico de pagos | F9: PAG-POL-003 | G9: Solo mostrar pagos existentes.Filtrar por rango de fechas, cliente, venta. | H9: - | I9: Pagos consultados | J9: ¿Qué hacer si no existen pagos para la venta consultada? | K9: Venta creada
A10: Administrador/Trabajador | B10: Modificar pago | C10: Permite actualizar datos de un pago registrado (monto, forma, etc). | D10: Catálogo de pagos | E10: Listado de pagos | F10: PAG-POL-005 | G10: Solo modificar pagos asociados a ventas abiertas. Registrar motivo de modificación. | H10: - | I10: Pago modificado | K10: Pago registrado | L10: Consultar pago

Sheet Forma de pago
A1: <-Volver al inicio
A2: Objeto de Dominio: | B2: ='Listado Objetos de Dominio'!$A$24 -> Forma de pago
A3: Descripción: | B3: ='Listado Objetos de Dominio'!$B$24 -> Objeto de dominio que representa las diferentes formas de pago
A4: Actor | B4: Action/Command | D4: Read Model | F4: Business Rule/Policy | H4: External System | I4: Domain Event | J4: Hotspot/questions/Risk | K4: Eventos Previos | L4: Comandos Posteriores
A5: Actor | B5: Acción | C5: Descripción | D5: Información externa | F5: Políticas | H5: Sistema Externo | I5: Evento | J5: Aspectos por solucionar
D6: Información | E6: Descripción | F6: Número | G6: Descripción
A7: Administrador/Trabajador | B7: Consultar formas | C7: Permite listar las formas de pago disponibles | D7: - | E7: Devuelve listado ordenado de formas de pago registradas | F7: FP-POL-001 | G7: Formas de pago no deben estar duplicadas | H7: No | I7: Formas de pago consultadas | L7: Asignación forma de pago a un pago

Sheet Estado de venta
A1: <-Volver al inicio
A2: Objeto de Dominio: | B2: ='Listado Objetos de Dominio'!$A$25 -> Estado Venta
A3: Descripción: | B3: ='Listado Objetos de Dominio'!$B$25 -> Objeto de dominio que representa los diferentes Estados de venta
A4: Actor | B4: Action/Command | D4: Read Model | F4: Business Rule/Policy | H4: External System | I4: Domain Event | J4: Hotspot/questions/Risk | K4: Eventos Previos | L4: Comandos Posteriores
A5: Actor | B5: Acción | C5: Descripción | D5: Información externa | F5: Políticas | H5: Sistema Externo | I5: Evento | J5: Aspectos por solucionar
D6: Información | E6: Descripción | F6: Número | G6: Descripción
A7: Administrador/Trabajador | B7: Consultar estado venta | C7: Permite visualizar los diferentes estados posibles de una venta. | D7: Catálogo de estados de venta | E7: Listado de estados | F7: ESTV-POL-001 | G7: Solo mostrar estados válidos. | H7: - | I7: Estados consultados | K7: - | L7: -

Sheet Devolucion
A1: <-Volver al inicio
A2: Objeto de Dominio: | B2: ='Listado Objetos de Dominio'!$A$26 -> Devolución
A3: Descripción: | B3: ='Listado Objetos de Dominio'!$B$26 -> Registra la devolución total o parcial de productos de una Venta, con su motivo,y método de reembolso (si aplica) y el ajuste de inventario correspondiente.
A4: Actor | B4: Action/Command | D4: Read Model | F4: Business Rule/Policy | H4: External System | I4: Domain Event | J4: Hotspot/questions/Risk | K4: Eventos Previos | L4: Comandos Posteriores
A5: Actor | B5: Acción | C5: Descripción | D5: Información externa | F5: Políticas | H5: Sistema Externo | I5: Evento | J5: Aspectos por solucionar
D6: Información | E6: Descripción | F6: Número | G6: Descripción
A7: Administrador/Trabajador | B7: Registrar devolución | C7: Crear una nueva devolución, asociandoVenta, listado de productos y cantidades, | D7: Cliente, Producto, Inventario, Venta | E7: Venta realizada a un cliente | F7: DEV-POL-001 | G7: No permitir devolución los productos a devolver excede la cantidad del producto en la venta | I7: Devolución registrada | J7: ¿Qué pasa cuando se realizan varias devoluciones de una venta ? | K7: Cliente, productos y venta | L7: Actualizar devolución
A8: Administrador/Trabajador | B8: Consultar devolución | C8: Ver historial de devolución con detalle de productos, cantidades, cliente y venta | D8: Cliente, Producto, Venta | E8: Filtrar por cliente y venta | F8: DEV-POL-002 | G8: Solo usuarios autorizados pueden consultar devoluciones. | I8: Devoluciones consultadas | K8: Devolución registrada | L8: Actualizar devolución
A9: Administrador/Trabajador | B9: Modificar venta | C9: Editar datos de una devolución, incluidos productos y cantidade | D9: Código de devolución, Cliente, Producto | E9: Identificador de devolución, cliente y productos | F9: DEV-POL-003 | G9: No permitir devolución los productos a devolver excede la cantidad del producto en la venta | I9: Devolución modificada | K9: Venta registrada, Devolución registrada | L9: NA
